Workbook
Name \0: #REF!
Name \1: #REF!
Name \3: #REF!
Name \4: #REF!
Name \a: #N/A
Name \B: #REF!
Name \B: #REF!
Name \c: #REF!
Name \c: #REF!
Name \c: #REF!
Name \c: #REF!
Name \c: #REF!
Name \c: #REF!
Name \c: #REF!
Name \c: #REF!
Name \c: #REF!
Name \c: #REF!
Name \c: #REF!
Name \d: #N/A
Name \e: #REF!
Name \e: #REF!
Name \e: #REF!
Name \e: #REF!
Name \e: #REF!
Name \e: #REF!
Name \e: #REF!
Name \e: #REF!
Name \e: #REF!
Name \e: #REF!
Name \e: #REF!
Name \f: #N/A
Name \FF: '[1]97 사업추정(WEKI)'!#REF!
Name \FG: [2]손익차총괄2!#REF!
Name \g: #REF!
Name \g: #REF!
Name \j: #REF!
Name \j: #REF!
Name \j: #REF!
Name \j: #REF!
Name \j: #REF!
Name \j: #REF!
Name \j: #REF!
Name \j: #REF!
Name \j: #REF!
Name \j: #REF!
Name \j: #REF!
Name \LL: #REF!
Name \M: #REF!
Name \n: #REF!
Name \n: #REF!
Name \n: #REF!
Name \n: #REF!
Name \n: #REF!
Name \n: #REF!
Name \n: #REF!
Name \n: #REF!
Name \n: #REF!
Name \n: #REF!
Name \n: #REF!
Name \o: #REF!

Sheet SZ Abstract (2)
A1: Abstract of SZ Plants | J1: District Wise Cost | M1: Division Wise Cost | R1: Rehab & O&M Cost
A2: Sr, No | B2: Division | C2: District | D2: Total No of Plants | E2: Functional | F2: Dys Fun + Abundand + Partly Functional | G2: Partly Fun | H2: Dys Fun | J2: Cost of Rehab Plants | K2: 1 Year O&M Cost of all Plants | L2: 3 Year O&M Cost of all Plants | M2: Divisions | N2: Total Cost | O2: 1 Year O&M Cost of all Plants | P2: 3 Year O&M Cost of all Plants | R2: 1 Year O&M Cost Rehab of all Plants | S2: 3 Year O&M Cost of all Plants
A3: 1 | B3: Multan | C3: Vehari | D3: 146 | E3: 135 | F3: 11 | G3: 0 | H3: 11 | J3: =D16*F3 -> #REF! | K3: =D18*D3 -> #REF! | L3: =D20*D3 -> #REF! | M3: Multan | N3: =SUM(J3:J6) -> #REF! | O3: =SUM(K3:K6) -> #REF! | P3: =SUM(L3:L6) -> #REF! | R3: =O3+N3 -> #REF! | S3: =P3+N3 -> #REF!
A4: 2 | C4: Lodhran | D4: 82 | E4: 64 | F4: 18 | G4: 2 | H4: 16 | J4: =D16*F4 -> #REF! | K4: =D18*D4 -> #REF! | L4: =D20*D4 -> #REF!
A5: 3 | C5: Khanewal | D5: 177 | E5: 157 | F5: 20 | G5: 1 | H5: 19 | J5: =D16*F5 -> #REF! | K5: =D18*D5 -> #REF! | L5: =D20*D5 -> #REF!
A6: 4 | C6: Multan | D6: 396 | E6: 273 | F6: 123 | G6: 29 | H6: 94 | J6: =D16*F6 -> #REF! | K6: =D18*D6 -> #REF! | L6: =D20*D6 -> #REF!
A7: 5 | B7: Bahawalpur | C7: Bahawalpur | D7: 190 | E7: 143 | F7: 47 | G7: 3 | H7: 44 | J7: =D16*F7 -> #REF! | K7: =D18*D7 -> #REF! | L7: =D20*D7 -> #REF! | M7: Bahawalpur | N7: =SUM(J7:J9) -> #REF! | O7: =SUM(K7:K9) -> #REF! | P7: =SUM(L7:L9) -> #REF! | R7: =O7+N7 -> #REF! | S7: =P7+N7 -> #REF!
A8: 6 | C8: Bahawalnagar | D8: 119 | E8: 98 | F8: 21 | G8: 0 | H8: 21 | J8: =D16*F8 -> #REF! | K8: =D18*D8 -> #REF! | L8: =D20*D8 -> #REF!
A9: 7 | C9: Rahimyar khan | D9: 203 | E9: 152 | F9: 51 | G9: 0 | H9: 51 | J9: =D16*F9 -> #REF! | K9: =D18*D9 -> #REF! | L9: =D20*D9 -> #REF!
A10: 8 | B10: DG Khan | C10: DG Khan | D10: 163 | E10: 63 | F10: 100 | G10: 16 | H10: 84 | J10: =D16*F10 -> #REF! | K10: =D18*D10 -> #REF! | L10: =D20*D10 -> #REF! | M10: DG Khan | N10: =SUM(J10:J13) -> #REF! | O10: =SUM(K10:K13) -> #REF! | P10: =SUM(L10:L13) -> #REF! | R10: =O10+N10 -> #REF! | S10: =P10+N10 -> #REF!
A11: 9 | C11: Rajanpur | D11: 63 | E11: 26 | F11: 37 | G11: 1 | H11: 36 | J11: =D16*F11 -> #REF! | K11: =D18*D11 -> #REF! | L11: =D20*D11 -> #REF!
A12: 10 | C12: Layyah | D12: 33 | E12: 14 | F12: 19 | G12: 14 | H12: 5 | J12: =D16*F12 -> #REF! | K12: =D18*D12 -> #REF! | L12: =D20*D12 -> #REF!
A13: 11 | C13: Muzafargarha | D13: 129 | E13: 22 | F13: 107 | G13: 42 | H13: 65 | J13: =D16*F13 -> #REF! | K13: =D18*D13 -> #REF! | L13: =D20*D13 -> #REF!
A14: Total # of Plants | D14: =SUM(D3:D13) -> 1701 | E14: =SUM(E3:E13) -> 1147 | F14: =SUM(F3:F13) -> 554 | G14: =SUM(G3:G13) -> 108 | H14: =SUM(H3:H13) -> 446 | J14: =SUM(J3:J13) -> #REF! | K14: =SUM(K3:K13) -> #REF! | L14: =SUM(L3:L13) -> #REF! | M14: Total | N14: =SUM(N3:N13) -> #REF! | O14: =SUM(O3:O13) -> #REF! | P14: =SUM(P3:P13) -> #REF! | R14: =SUM(R3:R13) -> #REF! | S14: =SUM(S3:S13) -> #REF!
A16: Average Rehab Cost of Plant | D16: =GS!#REF! -> #REF! | F16: Total Rehabilitaion Cost of 554 Plant | M16: =J14 -> #REF!
A18: Average O&M Cost of Plant for 1 Year | D18: ='SZ Abstract'!D18 -> #REF! | F18: Total Cost rehab + O&M of 1 Year for Total 1701 Plants | M18: =J14+K14 -> #REF!
A20: Average O&M Cost of Plant for 3 Year | D20: =D18*3 -> #REF! | F20: Total Cost rehab + O&M of 3 Year for Total 1701 Plants | M20: =J14+L14 -> #REF!
E27: =D16*(1782-542) -> #REF! | F27: =D18*(5179-542) -> #REF! | K27: =F27+E27 -> #REF!

Sheet SZ Abstract
A1: Abstract of SZ Plants | J1: District Wise Cost | M1: Division Wise Cost
A2: Sr, No | B2: Division | C2: District | D2: Total No of Plants | E2: Functional | F2: Dys Fun + Abundand + Partly Functional | G2: Partly Fun | H2: Dys Fun | J2: Cost of Rehab Plants | K2: 1 Year O&M Cost of all Plants | L2: 3 Year O&M Cost of all Plants | M2: Divisions | N2: Total Cost | O2: 1 Year O&M Cost of all Plants | P2: 3 Year O&M Cost of all Plants
A3: 1 | B3: Multan | C3: Vehari | D3: 146 | E3: 135 | F3: 11 | G3: 0 | H3: 11 | J3: =D16*F3 -> #REF! | K3: =D18*D3 -> #REF! | L3: =D20*D3 -> #REF! | M3: Multan | N3: =SUM(J3:J6) -> #REF! | O3: =SUM(K3:K6) -> #REF! | P3: =SUM(L3:L6) -> #REF!
A4: 2 | C4: Lodhran | D4: 82 | E4: 64 | F4: 18 | G4: 2 | H4: 16 | J4: =D16*F4 -> #REF! | K4: =D18*D4 -> #REF! | L4: =D20*D4 -> #REF!
A5: 3 | C5: Khanewal | D5: 177 | E5: 157 | F5: 20 | G5: 1 | H5: 19 | J5: =D16*F5 -> #REF! | K5: =D18*D5 -> #REF! | L5: =D20*D5 -> #REF!
A6: 4 | C6: Multan | D6: 396 | E6: 273 | F6: 123 | G6: 29 | H6: 94 | J6: =D16*F6 -> #REF! | K6: =D18*D6 -> #REF! | L6: =D20*D6 -> #REF!
A7: 5 | B7: Bahawalpur | C7: Bahawalpur | D7: 190 | E7: 143 | F7: 47 | G7: 3 | H7: 44 | J7: =D16*F7 -> #REF! | K7: =D18*D7 -> #REF! | L7: =D20*D7 -> #REF! | M7: Bahawalpur | N7: =SUM(J7:J9) -> #REF! | O7: =SUM(K7:K9) -> #REF! | P7: =SUM(L7:L9) -> #REF!
A8: 6 | C8: Bahawalnagar | D8: 119 | E8: 98 | F8: 21 | G8: 0 | H8: 21 | J8: =D16*F8 -> #REF! | K8: =D18*D8 -> #REF! | L8: =D20*D8 -> #REF!
A9: 7 | C9: Rahimyar khan | D9: 203 | E9: 152 | F9: 51 | G9: 0 | H9: 51 | J9: =D16*F9 -> #REF! | K9: =D18*D9 -> #REF! | L9: =D20*D9 -> #REF!
A10: 8 | B10: DG Khan | C10: DG Khan | D10: 163 | E10: 63 | F10: 100 | G10: 16 | H10: 84 | J10: =D16*F10 -> #REF! | K10: =D18*D10 -> #REF! | L10: =D20*D10 -> #REF! | M10: DG Khan | N10: =SUM(J10:J13) -> #REF! | O10: =SUM(K10:K13) -> #REF! | P10: =SUM(L10:L13) -> #REF!
A11: 9 | C11: Rajanpur | D11: 63 | E11: 26 | F11: 37 | G11: 1 | H11: 36 | J11: =D16*F11 -> #REF! | K11: =D18*D11 -> #REF! | L11: =D20*D11 -> #REF!
A12: 10 | C12: Layyah | D12: 33 | E12: 14 | F12: 19 | G12: 14 | H12: 5 | J12: =D16*F12 -> #REF! | K12: =D18*D12 -> #REF! | L12: =D20*D12 -> #REF!
A13: 11 | C13: Muzafargarha | D13: 129 | E13: 22 | F13: 107 | G13: 42 | H13: 65 | J13: =D16*F13 -> #REF! | K13: =D18*D13 -> #REF! | L13: =D20*D13 -> #REF!
A14: Total # of Plants | D14: =SUM(D3:D13) -> 1701 | E14: =SUM(E3:E13) -> 1147 | F14: =SUM(F3:F13) -> 554 | G14: =SUM(G3:G13) -> 108 | H14: =SUM(H3:H13) -> 446 | J14: =SUM(J3:J13) -> #REF! | K14: =SUM(K3:K13) -> #REF! | L14: =SUM(L3:L13) -> #REF! | M14: Total | N14: =SUM(N3:N13) -> #REF! | O14: =SUM(O3:O13) -> #REF! | P14: =SUM(P3:P13) -> #REF!
A16: Average Rehab Cost of Plant | D16: =Abstract!E29 -> #REF! | F16: Total Rehabilitaion Cost of 554 Plant | M16: =J14 -> #REF!
A18: Average O&M Cost of Plant for 1 Year | D18: ='O&M Abs 06 Months'!#REF! -> #REF! | F18: Total Cost rehab + O&M of 1 Year for Total 1701 Plants | M18: =J14+K14 -> #REF! | P18: 1518
A20: Average O&M Cost of Plant for 3 Year | D20: =D18*3 -> #REF! | F20: Total Cost rehab + O&M of 3 Year for Total 1701 Plants | M20: =J14+L14 -> #REF!

Sheet One Pager
A1: PUNJAB SAAF PANI AUTHORITY
A2: REHABILITATION & O&M OF DYSFUNCTIONAL WATER FILTRATION PLANTS INSTALLED BY MCL IN LAHORE
A4: ENGINEERING COST ESTIMATE
A5: Bill No | B5: Description | C5: Qty | D5: Unit Rate (Rs.) | E5: Amount (Rs.) | I5: Total no of Plants
A6: 1 | B6: Rehabilitation of Reverse Osmosis 500 LPH | C6: 4 | D6: ='R5'!#REF! -> #REF! | E6: =D6*C6 -> #REF! | F6: 6
A7: =A6+1 -> 2 | B7: Rehabilitation of Media Filtration 2000 LPH | C7: 20 | D7: =#REF! -> #REF! | E7: =D7*C7 -> #REF! | F7: 21
A8: =A7+1 -> 3 | B8: Rehabilitation of Ultra Filtration 4000 LPH | C8: 29 | D8: ='U4'!#REF! -> #REF! | E8: =D8*C8 -> #REF! | F8: 14 | G8: Functional Plants Included
A9: =A8+1 -> 4 | B9: Rehabilitation of Ultra Filtration 2000 LPH | C9: 2 | D9: ='U2'!#REF! -> #REF! | E9: =D9*C9 -> #REF! | H9: =(SUM(D6:D10)/5) -> #REF!
A10: =A9+1 -> 5 | B10: Rehabilitation of Ultra Filtration 1000 LPH | C10: 3 | D10: ='UF 1 Rehab'!G39 -> 0 | E10: =C10*D10 -> 0 | G10: =1025000*59 -> 60475000
A11: =A10+1 -> 6 | B11: Installation of Ultra Filtration 4000 LPH | C11: 4 | D11: 3663400 | E11: =C11*D11 -> 14653600
A12: =A11+1 -> 7 | B12: Installation of Reverese Osmosis 2000 LPH | C12: 1 | D12: 2831355 | E12: =C12*D12 -> 2831355
A13: =A12+1 -> 8 | B13: New Bore Holes | C13: =34*70% -> 23.8 | D13: =#REF! -> #REF! | E13: =D13*C13 -> #REF! | I13: =E27 -> 0
A14: =A13+1 -> 9 | B14: Washing of Bore Holes | C14: =30*85% -> 25.5 | D14: =WB!F7 -> 0 | E14: =D14*C14 -> 0
A15: =A14+1 -> 10 | B15: Rehabilitation of Pre Fab Work | C15: =49*65% -> 31.85 | D15: 100000 | E15: =D15*C15 -> 3185000
A16: =A15+1 -> 11 | B16: Rehabilitation of Civil Work | C16: 6 | D16: ='B8 Civil'!N54 -> 71461.12 | E16: =D16*C16 -> 428766.72
A17: =A16+1 -> 12 | B17: Water Analysis Reports | C17: 126 | D17: ='Rate Analysis'!F434 -> 5100 | E17: =D17*C17 -> 642600 | H17: Des | I17: Rehab | J17: Abnd | K17: Total Dist Plants | L17: Fun | P17: 43 | Q17: No of Plants | S17: 190
A18: Total: - | E18: =SUM(E6:E17) -> #REF! | H18: RO 500 LPH | I18: 0 | J18: 0 | P18: RO
A19: 6 Months O&M for 63 No. MCL Plants in Lahore Disctrict | E19: =SUM('O&M Abs 06 Months'!G35)*116% -> 21822102
B20: Total Capital Cost | E20: =E18 -> #REF! | H20: RO 1000 LPH | I20: 27 | J20: 2 | L20: 5 | M20: Per Plant Avg | N20: 150000 | P20: =SUM(I18:J22) -> 30 | Q20: RO | R20: 500 LPH | S20: 14
B21: Add 5% PRA | E21: =E20*5% -> #REF! | H21: RO 2000 LPH | I21: 0 | J21: 1 | L21: 0 | P21: UF | Q21: RO | R21: 1000 LPH | S21: 64
B22: Contingencies & Petty Charges 2% | E22: =E20*2% -> #REF! | M22: Total | N22: =N20*I28 -> 9000000 | P22: =SUM(I24:J26) -> 41 | Q22: RO | R22: 2000 LPH | S22: 68
B23: Resident Supervision 1.5% | E23: =E20*1.5% -> #REF!
B24: Electricity Charges & New Electricity Connections / Outstanding Bills | E24: =GA!E11 -> 33708000 | H24: UF 1000 LPH | I24: 0 | P24: MF | Q24: RO | R24: 4000 LPH | S24: 8
B25: Grand Total | E25: =SUM(E19:E24) -> #REF! | H25: UF 2000 LPH | I25: 33 | J25: 8 | L25: 5 | P25: =SUM(I27:J27) -> 0 | Q25: UF | R25: 1000 LPH | S25: 5
Q26: UF | R26: 2000 LPH | S26: 21
A28: Deputy Manager (P&MC) - CZ | C28: Director Planning | H28: Total | I28: =SUM(I18:I27) -> 60 | J28: =SUM(J18:J27) -> 11 | L28: =SUM(L18:L27) -> 10 | Q28: MF | R28: 1000 LPH
A29: Punjab Saaf Pani Authroity | C29: Punjab Saaf Pani Authroity | Q29: MF | R29: 2000 LPH | S29: 9
H30: Total | I30: =I28+J28 -> 71 | Q30: MF | R30: 4000 LPH
A31: Chief Engineer /DG Projects | H31: Functional | I31: =L28 -> 10 | Q31: No of Plants | S31: =SUM(S20:S30) -> 189
A32: Punjab Saaf Pani Authroity | H32: Total Plants | I32: =I31+I30 -> 81
I36: 80 Plants | J36: =E26 -> 0 | K36: =J36/1000000 -> 0
I37: 82 Plants | J37: ='[71]Abstract 2'!$E$22 -> 86073636 | K37: =J37/1000000 -> 86.073636
I38: Total | J38: =SUM(J36:J37) -> 86073636 | K38: =J38/1000000 -> 86.073636
I39: in millions | J39: =J38/1000000 -> 86.073636
I41: Total | J41: 206
I42: Already Estimated | J42: 80
I43: Lost | J43: 10
I44: Rehab by WASA | J44: 34
J45: =J41-J42-J43-J44 -> 82
I193: s
E203: 24900
E213: 35300
A221: RO Feed Pump Repair 4000 LPH
B223: Repair & maintenance of RO Feed water pump 8000 LPH, for 4000 LPH RO Plant, complete in all respect | E223: 46700
E233: 23950
E243: 36100
E253: 44900
A261: RO High Pressure Pump Repair 4000 LPH
B263: Repair & maintenance of RO High Pressure pump 8000 LPH, for 4000 LPH RO Plant, complete in all respect | E263: 56700

Sheet Gen Abstract 6 Months
A1: PUNJAB SAAF PANI AUTHORITY
A2: REHABILITATION & O&M OF DYSFUNCTIONAL WATER FILTRATION PLANTS INSTALLED BY MCL IN LAHORE
A4: ENGINEERING COST ESTIMATE
A5: No | B5: Description | E5: Amount (Rs.) in Million | H5: Total no of Plants
A6: 1 | B6: REHABILITATION OF DYSFUNCTIONAL WATER FILTRATION PLANTS INSTALLED BY MCL IN LAHORE | E6: =GS!E26 -> 0 | F6: =D6*28 -> 0 | G6: 18 | H6: RO | I6: =SUM(H7:I10) -> 23 | J6: =SUM(K7:K9) -> 11 | K6: =SUM(I6:J6) -> 34
B7: Total Capital Cost | E7: =E6 -> 0
B8: Add 5% PRA | E8: =E7*5% -> 0
B9: Contingencies & Petty Charges 2% | E9: =E6*2% -> 0 | G9: RO 2000 LPH | H9: 19 | I9: 4 | K9: 11 | O9: UF | P9: RO | Q9: 1000 LPH | R9: 64
B10: Resident Supervision 1.5% | E10: =E6*1.5% -> 0 | L10: Total | M10: =#REF!*H17 -> #REF! | O10: =SUM(H13:I15) -> 9 | P10: RO | Q10: 2000 LPH | R10: 68
B11: Electricity Charges & New Electricity Connections / Outstanding Bills | E11: =SUM('Electricity Charges 06 Months'!D6:F6) -> 13175000
B12: 6 Months O&M for MCL Plants including 16% PRA | E12: =SUM('O&M Abs 06 Months'!G35)*116% -> 21822102
B13: Grand Total | E13: =SUM(E7:E12) -> 34997102 | F13: =E13-#REF! -> #REF! | G13: UF 1000 LPH | H13: 9 | O13: MF | P13: RO | Q13: 4000 LPH | R13: 8
F14: =#REF!/70 -> #REF!
C15: Assistant Manager (P&MC) - CZ | P15: UF | Q15: 2000 LPH | R15: 21
F16: =108.47+#REF! -> #REF! | G16: MF 2000 LPH | P16: UF | Q16: 4000 LPH | R16: 1
G17: Total | H17: =SUM(H7:H16) -> 28 | I17: =SUM(I7:I16) -> 4 | K17: =SUM(K7:K16) -> 11 | P17: MF | Q17: 1000 LPH
P18: MF | Q18: 2000 LPH | R18: 9
A19: Deputy Manager (P&MC) - CZ | C19: Director Planning | G19: Total | H19: =H17+I17 -> 32 | P19: MF | Q19: 4000 LPH
G20: Functional | H20: =K17 -> 11 | P20: No of Plants | R20: =SUM(R9:R19) -> 171
G21: Total Plants | H21: =H20+H19 -> 43
A25: Chief Engineer/ D.G (O&M) | H25: 80 Plants | I25: =E15 -> 0 | J25: =I25/1000000 -> 0
H26: 82 Plants | I26: ='[71]Abstract 2'!$E$22 -> 86073636 | J26: =I26/1000000 -> 86.073636
H27: Total | I27: =SUM(I25:I26) -> 86073636 | J27: =I27/1000000 -> 86.073636
H30: in millions | I30: =I27/1000000 -> 86.073636
H32: Total | I32: 206
H33: Already Estimated | I33: 80
H34: Lost | I34: 10
H35: Rehab by WASA | I35: 34
I36: =I32-I33-I34-I35 -> 82
H184: s
E194: 24900
E204: 35300
A212: RO Feed Pump Repair 4000 LPH
B214: Repair & maintenance of RO Feed water pump 8000 LPH, for 4000 LPH RO Plant, complete in all respect | E214: 46700
E224: 23950
E234: 36100
E244: 44900
A252: RO High Pressure Pump Repair 4000 LPH
B254: Repair & maintenance of RO High Pressure pump 8000 LPH, for 4000 LPH RO Plant, complete in all respect | E254: 56700

Sheet GA
A1: PUNJAB SAAF PANI AUTHORITY
A2: REHABILITATION & O&M OF DYSFUNCTIONAL WATER FILTRATION PLANTS INSTALLED IN DIVISON FAISALABAD
A4: ENGINEERING COST ESTIMATE
A5: No | B5: Description | E5: Amount (Rs.) in Million
A6: 1 | B6: =A2 -> REHABILITATION & O&M OF DYSFUNCTIONAL WATER FILTRATION PLANTS INSTALLED IN DIVISON FAISALABAD | E6: =GS!E26 -> 0 | F6: =D6*28 -> 0
B7: Total Capital Cost | E7: =E6 -> 0
B8: Add 5% PRA | E8: =E7*5% -> 0 | F8: =E7+E8+E12 -> 0
B9: Contingencies & Petty Charges 2% | E9: =E6*2% -> 0 | F9: =F8*2% -> 0
B10: Resident Supervision 1.5% | E10: =E6*1.5% -> 0
B11: Electricity Charges & New Electricity Connections / Outstanding Bills | E11: ='EC 06'!D5+'EC 06'!E5+'EC 06'!F5 -> 33708000
B12: O&M for WFP Plants including 16% PRA | E12: ='O&M 06'!G43*116% -> 0
B13: Grand Total | E13: =SUM(E7:E12) -> 33708000
C15: Assistant Manager (P&MC) - CZ
C16: Punjab Saaf Pani Authority
A19: Deputy Manager (P&MC) - CZ | C19: Director (P&QC) CZ
A20: Punjab Saaf Pani Authority | C20: Punjab Saaf Pani Authority
E192: 24900
E202: 35300
A210: RO Feed Pump Repair 4000 LPH
B212: Repair & maintenance of RO Feed water pump 8000 LPH, for 4000 LPH RO Plant, complete in all respect | E212: 46700
E222: 23950
E232: 36100
E242: 44900
A250: RO High Pressure Pump Repair 4000 LPH
B252: Repair & maintenance of RO High Pressure pump 8000 LPH, for 4000 LPH RO Plant, complete in all respect | E252: 56700

Sheet GS
A1: PUNJAB SAAF PANI AUTHORITY
A2: =GA!A2 -> REHABILITATION & O&M OF DYSFUNCTIONAL WATER FILTRATION PLANTS INSTALLED IN DIVISON FAISALABAD
A4: BILL OF QUANTITY
A5: Bill No | B5: Description | C5: Qty | D5: Unit Rate (Rs.) | E5: Amount (Rs.)
A6: 1 | B6: Rehabilitation of Reverse Osmosis 500 LPH | C6: 1 | F6: 152 | G6: =39+58+55 -> 152
A7: 2 | B7: Rehabilitation of Reverse Osmosis 1000 LPH | C7: =41+6+3 -> 50
A8: 3 | B8: Rehabilitation of Reverse Osmosis 2000 LPH | C8: =45+2+1 -> 48
A9: 4 | B9: Rehabilitation of Ultra Filtration 4000 LPH | C9: 9
A10: 5 | B10: Rehabilitation of Ultra Filtration 2000 LPH | C10: =2+1 -> 3
A11: 6 | B11: Rehabilitation of Ultra Filtration 1000 LPH | C11: =3+4 -> 7
A12: 7 | B12: Installation of Ultra Filtration 2000 LPH | C12: 1
A13: 8 | B13: Installation of Reverse Osmosis 500 LPH | C13: 4
A14: 9 | B14: Installation of Reverse Osmosis 2000 LPH | C14: 9
A15: 10 | B15: Installation of Reverse Osmosis 1000 LPH | C15: 6
A16: 11 | B16: New Bore Holes | C16: 60
A17: 12 | B17: Development of Bore Hole | C17: 40
A18: 13 | B18: Injection Well | C18: 12
A19: 14 | B19: Rehabilitation of Pre Fab Work (Faisalabad) | C19: 12
A20: 15 | B20: Rehabilitation of Civil Work (Faisalabad) | C20: 96
A21: 16 | B21: Rehabilitation of Civil Work (Chiniot) | C21: 4
A22: 17 | B22: Rehabilitation of Civil Work (Jhang) | C22: 19
A23: 18 | B23: Rehabilitation of Civil Work (Toba Tek Singh) | C23: 2
... A25: 20 | B25: Water Analysis Reports | C25: 138
A26: Sub Total
A27: Add 5% PRA
A28: Sub Total (A) (Sub Total + 5% PRA)
A29: 06 months O&M for WFP Plants excluding Electricity Charges
A30: Sub Total (B) (06 months O&M)
A31: Add 16% PRA on Sub Total (B)
A32: Sub Total (C) (Sub Total B + 16% PRA)
A33: Grand Total (A+B+C)
E207: 24900
E217: 35300
A225: RO Feed Pump Repair 4000 LPH
B227: Repair & maintenance of RO Feed water pump 8000 LPH, for 4000 LPH RO Plant, complete in all respect | E227: 46700
E237: 23950
E247: 36100
E257: 44900
A265: RO High Pressure Pump Repair 4000 LPH
B267: Repair & maintenance of RO High Pressure pump 8000 LPH, for 4000 LPH RO Plant, complete in all respect | E267: 56700

Sheet Abstract
A1: PUNJAB AAB-E-PAK AUTHORITY
A2: REHABILITATION OF WATER FILTRATION PLANTS IN DISTRICT BAHAWALPUR
A4: Rough Cost Estimate for 47 Dysfunctional & 143 functional Plants: Total 190 Plants
A5: Sr. No | B5: Description | C5: Qty | D5: Per Unit | E5: Amount (Rs.) | H5: Total no of Plants
A6: 1 | B6: ='RO Rehab 500LPH'!A3 -> REHABLITATION OF RO PLANT 500 LPH | C6: =H21 -> 0 | D6: =E6/C6 -> #REF! | E6: ='RO Rehab 500LPH'!G42 -> #REF!
A7: 2 | B7: ='R5'!#REF! -> #REF! | C7: =H22 -> 20 | D7: =E7/C7 -> #REF! | E7: ='R5'!#REF! -> #REF! | H7: RO | I7: =SUM(H21:I24) -> 31
A8: 3 | B8: ='Bill No 2 RO 2000 Rehab'!A3 -> LAHORE DISTRICT | C8: =H23 -> 7 | D8: =E8/C8 -> #REF! | E8: ='Bill No 2 RO 2000 Rehab'!G44 -> #REF!
A9: 4 | B9: ='Bill No 3 UF 1000 Rehab'!A3 -> LAHORE DISTRICT | C9: =H25 -> 3 | D9: =E9/C9 -> #REF! | E9: ='Bill No 3 UF 1000 Rehab'!G41 -> #REF! | H9: UF | I9: =SUM(H25:I27) -> 41 | N9: =600/185 -> 3.2432432
A10: 5 | B10: ='U2'!#REF! -> #REF! | C10: =H26 -> 33 | D10: =E10/C10 -> #REF! | E10: ='U2'!#REF! -> #REF! | H10: MF | I10: =H28 -> 0
A11: 6 | B11: ='New RO500'!A2 -> INSTALATION OF RO 500 LPH WFP | C11: =I21 -> 0 | D11: ='New RO500'!F7 -> 1258666.5 | E11: =D11*C11 -> 0
A12: 7 | B12: ='Bill no 3 RO 1000 New'!A2 -> LAHORE DISTRICT | C12: =I22 -> 3 | D12: ='Bill no 3 RO 1000 New'!#REF! -> #REF! | E12: =D12*C12 -> #REF!
A13: 8 | B13: ='Bill No 4 RO 2000 New'!#REF! -> #REF! | C13: =I23 -> 1 | D13: ='Bill No 4 RO 2000 New'!#REF! -> #REF! | E13: =D13*C13 -> #REF!
A14: 9 | B14: ='Bill No 5 UF 2000 New'!#REF! -> #REF! | C14: =I26 -> 5 | D14: ='Bill No 5 UF 2000 New'!#REF! -> #REF! | E14: =D14*C14 -> #REF!
A15: 10 | B15: ='NEW MF 2000'!A2 -> INSTALATION OF MF 2000 LPH WFP | C15: =I28 -> 0 | D15: ='NEW MF 2000'!F7 -> 669243.75 | E15: =D15*C15 -> 0
A16: 11 | B16: New Bore Holes | C16: =H31*10% -> 7.2 | D16: =#REF! -> #REF! | E16: =D16*C16 -> #REF!
A17: 12 | B17: =WB!A4 -> Bill No 12:Development of Bore Holes | C17: =H31*10% -> 7.2 | D17: =WB!#REF! -> #REF! | E17: =D17*C17 -> #REF!
A18: 13 | B18: Repair of Civil Work | C18: =H31*30% -> 21.6 | D18: ='B8 Civil'!N54 -> 71461.12 | E18: =D18*C18 -> 1543560.2 | I18: =E21-F21 -> #REF!
A19: 14 | B19: Injection Well for Brine | C19: =SUM(H21:H23)*10% -> 2.7 | D19: ='Injection well'!G27 -> 0 | E19: =D19*C19 -> 0
A20: 15 | B20: Water Analysis Reports | C20: =2*H31 -> 144 | D20: ='Rate Analysis'!F434 -> 5100 | E20: =D20*C20 -> 734400 | G20: Des | H20: Rehab | I20: Abnd | J20: Total Dist Plants | L20: Outstanding Electricity Charges | O20: 43 | P20: No of Plants | R20: 190
A21: Total: - | E21: =SUM(E6:E20) -> #REF! | F21: =GS!E26 -> 0 | G21: RO 500 LPH | H21: 0 | I21: 0 | O21: RO
B22: Contingencies & Petty Charges 2% | E22: =F21*2% -> 0 | G22: RO 1000 LPH | H22: 20 | I22: 3 | L22: Per Plant Avg | M22: 150000 | O22: =SUM(H21:I24) -> 31 | P22: RO | Q22: 500 LPH | R22: 14
B23: Design & Resident Supervision 3% | E23: =F21*3% -> 0 | G23: RO 2000 LPH | H23: 7 | I23: 1 | O23: UF | P23: RO | Q23: 1000 LPH | R23: 64
B24: Electricity Charges | E24: {='O&M Abs 06 Months'!#REF!} -> #REF! | F24: #REF! | G24: #REF! | L24: Total | M24: =M22*H29 -> 9450000 | O24: =SUM(H25:I27) -> 41 | P24: RO | Q24: 2000 LPH | R24: 68
B25: O&M for 1 Year of 190 Plants in Bahawalpur District | E25: ='O&M Analysis'!C77 -> 1.163771e+08 | G25: UF 1000 LPH | H25: 3 | O25: MF | P25: RO | Q25: 4000 LPH | R25: 8
B26: Grand Total | E26: =SUM(E21:E25) -> #REF! | G26: UF 2000 LPH | H26: 33 | I26: 5 | O26: =SUM(H28:I28) -> 0 | P26: UF | Q26: 1000 LPH | R26: 5
B27: Say in million | E27: =E26/1000000 -> #REF! | P27: UF | Q27: 2000 LPH | R27: 21
G28: MF 2000 LPH | P28: UF | Q28: 4000 LPH | R28: 1
A29: Per Plant Value | E29: =E27/H33 -> #REF! | G29: Total | H29: =SUM(H21:H28) -> 63 | I29: =SUM(I21:I28) -> 9 | P29: MF | Q29: 1000 LPH
P30: MF | Q30: 2000 LPH | R30: 9
G31: Total Dysfun | H31: =H29+I29 -> 72 | P31: MF | Q31: 4000 LPH
F32: {=SUM(E22:E23+F21)} -> 0 | G32: Functional | H32: 8 | P32: No of Plants | R32: =SUM(R22:R31) -> 190
F33: =F32/H31 -> 0 | G33: Total Plants | H33: =H32+H31 -> 80
E34: =(E21/43)/1000000 -> #REF! | F34: =F33/1000000 -> 0
H193: s
E203: 24900
E213: 35300
A221: RO Feed Pump Repair 4000 LPH
B223: Repair & maintenance of RO Feed water pump 8000 LPH, for 4000 LPH RO Plant, complete in all respect | E223: 46700
E233: 23950
E243: 36100
E253: 44900
A261: RO High Pressure Pump Repair 4000 LPH
B263: Repair & maintenance of RO High Pressure pump 8000 LPH, for 4000 LPH RO Plant, complete in all respect | E263: 56700

Sheet RO Rehab 500LPH
A1: =Abstract!A2 -> REHABILITATION OF WATER FILTRATION PLANTS IN DISTRICT BAHAWALPUR | J1: RO | K1: =Abstract!H21 -> 0
J2: Bore | K2: 1
A3: REHABLITATION OF RO PLANT 500 LPH | J3: Abndd | K3: 2
A4: Sr. No. | B4: MRS Ref. # | C4: Description | D4: Unit | E4: Qty. | F4: Unit Rate (PKR) | G4: Amount (PKR) | J4: Dys | K4: 1
A5: 1 | B5: N.S | C5: ='Rate Analysis'!B6 -> Repair & maintenance of Plant Skid frame and Finishing, complete in all respect, inclusive of Carriage to Site and Labor for Installation | D5: p/job | E5: =K1 -> 0 | F5: ='Rate Analysis'!F13 -> 10800 | G5: =F5*E5 -> 0
A6: =A5+1 -> 2 | B6: N.S | C6: ='Rate Analysis'!B18 -> Membranes recovery with chemicals cleaning, including labour & testing, Complete in all respects, inclusive of Carriage to Site and Labor for Installation | D6: p/job | E6: =(K1*50%)*2 -> 0 | F6: ='Rate Analysis'!F25 -> 18000 | G6: =F6*E6 -> 0
A7: =A6+1 -> 3 | B7: N.S | C7: ='Rate Analysis'!B30 -> Supply Installation & Commissioning of Membrane Housing, Complete in all respect | D7: No. | E7: 0 | F7: ='Rate Analysis'!F37 -> 76015 | G7: =F7*E7 -> 0
A8: =A7+1 -> 4 | B8: N.S | C8: ='RA RO500'!B7 -> Supply Installtion and commissioning of RO Plant membranes(4x40), 2 No. complete in all respect | D8: No. | E8: 0 | F8: ='RA RO500'!F13 -> 105255 | G8: =F8*E8 -> 0
A9: =A8+1 -> 5 | B9: N.S | C9: ='RA RO500'!B19 -> Supply Installation and commissioning of RO Feed Pump capacity of 1000 LPH, for 500 LPH RO Plant, complete in all respect | D9: No. | E9: 0 | F9: ='RA RO500'!F25 -> 73095 | G9: =F9*E9 -> 0
A10: =A9+1 -> 6 | B10: N.S | C10: ='RA RO500'!B31 -> Supply, Installation and commissioning of RO High Pressure Pump Capacity of 1000 LPH, for 500 LPH RO Plant, complete in all respect | D10: p/job | E10: 0 | F10: ='RA RO500'!F37 -> 163730 | G10: =F10*E10 -> 0
A11: =A10+1 -> 7 | B11: N.S | C11: ='RA RO500'!B41 -> Repair & maintenance of RO Feed water pump 1000 LPH, for 500 LPH RO Plant, complete in all respect | D11: p/job | E11: 1 | F11: ='RA RO500'!F47 -> 28800 | G11: =F11*E11 -> 28800
A12: =A11+1 -> 8 | B12: N.S | C12: ='RA RO500'!B51 -> Repair & maintenance of RO High Pressure pump 1000 LPH, for 500 LPH RO Plant, complete in all respect | D12: No. | E12: 1 | F12: ='RA RO500'!F57 -> 40800 | G12: =F12*E12 -> 40800
A13: =A12+1 -> 9 | B13: N.S | C13: ='RA RO500'!B75 -> Supply Installation & commissioning of 3inch submersible pump 3HP including supporting clamp, pump coupling, cable clip, delivery pipe, cable complete in all respect. | D13: p/job | E13: 1 | F13: ='RA RO500'!F81 -> 116365 | G13: =F13*E13 -> 116365
A14: =A13+1 -> 10 | B14: N.S | C14: ='Rate Analysis'!B53 -> Supply Installation and Testing of Cartridge Filter complete in all respect | D14: p/job | E14: =K1 -> 0 | F14: ='Rate Analysis'!F59 -> 1510 | G14: =F14*E14 -> 0
A15: =A14+1 -> 11 | B15: N.S | C15: ='Rate Analysis'!B63 -> Supply Installation and Testing of TDS meter complete with all respects | D15: p/job | E15: =K1 -> 0 | F15: ='Rate Analysis'!F69 -> 11695 | G15: =F15*E15 -> 0
A16: =A15+1 -> 12 | B16: N.S | C16: ='Rate Analysis'!B73 -> Supply Installation and Testing of Pressure Switchs complete with all respects | D16: p/job | E16: =K1*60% -> 0 | F16: ='Rate Analysis'!F79 -> 16375 | G16: =F16*E16 -> 0
A17: =A16+1 -> 13 | B17: N.S | C17: ='Rate Analysis'!B97 -> Supply Installation and testing of Rota meter complete in all respect | D17: p/job | E17: =K1*60% -> 0 | F17: ='Rate Analysis'!F103 -> 7015 | G17: =F17*E17 -> 0
A18: =A17+1 -> 14 | B18: N.S | C18: ='Rate Analysis'!B106 -> Supply Installation and Testing of pressure gauges, complete in all respect | D18: p/job | E18: 2 | F18: ='Rate Analysis'!F112 -> 9940 | G18: =F18*E18 -> 19880
A19: =A18+1 -> 15 | B19: N.S | C19: ='Rate Analysis'!B116 -> Supply Installation and testing of Water meter, complete in all respect | D19: p/job | E19: 0 | F19: ='Rate Analysis'!F122 -> 17540 | G19: =F19*E19 -> 0
A20: =A19+1 -> 16 | B20: N.S | C20: ='Rate Analysis'!B143 -> Repair & maintenance of water meter including callibration, complete in all respect | D20: p/job | E20: 1 | F20: ='Rate Analysis'!F150 -> 6000 | G20: =F20*E20 -> 6000
A21: =A20+1 -> 17 | B21: N.S | C21: ='Rate Analysis'!B154 -> Supply Installation and Testing of Solinoid valve complete in all respect | D21: p/job | E21: 1 | F21: ='Rate Analysis'!F160 -> 8770 | G21: =F21*E21 -> 8770
A22: =A21+1 -> 18 | B22: N.S | C22: ='Rate Analysis'!B163 -> Repair & maintenance of Solinoid valve complete in all respect | D22: p/job | E22: 1 | F22: ='Rate Analysis'!F170 -> 4200 | G22: =F22*E22 -> 4200
A23: =A22+1 -> 19 | B23: N.S | C23: ='Rate Analysis'!B191 -> Supply Installation & Commissioning of 3way Multiport Valve, top & bottom distributers, complete in all respect | D23: p/job | E23: 1 | F23: ='Rate Analysis'!F197 -> 40930 | G23: =F23*E23 -> 40930
A24: =A23+1 -> 20 | B24: N.S | C24: ='Rate Analysis'!B201 -> Repair & maintenance of 3way Multiport Valve, top & bottom distributers, complete in all respect | D24: p/job | E24: 1 | F24: ='Rate Analysis'!F208 -> 8400 | G24: =F24*E24 -> 8400
A25: =A24+1 -> 21 | B25: N.S | C25: ='Rate Analysis'!B452 -> 0 | D25: p/job | E25: 1 | F25: ='Rate Analysis'!#REF! -> #REF! | G25: =F25*E25 -> #REF!
A26: =A25+1 -> 22 | B26: N.S | C26: ='Rate Analysis'!B213 -> Supply, installation and Testing of Chemical Dosing Pump, Chlorinator / Liqued Dosing Pump with working pressure 5 - 7 Bar Imported, along with 80 liter capacity tank with all repects.complete in all respect | D26: p/job | E26: 1 | F26: ='Rate Analysis'!F219 -> 69235 | G26: =F26*E26 -> 69235
A27: =A26+1 -> 23 | B27: N.S | C27: ='Rate Analysis'!B235 -> Supply and installation of Water Storage Tank, Capacity 2000 Liters, Material PE, Food Grade, complete in all respects | D27: p/job | E27: 1 | F27: ='Rate Analysis'!F241 -> 31575 | G27: =F27*E27 -> 31575
A28: =A27+1 -> 24 | B28: N.S | C28: ='Rate Analysis'!B247 -> Chemical Cleaning & repair of Water Storage tank, complete in all respects at site | D28: p/job | E28: 1 | F28: ='Rate Analysis'!F254 -> 6000 | G28: =F28*E28 -> 6000
A29: =A28+1 -> 25 | B29: N.S | C29: ='Rate Analysis'!B259 -> Supply and installation of float switch for Water Storage Tank, complete in all respect | D29: kg | E29: 2 | F29: ='Rate Analysis'!F265 -> 2925 | G29: =F29*E29 -> 5850
A30: =A29+1 -> 26 | B30: N.S | C30: ='Rate Analysis'!B280 -> Replacement of Activated Carbon media supply, installation and commissioning complete in all respect NSF Certified, Iodin No 900-1100 | D30: kg | E30: 30 | F30: ='Rate Analysis'!F287 -> 1510 | G30: =F30*E30 -> 45300
A31: =A30+1 -> 27 | B31: N.S | C31: ='Rate Analysis'!B293 -> Replacement of Silica sand media supply, installation and commissioning complete in all respect | D31: kg | E31: 80 | F31: ='Rate Analysis'!F300 -> 110 | G31: =F31*E31 -> 8800
A32: =A31+1 -> 28 | B32: N.S | C32: ='Rate Analysis'!B305 -> Replacement of Natural Gravels media supply, installation and commissioning complete in all respect | D32: p/job | E32: 80 | F32: ='Rate Analysis'!F312 -> 110 | G32: =F32*E32 -> 8800
A33: =A32+1 -> 29 | B33: N.S | C33: ='Rate Analysis'!B341 -> Supply installation and commissioning of UV lamp complete in all respect | D33: p/job | E33: =K1 -> 0 | F33: ='Rate Analysis'!F347 -> 23390 | G33: =F33*E33 -> 0
A34: =A33+1 -> 30 | B34: N.S | C34: ='Rate Analysis'!B352 -> Supply Installation & Commissioning of Manual Valve complete in all respect | D34: p/job | E34: 2 | F34: ='Rate Analysis'!F358 -> 3510 | G34: =F34*E34 -> 7020
A35: =A34+1 -> 31 | B35: N.S | C35: ='Rate Analysis'!B372 -> Repair & maintenance of Pipe and fittings, complete plant fitting in all respect | D35: no. | E35: =K1 -> 0 | F35: ='Rate Analysis'!F379 -> 12000 | G35: =F35*E35 -> 0
A36: =A35+1 -> 32 | B36: N.S | C36: ='Rate Analysis'!B384 -> Supply installation & testing of Plastic water Taps with fussion joint, complete in all respect | D36: p/job | E36: =K1*5 -> 0 | F36: ='Rate Analysis'!F390 -> 585 | G36: =F36*E36 -> 0
A37: =A36+1 -> 33 | B37: N.S | C37: ='Rate Analysis'!B395 -> Repair & maintenance of Plant control panel with PLC & HMI complete in all respect | D37: p/job | E37: =K1 -> 0 | F37: ='Rate Analysis'!F402 -> 36000 | G37: =F37*E37 -> 0
A38: Total Supply & Installtion | G38: =G7+G8+G9+G10+G13+G14+G15+G16+G17+G18+G19+G21+G23+G25+G26+G27+G29+G33+G34+G36 -> #REF! | K38: =SUM(G5:G36) -> #REF!
A39: PRA 5 % (Total Supply & Installtion) | G39: =G38*5% -> #REF! | K39: =K38*5% -> #REF! | L39: =K38+K39 -> #REF!
A40: Total Repair & Maintenance | G40: =G5+G6+G11+G12+G20+G22+G24+G28+G30+G31+G32+G35+G37 -> 157100 | K40: =K38*16% -> #REF! | L40: =K38+K40 -> #REF!
A41: PRA 16 % (Total Repair & Maintenance) | G41: =G40*16% -> 25136
A42: Total cost of 500LPH Rehab RO Plant Inclusive of Tax | G42: =SUM(G38:G41) -> #REF! | H42: =G42/1000000 -> #REF!
A43: Total cost of 500LPH Rehab RO Plant Without Tax | G43: =G40+G38 -> #REF! | H43: =G43/1000000 -> #REF!

Sheet New RO500
A1: ='RO Rehab 500LPH'!A1 -> REHABILITATION OF WATER FILTRATION PLANTS IN DISTRICT BAHAWALPUR
A2: INSTALATION OF RO 500 LPH WFP
A3: Sr, No | B3: Description | C3: Unit | D3: Quantity | E3: Unit Rate (RS) | F3: Amount (RS)
A4: 1 | B4: ='RA RO500'!B63 -> Supply installation and commissioning of 500 L/H Reverse Osmosis (RO) Plant for TDS removal up to 5000 mg/l and inclusive of all taxes conforming to standard specifications according to the Punjab Aab-e-Pak Authority. The specifications along with equipment and accessories properly mounted in the SS frame/skid. | C4: No. | D4: 1 | E4: ='RA RO500'!F69 -> 1198730 | F4: =D4*E4 -> 1198730
B5: Total Capital | F5: =F4 -> 1198730
B6: PRA 5% | F6: =F5*5% -> 59936.5
B7: Grand Total :- | F7: =F5+F6 -> 1258666.5

Sheet R5
A1: =GS!A1 -> PUNJAB SAAF PANI AUTHORITY | H1: =H33 -> 0 | I1: RO | J1: 1
A2: =GS!A2 -> REHABILITATION & O&M OF DYSFUNCTIONAL WATER FILTRATION PLANTS INSTALLED IN DIVISON FAISALABAD | H2: 3 | I2: Bore
A3: =GS!A4:E4 -> BILL OF QUANTITY
A4: Bill No. 1: Rehabilitation of Reverse Osmosis 500 LPH | H4: 3 No., Plant
A5: Sr. No. | B5: MRS Ref. # | C5: Description | D5: Unit | E5: Qty. | F5: Unit Rate (PKR) | G5: Amount (PKR)
A6: 1 | B6: N.S | C6: Rehabilitation of Plant Skid frame and Finishing, complete in all respect, inclusive of Carriage to Site and Labor for Installation Frame: Stainless Steel | D6: Per Plant | E6: 1
A7: 2 | B7: N.S | C7: Supply Installation and commissioning of RO Plant membrane (4x40), including Membrane Housing complete in all respect. Origin: Europe / USA or Equivalent Certification: NSF Pore Size: 0.001 Micron Stablized salt rejection: 99% Capable for TDS: Upto 5000 mg/l Recovery: 15% (each) Life of RO Membrane: 03 to 05 years Pressure Rating: Upto 17 Barg | D7: Per Membrane | E7: 2 | H7: 45000
A8: 3 | B8: N.S | C8: Supply, Installation and commissioning of 1000 LPH High Pressure Pump for 500 LPH RO WFP, complete in all respect Origin: Europe / USA / Japan or Equivalent Discharge: 1000 LPH Operating Head: Up to 16 Barg Pump Type: Vertical / Horizontal High Pressure Pump Impeller material: S.S. 304 Pump Efficiency: > 50% Motor Starter: DOL IP 55 Ambient Temperature Class: 45 degree Celsius | D8: p/job | E8: 1 | I8: 130000
A9: 4 | B9: N.S | C9: Rehabilitation of RO Feed water pump 1000 LPH, for 500 LPH RO Plant, complete in all respect | D9: p/job | E9: 1
A10: 5 | B10: N.S | C10: Supply Installation & commissioning of submersible pump 3HP including supporting clamp with steel cable, pump coupling, cable clip, delivery pipe, electric cable complete in all respect. Origin: Europe / USA/ Asia or Equivalent Minimum Discharge: 2000 LPH Minimum Operation Head: Up to 130 m. Pump Type: Submersible Pump Impeller Type: S.S. 304 Motor Starter: DOL | D10: p/job | E10: 1 | H10: 91365
A11: 6 | B11: N.S | C11: Supply Installation and Testing of Cartridge Filter complete in all respect Size: 20 Inches / As per Flow Porosity: 1-5 micron Material: High pressure Plastic Melt Blown PE | D11: p/job | E11: 1
A12: 7 | B12: N.S | C12: Supply Installation and Testing of Online TDS meter complete with all respects | D12: p/job | E12: 1
A13: 8 | B13: N.S | C13: Supply Installation and Testing of Pressure Switches complete with all respects | D13: p/job | E13: 1
A14: 9 | B14: N.S | C14: Supply Installation and testing of Rota meter complete in all respect Origin: Europe / USA / German / Pakistan or Equivalent Type: Rota Meter / Flow Type Material: Acryclic | D14: p/job | E14: 2
A15: 10 | B15: N.S | C15: Supply Installation and Testing of pressure gauges, complete in all respect | D15: p/job | E15: 3
A16: 11 | B16: N.S | C16: Rehabilitation of Analogue Water meter including callibration, complete in all respect. | D16: p/job | E16: 1
A17: 12 | B17: N.S | C17: Supply Installation and Testing of Solinoid valve complete in all respect | D17: p/job | E17: 2
A18: 13 | B18: N.S | C18: Rehabilitation of Solinoid valve complete in all respect | D18: p/job | E18: 2
A19: 14 | B19: N.S | C19: Supply Installation & Commissioning of 3way Automatic Multiport Valve, top & bottom distributers, complete in all respect | D19: p/job | E19: 1
A20: 15 | B20: N.S | C20: Rehabilitation of 3way Automatic Multiport Valve, top & bottom distributers, complete in all respect | D20: p/job | E20: 1
A21: 16 | B21: N.S | C21: Supply, installation and Testing of Chemical Dosing Pump / Liquid Dosing Pump with working pressure 4 Bar Imported, along with 80 liter capacity tank complete in all respect Origin: Europe / USA / Asia or Equivalent Pressure: 4 bar Tank Size: Maximum 80 liter Chemical Anti Sclanet: Food Grade | D21: p/job | E21: 1
A22: 17 | B22: N.S | C22: Supply and installation of Water Storage Tank, Capacity 2000 Liters, Material PE, Food Grade, 3 to 5 mm wall thickness, weight minimum 32 kg, complete in all respects Capacity : 2000 Litre minimum Material: Plastic food grade | D22: p/job | E22: 1
A23: 18 | B23: N.S | C23: Chemical Cleaning & repair of Water Storage tank, complete in all respects at site | D23: p/job | E23: 1
A24: 19 | B24: N.S | C24: Supply and installation of 2 No. electric float switch for Water Storage Tank, complete in all respect | D24: No. | E24: 1 | H24: =F24/2 -> 0
A25: 20 | B25: N.S | C25: Replacement of Activated Carbon media supply, installation and commissioning complete in all respect NSF Certified, Iodine No 850-1000 Material: Coconut Shell Origin: Sri Lanka / Thailand or Equivalent Size of Media: 1.2 - 1.6 mm Surface Area: 900 m2 / g Bulk Density: 440 - 540 kg / m3 Hardness No: 80 Ash Contents: 5 % Height of Gravel: 200 mm Media Bed Height: > 800 mm | D25: kg | E25: 30 | H25: WASA
A26: 21 | B26: N.S | C26: Replacement of Silica sand media supply, installation and commissioning complete in all respect Material: Quartz Silica Sand Size of Media: 0.85 - 2 mm Cleaning Process: Automatic, through PLC / Time Controller MPV | D26: kg | E26: 90
A27: 22 | B27: N.S | C27: Replacement of Natural Gravels media supply, installation and commissioning complete in all respect Material: Gravel Media | D27: kg | E27: 90
A28: 23 | B28: N.S | C28: Supply installation and commissioning of UV lamp rod with quartz complete in all respect Origin: Europe / USA / German or Equivalent | D28: Per Plant | E28: 1
A29: 24 | B29: N.S | C29: Rehabilitation of Pipe and fittings, complete plant fitting in all respect | D29: Per Plant | E29: 1
A30: 25 | B30: N.S | C30: Supply installation & testing of Plastic water Taps with fusion joint, complete in all respect | D30: p/job | E30: 5
A31: 26 | B31: N.S | C31: Rehabilitation of Plant Control Panel / RO Controller complete in all respect | D31: p/job | E31: 1
A32: 27 | B32: N.S | C32: Supply & Installation of FRP Vessel (Size16 X 65) Origin: Europe / USA / German / China or Equivalent | D32: No. | E32: 1
A33: Grand Total
A34: Per Unit Cost = Grand Total

Sheet Bill No 2 RO 2000 Rehab
A1: ='Bill No 3 UF 1000 Rehab'!A1 -> PUNJAB SAAF PANI AUTHORITY | I1: 21013737 | J1: RO | K1: 1
I2: =G39 -> 957635 | J2: Bore
A3: LAHORE DISTRICT | I3: =I1-I2 -> 20056102 | J3: Dys
A4: =GS!A4:E4 -> BILL OF QUANTITY | J4: fun
A5: Bill No. 2: Rehabilitation of Reverse Osmosis 2 m3/hr
A6: Sr. No. | B6: MRS Ref. # | C6: Description | D6: Unit | E6: Qty. | F6: Unit Rate (PKR) | G6: Amount (PKR) | K6: =GS!#REF! -> #REF!
A7: 1 | B7: N.S | C7: ='Rate Analysis'!B6 -> Repair & maintenance of Plant Skid frame and Finishing, complete in all respect, inclusive of Carriage to Site and Labor for Installation | D7: p/job | E7: 1 | F7: ='Rate Analysis'!F13 -> 10800 | G7: =F7*E7 -> 10800
A8: =A7+1 -> 2 | B8: N.S | C8: ='Rate Analysis'!B18 -> Membranes recovery with chemicals cleaning, including labour & testing, Complete in all respects, inclusive of Carriage to Site and Labor for Installation | D8: p/job | E8: 0 | F8: ='Rate Analysis'!F25 -> 18000 | G8: =F8*E8 -> 0
A9: =A8+1 -> 3 | B9: N.S | C9: ='Rate Analysis'!B30 -> Supply Installation & Commissioning of Membrane Housing, Complete in all respect | D9: No. | E9: 0 | F9: ='Rate Analysis'!F37 -> 76015 | G9: =F9*E9 -> 0
A10: =A9+1 -> 4 | B10: N.S | C10: ='RA RO2000'!B6 -> Supply Installtion and commissioning of RO Plant membranes(4x40), 4 No. complete in all respect. inclusive of Carriage to Site and Labor for Installation | D10: No. | E10: 1 | F10: ='RA RO2000'!F12 -> 421015 | G10: =F10*E10 -> 421015
A11: =A10+1 -> 5 | B11: N.S | C11: ='RA RO2000'!B18 -> Supply Installation and commissioning of RO Feed Pump capacity of 4000 LPH, for 2000 LPH RO Plant, complete in all respect | D11: No. | E11: 0 | F11: ='RA RO2000'!F24 -> 119290 | G11: =F11*E11 -> 0
A12: =A11+1 -> 6 | B12: N.S | C12: ='RA RO2000'!B30 -> Supply, Installation and commissioning of RO High Pressure Pump Capacity of 4000 LPH, for 2000 LPH RO Plant, complete in all respect | D12: p/job | E12: 0 | F12: ='RA RO2000'!F36 -> 239745 | G12: =F12*E12 -> 0
A13: =A12+1 -> 7 | B13: N.S | C13: ='RA RO1000'!B52 -> Repair & maintenance of RO Feed water pump 2000 LPH, for 1000 LPH RO Plant, complete in all respect | D13: p/job | E13: 1 | F13: ='RA RO2000'!F58 -> 28800 | G13: =F13*E13 -> 28800
A14: =A13+1 -> 8 | B14: N.S | C14: ='RA RO2000'!B61 -> Repair & maintenance of RO High Pressure pump 4000 LPH, for 2000 LPH RO Plant, complete in all respect | D14: No. | E14: 1 | F14: ='RA RO2000'!F68 -> 40800 | G14: =F14*E14 -> 40800
A15: =A14+1 -> 9 | B15: N.S | C15: ='RA RO2000'!B95 -> Supply Installation & commissioning of 3inch submersible pump 3HP including supporting clamp, pump coupling, cable clip, delivery pipe, cable complete in all respect. | D15: p/job | E15: 0 | F15: ='RA RO2000'!F101 -> 116365 | G15: =F15*E15 -> 0
A16: =A15+1 -> 10 | B16: N.S | C16: ='Rate Analysis'!B53 -> Supply Installation and Testing of Cartridge Filter complete in all respect | D16: p/job | E16: =K1 -> 1 | F16: ='Rate Analysis'!F59 -> 1510 | G16: =F16*E16 -> 1510
A17: =A16+1 -> 11 | B17: N.S | C17: ='Rate Analysis'!B63 -> Supply Installation and Testing of TDS meter complete with all respects | D17: p/job | E17: =E16 -> 1 | F17: ='Rate Analysis'!F69 -> 11695 | G17: =F17*E17 -> 11695
A18: =A17+1 -> 12 | B18: N.S | C18: ='Rate Analysis'!B73 -> Supply Installation and Testing of Pressure Switchs complete with all respects | D18: p/job | E18: =K1 -> 1 | F18: ='Rate Analysis'!F79 -> 16375 | G18: =F18*E18 -> 16375
A19: =A18+1 -> 13 | B19: N.S | C19: ='Rate Analysis'!B97 -> Supply Installation and testing of Rota meter complete in all respect | D19: p/job | E19: =K1 -> 1 | F19: ='Rate Analysis'!F103 -> 7015 | G19: =F19*E19 -> 7015
A20: =A19+1 -> 14 | B20: N.S | C20: ='Rate Analysis'!B106 -> Supply Installation and Testing of pressure gauges, complete in all respect | D20: p/job | E20: =K1*2 -> 2 | F20: ='Rate Analysis'!F112 -> 9940 | G20: =F20*E20 -> 19880
A21: =A20+1 -> 15 | B21: N.S | C21: ='Rate Analysis'!B116 -> Supply Installation and testing of Water meter, complete in all respect | D21: p/job | E21: 0 | F21: ='Rate Analysis'!F122 -> 17540 | G21: =F21*E21 -> 0
A22: =A21+1 -> 16 | B22: N.S | C22: ='Rate Analysis'!B143 -> Repair & maintenance of water meter including callibration, complete in all respect | D22: p/job | E22: 1 | F22: ='Rate Analysis'!F150 -> 6000 | G22: =F22*E22 -> 6000
A23: =A22+1 -> 17 | B23: N.S | C23: ='Rate Analysis'!B154 -> Supply Installation and Testing of Solinoid valve complete in all respect | D23: p/job | E23: 0 | F23: ='Rate Analysis'!F160 -> 8770 | G23: =F23*E23 -> 0
A24: =A23+1 -> 18 | B24: N.S | C24: ='Rate Analysis'!B163 -> Repair & maintenance of Solinoid valve complete in all respect | D24: p/job | E24: 1 | F24: ='Rate Analysis'!F170 -> 4200 | G24: =F24*E24 -> 4200
A25: =A24+1 -> 19 | B25: N.S | C25: ='Rate Analysis'!B191 -> Supply Installation & Commissioning of 3way Multiport Valve, top & bottom distributers, complete in all respect | D25: p/job | E25: 0 | F25: ='Rate Analysis'!F197 -> 40930 | G25: =F25*E25 -> 0
A26: =A25+1 -> 20 | B26: N.S | C26: ='Rate Analysis'!B201 -> Repair & maintenance of 3way Multiport Valve, top & bottom distributers, complete in all respect | D26: p/job | E26: 2 | F26: ='Rate Analysis'!F208 -> 8400 | G26: =F26*E26 -> 16800
A27: =A26+1 -> 21 | B27: N.S | C27: ='Rate Analysis'!B213 -> Supply, installation and Testing of Chemical Dosing Pump, Chlorinator / Liqued Dosing Pump with working pressure 5 - 7 Bar Imported, along with 80 liter capacity tank with all repects.complete in all respect | D27: p/job | E27: =K1 -> 1 | F27: ='Rate Analysis'!F219 -> 69235 | G27: =F27*E27 -> 69235
A28: =A27+1 -> 22 | B28: N.S | C28: ='Rate Analysis'!B235 -> Supply and installation of Water Storage Tank, Capacity 2000 Liters, Material PE, Food Grade, complete in all respects | D28: p/job | E28: 0 | F28: ='Rate Analysis'!F241 -> 31575 | G28: =F28*E28 -> 0
A29: =A28+1 -> 23 | B29: N.S | C29: ='Rate Analysis'!B247 -> Chemical Cleaning & repair of Water Storage tank, complete in all respects at site | D29: p/job | E29: 1 | F29: ='Rate Analysis'!F254 -> 6000 | G29: =F29*E29 -> 6000
A30: =A29+1 -> 24 | B30: N.S | C30: ='Rate Analysis'!B259 -> Supply and installation of float switch for Water Storage Tank, complete in all respect | D30: No. | E30: 1 | F30: ='Rate Analysis'!F265 -> 2925 | G30: =F30*E30 -> 2925
A31: =A30+1 -> 25 | B31: N.S | C31: ='Rate Analysis'!B280 -> Replacement of Activated Carbon media supply, installation and commissioning complete in all respect NSF Certified, Iodin No 900-1100 | D31: kg | E31: =160*(K1*80%) -> 128 | F31: ='Rate Analysis'!F287 -> 1510 | G31: =F31*E31 -> 193280
A32: =A31+1 -> 26 | B32: N.S | C32: ='Rate Analysis'!B293 -> Replacement of Silica sand media supply, installation and commissioning complete in all respect | D32: kg | E32: =160*(K1*80%) -> 128 | F32: ='Rate Analysis'!F300 -> 110 | G32: =F32*E32 -> 14080
A33: =A32+1 -> 27 | B33: N.S | C33: ='Rate Analysis'!B305 -> Replacement of Natural Gravels media supply, installation and commissioning complete in all respect | D33: kg | E33: =160*(K1*80%) -> 128 | F33: ='Rate Analysis'!F312 -> 110 | G33: =F33*E33 -> 14080
A34: =A33+1 -> 28 | B34: N.S | C34: ='Rate Analysis'!B341 -> Supply installation and commissioning of UV lamp complete in all respect | D34: p/job | E34: =K1 -> 1 | F34: ='Rate Analysis'!F347 -> 23390 | G34: =F34*E34 -> 23390
A35: =A34+1 -> 29 | B35: N.S | C35: ='Rate Analysis'!B352 -> Supply Installation & Commissioning of Manual Valve complete in all respect | D35: p/job | E35: 0 | F35: ='Rate Analysis'!F358 -> 3510 | G35: =F35*E35 -> 0
A36: =A35+1 -> 30 | B36: N.S | C36: ='Rate Analysis'!B372 -> Repair & maintenance of Pipe and fittings, complete plant fitting in all respect | D36: no. | E36: 1 | F36: ='Rate Analysis'!F379 -> 12000 | G36: =F36*E36 -> 12000
A37: =A36+1 -> 31 | B37: N.S | C37: ='Rate Analysis'!B384 -> Supply installation & testing of Plastic water Taps with fussion joint, complete in all respect | D37: p/job | E37: =K1*3 -> 3 | F37: ='Rate Analysis'!F390 -> 585 | G37: =F37*E37 -> 1755
A38: =A37+1 -> 32 | B38: N.S | C38: ='Rate Analysis'!B395 -> Repair & maintenance of Plant control panel with PLC & HMI complete in all respect | D38: p/job | E38: =K1 -> 1 | F38: ='Rate Analysis'!F402 -> 36000 | G38: =F38*E38 -> 36000
A39: Grand Total | G39: =SUM(G7:G38) -> 957635
A40: Total Supply & Installtion | G40: =G9+G10+G11+G12+G15+G16+G17+G18+G19+G20+G21+G23+G25+#REF!+#REF!+G27+G28+G30+G34+G35+G37 -> #REF! | K40: =SUM(G7:G37) -> 921635
A41: PRA 5 % (Total Supply & Installtion) | G41: =G40*5% -> #REF! | K41: =K40*5% -> 46081.75 | L41: =K40+K41 -> 967716.75
A42: Total Repair & Maintenance | G42: =G7+G8+G13+G14+G22+G24+G26+G29+G31+G32+G33+G36+G38 -> 382840 | K42: =K40*16% -> 147461.6 | L42: =K40+K42 -> 1069096.6
A43: PRA 16 % (Total Repair & Maintenance) | G43: =G42*16% -> 61254.4
A44: Total cost of 2000LPH Rehab RO Plant Inclusive of Tax | G44: =SUM(G40:G43) -> #REF! | H44: =G44/1000000 -> #REF!
A45: Total cost of 2000LPH Rehab RO Plant Without Tax | G45: =G42+G40 -> #REF! | H45: =G45/1000000 -> #REF!
D49: Per Unit Cost | G49: =G39/K1 -> 957635
A54: Assistant Manager (P&MC) - CZ | D54: Deputy Manager (P&MC) - CZ
A55: Punjab Aab-e-Pak Authority | D55: Punjab Aab-e-Pak Authority

Sheet Bill No 3 UF 1000 Rehab
A1: ='Bill no 3 RO 1000 New'!A1 -> PUNJAB SAAF PANI AUTHORITY | I1: 3460870 | J1: UF | K1: =GS!#REF! -> #REF!
I2: =G36 -> 0 | J2: abnd | K2: 0
A3: LAHORE DISTRICT | I3: =I1-I2 -> 3460870 | J3: dys | K3: 2
A4: =GS!A4:E4 -> BILL OF QUANTITY
A5: Bill No. 3: Rehabilitation of Ultra Filtration 1 m3/hr
A6: Sr. No. | B6: MRS Ref. # | C6: Description | D6: Unit | E6: Qty. | F6: Unit Rate (PKR) | G6: Amount (PKR)
A7: 1 | B7: N.S | C7: ='Rate Analysis'!B6 -> Repair & maintenance of Plant Skid frame and Finishing, complete in all respect, inclusive of Carriage to Site and Labor for Installation | D7: p/job | E7: 3 | F7: ='Rate Analysis'!F13 -> 10800 | G7: =F7*E7 -> 32400
A8: 2 | B8: N.S | C8: ='Rate Analysis'!B18 -> Membranes recovery with chemicals cleaning, including labour & testing, Complete in all respects, inclusive of Carriage to Site and Labor for Installation | D8: p/job | E8: 2 | F8: ='Rate Analysis'!F25 -> 18000 | G8: =F8*E8 -> 36000
A9: 3 | B9: N.S | C9: ='RA UF1000'!B18 -> Supply Installation and commissioning of UF Feed Pump capacity of 1000 LPH, for 1000 LPH UF Plant, complete in all respect | D9: No. | E9: 1 | F9: ='RA UF1000'!F24 -> 73095 | G9: =F9*E9 -> 73095
A10: =A9+1 -> 4 | B10: N.S | C10: ='RA UF1000'!B28 -> Repair & maintenance of UF Feed water pump 1000 LPH, for 1000 LPH UF Plant, complete in all respect | D10: p/job | E10: 1 | F10: ='RA UF1000'!F34 -> 28800 | G10: =F10*E10 -> 28800
A11: =A10+1 -> 5 | B11: N.S | C11: ='RA UF1000'!B66 -> Supply Installation & commissioning of 3inch submersible pump 3HP including supporting clamp, pump coupling, cable clip, delivery pipe, cable complete in all respect. | D11: p/job | E11: 1 | F11: ='RA UF1000'!F72 -> 116365 | G11: =F11*E11 -> 116365
A12: =A11+1 -> 6 | B12: N.S | C12: ='Rate Analysis'!B438 -> Supply and installation of safety filter strainer | D12: p/job | E12: 9 | F12: ='Rate Analysis'!F444 -> 1405 | G12: =F12*E12 -> 12645
A13: =A12+1 -> 7 | B13: N.S | C13: ='Rate Analysis'!B63 -> Supply Installation and Testing of TDS meter complete with all respects | D13: p/job | E13: =K1 -> #REF! | F13: ='Rate Analysis'!F69 -> 11695 | G13: =F13*E13 -> #REF!
A14: =A13+1 -> 8 | B14: N.S | C14: ='Rate Analysis'!B73 -> Supply Installation and Testing of Pressure Switchs complete with all respects | D14: p/job | E14: 9 | F14: ='Rate Analysis'!F79 -> 16375 | G14: =F14*E14 -> 147375
A15: =A14+1 -> 9 | B15: N.S | C15: ='Rate Analysis'!B97 -> Supply Installation and testing of Rota meter complete in all respect | D15: p/job | E15: 9 | F15: ='Rate Analysis'!F103 -> 7015 | G15: =F15*E15 -> 63135
A16: =A15+1 -> 10 | B16: N.S | C16: ='Rate Analysis'!B106 -> Supply Installation and Testing of pressure gauges, complete in all respect | D16: p/job | E16: 18 | F16: ='Rate Analysis'!F112 -> 9940 | G16: =F16*E16 -> 178920
A17: =A16+1 -> 11 | B17: N.S | C17: ='Rate Analysis'!B116 -> Supply Installation and testing of Water meter, complete in all respect | D17: p/job | E17: 3 | F17: ='Rate Analysis'!F122 -> 17540 | G17: =F17*E17 -> 52620
A18: =A17+1 -> 12 | B18: N.S | C18: ='Rate Analysis'!B143 -> Repair & maintenance of water meter including callibration, complete in all respect | D18: p/job | E18: 5 | F18: ='Rate Analysis'!F150 -> 6000 | G18: =F18*E18 -> 30000
A19: =A18+1 -> 13 | B19: N.S | C19: ='Rate Analysis'!B154 -> Supply Installation and Testing of Solinoid valve complete in all respect | D19: p/job | E19: 6 | F19: ='Rate Analysis'!F160 -> 8770 | G19: =F19*E19 -> 52620
A20: =A19+1 -> 14 | B20: N.S | C20: ='Rate Analysis'!B163 -> Repair & maintenance of Solinoid valve complete in all respect | D20: p/job | E20: 5 | F20: ='Rate Analysis'!F170 -> 4200 | G20: =F20*E20 -> 21000
A21: =A20+1 -> 15 | B21: N.S | C21: ='Rate Analysis'!B191 -> Supply Installation & Commissioning of 3way Multiport Valve, top & bottom distributers, complete in all respect | D21: p/job | E21: 3 | F21: ='Rate Analysis'!F197 -> 40930 | G21: =F21*E21 -> 122790
A22: =A21+1 -> 16 | B22: N.S | C22: ='Rate Analysis'!B201 -> Repair & maintenance of 3way Multiport Valve, top & bottom distributers, complete in all respect | D22: p/job | E22: 5 | F22: ='Rate Analysis'!F208 -> 8400 | G22: =F22*E22 -> 42000
A23: =A22+1 -> 17 | B23: N.S | C23: ='Rate Analysis'!B213 -> Supply, installation and Testing of Chemical Dosing Pump, Chlorinator / Liqued Dosing Pump with working pressure 5 - 7 Bar Imported, along with 80 liter capacity tank with all repects.complete in all respect | D23: p/job | E23: =K1 -> #REF! | F23: ='Rate Analysis'!F219 -> 69235 | G23: =F23*E23 -> #REF!
A24: =A23+1 -> 18 | B24: N.S | C24: ='Rate Analysis'!B235 -> Supply and installation of Water Storage Tank, Capacity 2000 Liters, Material PE, Food Grade, complete in all respects | D24: p/job | E24: 1 | F24: ='Rate Analysis'!F241 -> 31575 | G24: =F24*E24 -> 31575
A25: =A24+1 -> 19 | B25: N.S | C25: ='Rate Analysis'!B247 -> Chemical Cleaning & repair of Water Storage tank, complete in all respects at site | D25: p/job | E25: 17 | F25: ='Rate Analysis'!F254 -> 6000 | G25: =F25*E25 -> 102000
A26: =A25+1 -> 20 | B26: N.S | C26: ='Rate Analysis'!B259 -> Supply and installation of float switch for Water Storage Tank, complete in all respect | D26: kg | E26: 2 | F26: ='Rate Analysis'!F265 -> 2925 | G26: =F26*E26 -> 5850
A27: =A26+1 -> 21 | B27: N.S | C27: ='Rate Analysis'!B280 -> Replacement of Activated Carbon media supply, installation and commissioning complete in all respect NSF Certified, Iodin No 900-1100 | D27: kg | E27: =50*(K1*50%) -> #REF! | F27: ='Rate Analysis'!F287 -> 1510 | G27: =F27*E27 -> #REF!
A28: =A27+1 -> 22 | B28: N.S | C28: ='Rate Analysis'!B293 -> Replacement of Silica sand media supply, installation and commissioning complete in all respect | D28: kg | E28: =160*(K1*50%) -> #REF! | F28: ='Rate Analysis'!F300 -> 110 | G28: =F28*E28 -> #REF!
A29: =A28+1 -> 23 | B29: N.S | C29: ='Rate Analysis'!B305 -> Replacement of Natural Gravels media supply, installation and commissioning complete in all respect | D29: p/job | E29: =160*(K1*50%) -> #REF! | F29: ='Rate Analysis'!F312 -> 110 | G29: =F29*E29 -> #REF!
A30: =A29+1 -> 24 | B30: N.S | C30: ='Rate Analysis'!B328 -> Replacement of Granular Feric Oxide use for druinking water treatment with oxidation capavity of AS3 to AS5, commissioning complete in all respect | D30: kg | E30: =160*1 -> 160 | F30: ='Rate Analysis'!F335 -> 2640 | G30: =F30*E30 -> 422400
A31: =A30+1 -> 25 | B31: N.S | C31: ='Rate Analysis'!B341 -> Supply installation and commissioning of UV lamp complete in all respect | D31: p/job | E31: =K1 -> #REF! | F31: ='Rate Analysis'!F347 -> 23390 | G31: =F31*E31 -> #REF!
A32: =A31+1 -> 26 | B32: N.S | C32: ='Rate Analysis'!B352 -> Supply Installation & Commissioning of Manual Valve complete in all respect | D32: p/job | E32: 1 | F32: ='Rate Analysis'!F358 -> 3510 | G32: =F32*E32 -> 3510
A33: =A32+1 -> 27 | B33: N.S | C33: ='Rate Analysis'!B372 -> Repair & maintenance of Pipe and fittings, complete plant fitting in all respect | D33: no. | E33: =K1 -> #REF! | F33: ='Rate Analysis'!F379 -> 12000 | G33: =F33*E33 -> #REF!
A34: =A33+1 -> 28 | B34: N.S | C34: ='Rate Analysis'!B384 -> Supply installation & testing of Plastic water Taps with fussion joint, complete in all respect | D34: p/job | E34: =K1*3 -> #REF! | F34: ='Rate Analysis'!F390 -> 585 | G34: =F34*E34 -> #REF!
A35: =A34+1 -> 29 | B35: N.S | C35: ='Rate Analysis'!B395 -> Repair & maintenance of Plant control panel with PLC & HMI complete in all respect | D35: p/job | E35: =K1 -> #REF! | F35: ='Rate Analysis'!F402 -> 36000 | G35: =F35*E35 -> #REF!
A36: Grand Total | G36: 0
A37: Total Supply & Installtion | G37: =#REF!+#REF!+G9+G11+G12+G13+G14+G15+G16+G17+G19+G21+#REF!+G23+G24+G26+G31+G32+G34 -> #REF! | K37: =SUM(G7:G34) -> #REF!
A38: PRA 5 % (Total Supply & Installtion) | G38: =G37*5% -> #REF! | K38: =K37*5% -> #REF! | L38: =K37+K38 -> #REF!
A39: Total Repair & Maintenance | G39: =G7+G8+G10+G18+G20+G22+G25+G27+G28+G29+G30+G33+G35 -> #REF! | K39: =K37*16% -> #REF! | L39: =K37+K39 -> #REF!
A40: PRA 16 % (Total Repair & Maintenance) | G40: =G39*16% -> #REF!
A41: Total cost of 1000LPH Rehab UF Plant Inclusive of Tax | G41: =SUM(G37:G40) -> #REF! | H41: =G41/1000000 -> #REF!
A42: Total cost of 1000LPH Rehab UF Plant Without Tax | G42: =G39+G37 -> #REF! | H42: =G42/1000000 -> #REF!
D44: Per Unit Cost | G44: =G36/K1 -> #REF!
A49: Assistant Manager (P&MC) - CZ | D49: Deputy Manager (P&MC) - CZ
A50: Punjab Aab-e-Pak Authority | D50: Punjab Aab-e-Pak Authority

Sheet R1
A1: ='R5'!A1:G2 -> PUNJAB SAAF PANI AUTHORITY | H1: =H37 -> 0 | I1: RO | J1: 50
A2: ='R5'!A2:G2 -> REHABILITATION & O&M OF DYSFUNCTIONAL WATER FILTRATION PLANTS INSTALLED IN DIVISON FAISALABAD | H2: =G37 -> 0 | I2: Bore
A3: ='R5'!A3:G3 -> BILL OF QUANTITY
A4: Bill No. 2: Rehabilitation of Reverse Osmosis 1000 LPH
A5: Sr. No. | B5: MRS Ref. # | C5: Description | D5: Unit | E5: Qty. | F5: Unit Rate (PKR) | G5: Amount (PKR)
A6: 1 | B6: N.S | C6: Rehabilitation of Plant Skid frame and Finishing, complete in all respect, inclusive of Carriage to Site and Labor for Installation Frame: Stainless Steel | D6: Per Plant | E6: 30 | H6: 10800
A7: 2 | B7: N.S | C7: Membranes recovery with chemicals cleaning, including labour & testing, Complete in all respects, inclusive of Carriage to Site and Labor for Installation | D7: Per Plant | E7: 20 | H7: 19000
A8: 3 | B8: N.S | C8: Supply Installation and commissioning of RO Plant membrane (4x40), including Membrane Housing complete in all respect. Origin: Europe / USA or Equivalent Certification: NSF Pore Size: 0.001 Micron Stablized salt rejection: 99% Capable for TDS: Upto 5000 mg/l Recovery: 15% (each) Life of RO Membrane: 03 to 05 years Pressure Rating: Upto 17 Barg | D8: Per Membrane | E8: 80 | H8: =210510/4 -> 52627.5 | I8: =40/4 -> 10 | J8: =40/4 -> 10 | K8: =80/4 -> 20
A9: 4 | B9: N.S | C9: Supply Installation and commissioning of 2000 LPH Feed Pump for 1000 LPH RO WFP, complete in all respect Discharge: 2000 LPH Minimum Operation Head: 04 Barg Maximum. Origin: Europe / USA / China or Equivalent Pump Type: Vertical / Horizontal Low Pressure Pump Impeller Type: S.S. 304 Operating Head: Up to 06 Barg Pump Efficiency: ≥ 40% Motor Starter: DOL | D9: No. | E9: 15 | H9: 94745 | I9: 80000
A10: 5 | B10: N.S | C10: Supply, Installation and commissioning of 2000 LPH High Pressure Pump for 1000 LPH RO WFP, complete in all respect Origin: Europe / USA / Japan or Equivalent Discharge: 2000 LPH Operating Head: Up to 16 Barg Pump Type: Vertical / Horizontal High Pressure Pump Impeller material: S.S. 304 Pump Efficiency: > 50% Motor Starter: DOL IP 55 Ambient Temperature Class: 45 degree Celsius | D10: p/job | E10: 15 | H10: 204660 | I10: 130000
A11: 6 | B11: N.S | C11: Rehabilitation of RO Feed water pump 2000 LPH, for 1000 LPH RO Plant, complete in all respect | D11: p/job | E11: 35 | H11: 18800
A12: 7 | B12: N.S | C12: Rehabilitation of RO High Pressure pump 2000 LPH, for 1000 LPH RO Plant, complete in all respect | D12: p/job | E12: 35 | H12: 35800
A13: 8 | B13: N.S | C13: Supply Installation & commissioning of submersible pump 3HP including supporting clamp with steel cable, pump coupling, cable clip, delivery pipe, electric cable complete in all respect. Origin: Europe / USA/ Asia or Equivalent Minimum Discharge: 2000 LPH Minimum Operation Head: Up to 130 m. Pump Type: Submersible Pump Impeller Type: S.S. 304 Motor Starter: DOL | D13: p/job | E13: 25 | H13: 91365
A14: 9 | B14: N.S | C14: Supply Installation and Testing of Cartridge Filter complete in all respect Size: 20 Inches / As per Flow Porosity: 1-5 micron Material: High pressure Plastic Melt Blown PE | D14: p/job | E14: =J1*100% -> 50 | H14: 1510
A15: 10 | B15: N.S | C15: Supply Installation and Testing of Online TDS meter complete with all respects | D15: p/job | E15: =J1 -> 50 | H15: 8695
A16: 11 | B16: N.S | C16: Supply Installation and Testing of Pressure Switches complete with all respects | D16: p/job | E16: =J1 -> 50 | H16: 6375
A17: 12 | B17: N.S | C17: Supply Installation and testing of Rota meter complete in all respect Origin: Europe / USA / German / Pakistan or Equivalent Type: Rota Meter / Flow Type Material: Acryclic | D17: p/job | E17: =J1 -> 50 | H17: 5117
A18: 13 | B18: N.S | C18: Supply Installation and Testing of pressure gauges, complete in all respect | D18: p/job | E18: =J1*4 -> 200 | H18: 3400
A19: 14 | B19: N.S | C19: Supply Installation and testing of Analogue Water meter, complete in all respect | D19: p/job | E19: 25 | H19: 17540
A20: 15 | B20: N.S | C20: Rehabilitation of analogue water meter including callibration, complete in all respect | D20: p/job | E20: 25 | H20: 6000
A21: 16 | B21: N.S | C21: Supply Installation and Testing of Solinoid valve complete in all respect | D21: p/job | E21: 50 | H21: 8500
A22: 17 | B22: N.S | C22: Rehabilitation of Solinoid valve complete in all respect | D22: p/job | E22: 60 | H22: 3200
A23: 18 | B23: N.S | C23: Supply Installation & Commissioning of 3way Automatic Multiport Valve, top & bottom distributers, complete in all respect | D23: p/job | E23: 30 | H23: 40930
A24: 19 | B24: N.S | C24: Rehabilitation of 3way Automatic Multiport Valve, top & bottom distributers, complete in all respect | D24: p/job | E24: 50 | H24: 8400
A25: 20 | B25: N.S | C25: Supply, installation and Testing of Chemical Dosing Pump / Liquid Dosing Pump with working pressure 5 - 7 Bar Imported, along with 80 liter capacity tank complete in all respect Origin: Europe / USA / Asia or Equivalent Pressure: 5 -7 bar Tank Size: Maximum 80 liter Chemical Anti Sclanet: Food Grade | D25: p/job | E25: 25 | H25: 69235
A26: 21 | B26: N.S | C26: Supply and installation of Water Storage Tank, Capacity 2000 Liters, Material PE, Food Grade, 3 to 5 mm wall thickness, weight minimum 32 kg, complete in all respects Capacity : 2000 Litre minimum Material: Plastic food grade | D26: p/job | E26: 35 | H26: 45575
A27: 22 | B27: N.S | C27: Chemical Cleaning of Water Storage tank, complete in all respects at site | D27: p/job | E27: =(J1*2)-E26 -> 65 | H27: 2500
A28: 23 | B28: N.S | C28: Supply and installation of 2 No. electric float switch for Water Storage Tank, complete in all respect | D28: No. | E28: 28 | H28: 3625
A29: 24 | B29: N.S | C29: Replacement of Activated Carbon media supply, installation and commissioning complete in all respect NSF Certified, Iodine No 850-1000 Material: Coconut Shell Origin: Sri Lanka / Thailand or Equivalent Size of Media: 1.2 - 1.6 mm Surface Area: 900 m2 / g Bulk Density: 440 - 540 kg / m3 Hardness No: 80 Ash Contents: 5 % Height of Gravel: 200 mm Media Bed Height: > 800 mm | D29: kg | E29: =40*(J1*60%) -> 1200 | H29: 1510
A30: 25 | B30: N.S | C30: Replacement of Silica sand media supply, installation and commissioning complete in all respect Material: Quartz Silica Sand Size of Media: 0.85 - 2 mm Cleaning Process: Automatic, through PLC / Time Controller MPV | D30: kg | E30: =90*(J1*70%) -> 3150 | H30: 70
A31: 26 | B31: N.S | C31: Replacement of Natural Gravels media supply, installation and commissioning complete in all respect Material: Gravel Media | D31: kg | E31: =90*(J1*60%) -> 2700 | H31: 70
A32: 27 | B32: N.S | C32: Supply installation and commissioning of UV lamp rod with quartz complete in all respect Origin: Europe / USA / German or Equivalent | D32: Per Plant | E32: 20 | H32: 11390
A33: 28 | B33: N.S | C33: Rehabilitation of Pipe and fittings, complete plant fitting in all respect | D33: Per Plant | E33: 25 | H33: 22000
A34: 29 | B34: N.S | C34: Supply installation & testing of Plastic water Taps with fusion joint, complete in all respect | D34: p/job | E34: =J1*5 -> 250 | H34: 585
A35: 30 | B35: N.S | C35: Rehabilitation of Plant Control Panel / RO Controller complete in all respect | D35: p/job | E35: 25 | H35: 36000
A36: 31 | B36: N.S | C36: Supply & Installation of FRP Vessel (Size16 X 65) Origin: Europe / USA / German / China or Equivalent | D36: No. | E36: 1
A37: Grand Total
A38: Per Unit Cost = Grand Total / 50

Sheet R2
A1: ='R5'!A1:G2 -> PUNJAB SAAF PANI AUTHORITY | J1: RO | K1: 48
A2: ='R5'!A2:G2 -> REHABILITATION & O&M OF DYSFUNCTIONAL WATER FILTRATION PLANTS INSTALLED IN DIVISON FAISALABAD
A3: ='R1'!A3:G3 -> BILL OF QUANTITY
A4: Bill No. 3: Rehabilitation of Reverse Osmosis 2000 LPH
A5: Sr. No. | B5: MRS Ref. # | C5: Description | D5: Unit | E5: Qty. | F5: Unit Rate (PKR) | G5: Amount (PKR)
A6: 1 | B6: N.S | C6: Rehabilitation of Plant Skid frame and Finishing, complete in all respect, inclusive of Carriage to Site and Labor for Installation Frame: Frame stainless steel | D6: p/job | E6: 30 | K6: 0.3
A7: 2 | B7: N.S | C7: Membranes recovery with chemicals cleaning, including labour & testing, Complete in all respects, inclusive of Carriage to Site and Labor for Installation | D7: p/job | E7: 20 | K7: 0.3
A8: 3 | B8: N.S | C8: Supply Installation and commissioning of RO Plant membrane (4x40), including Membrane Housing complete in all respect. Origin: Europe / USA or Equivalent Certification: NSF Pore Size: 0.001 Micron Stablized salt rejection: 99% Capable for TDS: Upto 5000 mg/l Recovery: 15% (each) Life of RO Membrane: 03 to 05 years Pressure Rating: Upto 17 Barg | D8: Per Membrane | E8: 160 | K8: =E8/8 -> 20 | L8: =160/8 -> 20
A9: 4 | B9: N.S | C9: Supply Installation and commissioning of 4000 LPH Feed Pump for 2000 LPH RO WFP, complete in all respect Discharge: 4000 LPH Minimum Operation Head: 04 Barg Maximum. Origin: Europe / USA / China or Equivalent Pump Type: Vertical / Horizontal Low Pressure Pump Impeller Type: S.S. 304 Operating Head: Up to 06 Barg Pump Efficiency: ≥ 40% Motor Starter: DOL | D9: No. | E9: 20 | K9: 0.1
A10: 5 | B10: N.S | C10: Supply, Installation and commissioning of 4000 LPH High Pressure Pump for 2000 LPH RO WFP, complete in all respect Origin: Europe / USA / Japan or Equivalent Discharge: 4000 LPH Operating Head: Up to 16 Barg Pump Type: Vertical / Horizontal High Pressure Pump Impeller material: S.S. 304 Pump Efficiency: > 50% Motor Starter: DOL IP 55 Ambient Temperature Class: 45 degree Celsius | D10: p/job | E10: 20 | K10: 0.1
A11: 6 | B11: N.S | C11: Rehabilitation of RO Feed water pump 2000 LPH, for 1000 LPH RO Plant, complete in all respect | D11: p/job | E11: 28 | K11: 0.3
A12: 7 | B12: N.S | C12: Rehabilitation of RO High Pressure pump 4000 LPH, for 2000 LPH RO Plant, complete in all respect | D12: No. | E12: 28 | K12: 0.3
A13: 8 | B13: N.S | C13: Supply Installation & commissioning of submersible pump 3HP including supporting clamp with steel cable, pump coupling, cable clip, delivery pipe, electric cable complete in all respect. Origin: Europe / USA/ Asia or Equivalent Minimum Discharge: 2000 LPH Minimum Operation Head: Up to 130 m. Pump Type: Submersible Pump Impeller Type: S.S. 304 Motor Starter: DOL | D13: p/job | E13: 20 | K13: 0.1
A14: 9 | B14: N.S | C14: Supply Installation and Testing of Cartridge Filter complete in all respect Size: 20 Inches / As per Flow Porosity: 1-5 micron Material: High pressure Plastic Melt Blown PE | D14: p/job | E14: 38 | K14: 1
A15: 10 | B15: N.S | C15: Supply Installation and Testing of online TDS meter complete with all respects | D15: p/job | E15: 38 | K15: 0.6
A16: 11 | B16: N.S | C16: Supply Installation and Testing of Pressure Switchs complete with all respects | D16: p/job | E16: 38 | K16: 0.4
A17: 12 | B17: N.S | C17: Supply Installation and testing of Rota meter complete in all respect Origin: Europe / USA / German / Pakistan or Equiavlent Type: Rota Meter / Flow Type Material: Acryclic | D17: p/job | E17: 38 | K17: 0.6
A18: 13 | B18: N.S | C18: Supply Installation and Testing of pressure gauges, complete in all respect | D18: p/job | E18: =K1*4 -> 192 | K18: 2
A19: 14 | B19: N.S | C19: Supply Installation and testing of analogue Water meter, complete in all respect | D19: p/job | E19: 15 | K19: 0.2
A20: 15 | B20: N.S | C20: Rehabilitation of analogue water meter including callibration, complete in all respect | D20: p/job | E20: 33 | K20: 0.5
A21: 16 | B21: N.S | C21: Supply Installation and Testing of Solinoid valve complete in all respect | D21: p/job | E21: =K1*2 -> 96 | K21: 0.5
A22: 17 | B22: N.S | C22: Rehabilitation of Solinoid valve complete in all respect | D22: p/job | E22: =K1 -> 48 | K22: 1
A23: 18 | B23: N.S | C23: Supply Installation & Commissioning of 3way Multiport Valve, top & bottom distributers, complete in all respect | D23: p/job | E23: 42 | K23: 0.1
A24: 19 | B24: N.S | C24: Rehabilitation of 3way Multiport Valve, top & bottom distributers, complete in all respect | D24: p/job | E24: =K1*K24 -> 28.8 | K24: 0.6 | M24: =48*2 -> 96
A25: 20 | B25: N.S | C25: Supply, installation and Testing of Chemical Dosing Pump / Liquid Dosing Pump with working pressure 5 - 7 Bar Imported, along with 80 liter capacity tank complete in all respect Origin: Europe / USA / Asia or Equivalent Pressure: 5 -7 bar Tank Size: Maximum 80 liter Chemical Anti Sclanet: Food Grade | D25: p/job | E25: 20
A26: 21 | B26: N.S | C26: Supply and installation of Water Storage Tank, Capacity 2000 Liters, Material PE, Food Grade, 3 to 5 mm wall thickness, weight minimum 32 kg, complete in all respects Capacity : 2000 Litre minimum Material: Plastic food grade | D26: p/job | E26: 12
A27: 22 | B27: N.S | C27: Chemical Cleaning & repair of Water Storage tanks, complete in all respects at site | D27: p/job | E27: =K1-E26 -> 36
A28: 23 | B28: N.S | C28: Supply and installation of 2 No. float switch for Water Storage Tank, complete in all respect | D28: kg | E28: 24 | K28: 0.5
A29: 24 | B29: N.S | C29: Replacement of Activated Carbon media supply, installation and commissioning complete in all respect NSF Certified, Iodine No 850-1000 Material: Coconut Shell Origin: Sri Lanka / Thailand or Equivalent Size of Media: 1.2 - 1.6 mm Surface Area: 900 m2 / g Bulk Density: 440 - 540 kg / m3 Hardness No: 80 Ash Contents: 5 % Height of Gravel: 200 mm Media Bed Height: > 800 mm | D29: kg | E29: =50*(K1*60%) -> 1440 | K29: 50
A30: 25 | B30: N.S | C30: Replacement of Silica sand media supply, installation and commissioning complete in all respect Material: Quartz Silica Sand Size of Media: 0.85 - 2 mm Cleaning Process: Automatic, through PLC / Time Controller MPV | D30: kg | E30: =160*(K1*70%) -> 5376 | K30: 160
A31: 26 | B31: N.S | C31: Replacement of Natural Gravels media supply, installation and commissioning complete in all respect Material: Gravel media | D31: p/job | E31: =160*(K1*60%) -> 4608 | K31: 160
A32: 27 | B32: N.S | C32: Replacement of Granular Feric Hydroxide use for drinking water treatment with oxidation capacity of As3 to As5, commissioning complete in all respect Operating Pressure: 1.5 - 3 Bar Media: Grannular Ferric Hydroxide Origin: Europe / USA / German or Equivalent (NSF Certified) Cleaning Process: Automatic, through PLC / Time Controller MPV | D32: kg | E32: =160*(K1*40%) -> 3072
A33: 28 | B33: N.S | C33: Supply installation and commissioning of UV lamp rod with quartz complete in all respect Origin: Europe / USA / German or Equivalent | D33: p/job | E33: 20 | K33: 1
A34: 29 | B34: N.S | C34: Rehabilitation of Pipe and fittings, complete plant fitting in all respect | D34: no. | E34: 25 | K34: 0.5
A35: 30 | B35: N.S | C35: Supply installation & testing of Plastic water Taps with fussion joint, complete in all respect | D35: p/job | E35: =K1*5 -> 240 | K35: 5
A36: 31 | B36: N.S | C36: Rehabilitation of Plant Control Panel / RO Controller complete in all respect | D36: p/job | E36: 25 | K36: 1
A37: 32 | B37: N.S | C37: Supply & Installation of FRP Vessel (Size24 X 72) Origin: Europe / USA / German / China or Equivalent | D37: No. | E37: 1
A38: Grand Total | H38: =G38/1000000 -> 0
A39: Per Unit Cost = Grand Total / 48

Sheet UF 1 Rehab
A1: ='Bill No 4 RO 2000 New'!A1 -> PUNJAB SAAF PANI AUTHORITY | H1: 39402793 | I1: UF | J1: 2
H2: =G38 -> 0 | I2: Abnd
A3: LAHORE DISTRICT | H3: =H1-H2 -> 39402793 | I3: fed
A4: =GS!A4:E4 -> BILL OF QUANTITY | I4: Dys
A5: Bill No. 2: Rehabilitation of Ultra Filtration 1000 LPH | I5: fun
A6: Sr. No. | B6: MRS Ref. # | C6: Description | D6: Unit | E6: Qty. | F6: Unit Rate (PKR) | G6: Amount (PKR) | J6: =GS!#REF! -> #REF!
A7: 1 | B7: N.S | C7: Rehabilitation of Plant Skid frame and Finishing, complete in all respect, inclusive of Carriage to Site and Labor for Installation Frame: Frame stainless steel | D7: Per Plant | E7: 2 | F7: 10800 | G7: =F7*E7 -> 21600
A8: =A7+1 -> 2 | B8: N.S | C8: Membranes recovery (minimum 50%) with chemicals cleaning, including labour & testing, Complete in all respects, inclusive of Carriage to Site and Labor for Installation | D8: Per Plant | E8: 1 | F8: 19000 | G8: =F8*E8 -> 19000
A9: 3 | B9: N.S | C9: Supply, Installation & Commissioning of UF membrane/s Material of vessel: uPVC Removal Size: 0.02 Micron Manufacturer Type: Mutibore (seven bore) Manufecturer: GE Power (IMT) / INGE or Equivalent Filter vessel: uPVC Thickness: 5mm Membrane material: PES (Polystyrene) Countery Made: Europe / USA / Germany or Equivalent. Membrane Working pressure: 5 Bar Max Membrane Life: 5 years Bacterail Removal Effciency of UF membrane: 99.9999% log 6 Viruses Removal effciency of the UF membrane: 99.99% log 4 Auto Back wash Working pressure: 0-2 Bar Working temprature: Max 40 degree Celsius | D9: Per Plant | E9: 1 | F9: =304070 -> 304070 | G9: =F9*E9 -> 304070 | I9: 45000
A10: =A9+1 -> 4 | B10: N.S | C10: Supply Installation and commissioning of UF Feed Pump capacity of 4000 LPH, for 2000 LPH UF Plant, complete in all respect Operating Pressure: 2m3/h at minimum 10 m head, efficiency > 60% Sand Filter: Sand Filter with automatic Backwash Active Carbon Filter: Active Carbon Filter with automatic backwash | D10: No. | E10: 1 | F10: 94745 | G10: =F10*E10 -> 94745 | I10: 80000
A11: =A10+1 -> 5 | B11: N.S | C11: Supply Installation and commissioning of UF Back Wash Pump capacity of 4000 LPH, for 2000 LPH UF Plant, complete in all respect Operating Pressure: 2m3/h at minimum 10 m head, efficiency > 60% Sand Filter: Sand Filter with automatic Backwash Active Carbon Filter: Active Carbon Filter with automatic backwash | D11: No. | E11: 1 | F11: 94745 | G11: =F11*E11 -> 94745
A12: =A11+1 -> 6 | B12: N.S | C12: Rehabilitation of UF Feed water pump 4000 LPH, for 2000 LPH UF Plant, complete in all respect | D12: p/job | E12: 1 | F12: 18800 | G12: =F12*E12 -> 18800
A13: =A12+1 -> 7 | B13: N.S | C13: Rehabilitation of UF Feed water pump 4000 LPH, for 2000 LPH UF Plant, complete in all respect | D13: p/job | E13: 1 | F13: 18800 | G13: =F13*E13 -> 18800
A14: =A13+1 -> 8 | B14: N.S | C14: Supply Installation & commissioning of submersible pump 3HP including supporting clamp, pump coupling, cable clip, delivery pipe, cable complete in all respect. Discharge: 2000 LPH Minimum Operation Head: Up to 130 m. Origin: Europe / USA / German / Pakistan or Equivalent Pump Type: Submersible Pump Impeller Type: SS 304 Pump Efficiency: >60% Motor Starter: Star Delta | D14: p/job | E14: 1 | F14: 91365 | G14: =F14*E14 -> 91365
A15: =A14+1 -> 9 | B15: N.S | C15: Supply and installation of safety filter strainer | D15: p/job | E15: =J1 -> 2 | F15: 8405 | G15: =F15*E15 -> 16810
A16: =A15+1 -> 10 | B16: N.S | C16: Supply Installation and Testing of Online TDS meter complete with all respects | D16: p/job | E16: =J1 -> 2 | F16: 8695 | G16: =F16*E16 -> 17390
A17: =A16+1 -> 11 | B17: N.S | C17: Supply Installation and Testing of Pressure Switches complete with all respects | D17: p/job | E17: =J1 -> 2 | F17: 6375 | G17: =F17*E17 -> 12750
A18: =A17+1 -> 12 | B18: N.S | C18: Supply Installation and testing of Rota meter complete in all respect Origin: Europe / USA / German / Pakistan or Equiavlent Type: Rota Meter / Flow Type Material: Acryclic | D18: p/job | E18: =J1*2 -> 4 | F18: 5117 | G18: =F18*E18 -> 20468
A19: =A18+1 -> 13 | B19: N.S | C19: Supply Installation and Testing of pressure gauges, complete in all respect | D19: p/job | E19: 6 | F19: 3400 | G19: =F19*E19 -> 20400
A20: =A19+1 -> 14 | B20: N.S | C20: Supply Installation and testing of Analogue Water meter, complete in all respect | D20: p/job | E20: 2 | F20: 17540 | G20: =F20*E20 -> 35080
A21: =A20+1 -> 15 | B21: N.S | C21: Rehabilitation of Analogue Water meter including callibration, complete in all respect | D21: p/job | E21: =J1-E20 -> 0 | F21: 6000 | G21: =F21*E21 -> 0
A22: =A21+1 -> 16 | B22: N.S | C22: Supply Installation and Testing of Solinoid valve complete in all respect | D22: p/job | E22: 8 | F22: 8500 | G22: =F22*E22 -> 68000
A23: =A22+1 -> 17 | B23: N.S | C23: Rehabilitation of Solinoid valve complete in all respect | D23: p/job | E23: 4 | F23: 3200 | G23: =F23*E23 -> 12800
A24: =A23+1 -> 18 | B24: N.S | C24: Supply Installation & Commissioning of 3way Automatic Multiport Valve, top & bottom distributers, complete in all respect | D24: p/job | E24: 5 | F24: 40930 | G24: =F24*E24 -> 204650
A25: =A24+1 -> 19 | B25: N.S | C25: Rehabilitation of 3way Automatic Multiport Valve, top & bottom distributers, complete in all respect | D25: p/job | E25: 0 | F25: 8400 | G25: =F25*E25 -> 0
A26: =A25+1 -> 20 | B26: N.S | C26: Supply, installation and Testing of Chlorine Dosing Pump with working pressure 5 - 7 Bar imported, along with 80 liter capacity tank with all repects.complete in all respect Origin: Europe / USA / German or Equivalent Pressure: 5 -7 bar Tank Size: Maximum 80 liter Material: PVDF | D26: p/job | E26: 3 | F26: 89235 | G26: =F26*E26 -> 267705
A27: =A26+1 -> 21 | B27: N.S | C27: Supply and installation of Water Storage Tank, Capacity 2000 Liters, Material PE, Food Grade, 3 to 5 mm wall thickness, weight minimum 32 kg, complete in all respects Capacity : 2000 Litre minimum Material: Plastic food grade | D27: p/job | E27: 2 | F27: 45575 | G27: =F27*E27 -> 91150
A28: =A27+1 -> 22 | B28: N.S | C28: Chemical Cleaning & repair of Water Storage tank, complete in all respects at site | D28: p/job | E28: 4 | F28: 2500 | G28: =F28*E28 -> 10000
A29: =A28+1 -> 23 | B29: N.S | C29: Supply and installation of electric float switch for Water Storage Tank, complete in all respect No: 02 | D29: No. | E29: 6 | F29: 3625 | G29: =F29*E29 -> 21750
A30: =A29+1 -> 24 | B30: N.S | C30: Replacement of Activated Carbon media supply, installation and commissioning complete in all respect NSF Certified, Iodine No 850-1000 Material: Coconut Shell Origin: Sri Lanka / Thailand or Equivalent Size of Media: 1.2 - 1.6 mm Surface Area: 900 m2 / g Bulk Density: 440 - 540 kg / m3 Hardness No: 80 Ash Contents: 5 % Height of Gravel: 200 mm Media Bed Height: > 800 mm | D30: kg | E30: =40*(J1*60%) -> 48 | F30: 1510 | G30: =F30*E30 -> 72480
A31: =A30+1 -> 25 | B31: N.S | C31: Replacement of Silica sand media supply, installation and commissioning complete in all respect Material: Quartz Silica Sand Size of Media: 0.85 - 2 mm Cleaning Process: Automatic, through PLC / Time Controller MPV | D31: kg | E31: =100*(J1*60%) -> 120 | F31: 70 | G31: =F31*E31 -> 8400
A32: =A31+1 -> 26 | B32: N.S | C32: Replacement of Natural Gravels media supply, installation and commissioning complete in all respect Material: Gravel Media | D32: kg | E32: =100*(J1*60%) -> 120 | F32: 70 | G32: =F32*E32 -> 8400
A33: =A32+1 -> 27 | B33: N.S | C33: Replacement of Granular Feric Hydroxide use for drinking water treatment with oxidation capacity of As3 to As5, commissioning complete in all respect Operating Pressure: 1.5 - 3 Bar Media: Grannular Ferric Hydroxide Origin: Europe / USA / German or Equivalent (NSF Certified) Cleaning Process: Automatic, through PLC / Time Controller MPV | D33: kg | E33: =100*(J1*60%) -> 120 | F33: 2510 | G33: =F33*E33 -> 301200 | H33: WASA
A34: 26 | B34: N.S | C34: Supply Installation & Commissioning of Manual Valve 3Way complete in all respect | D34: p/job | E34: 0 | F34: 22210 | G34: =F34*E34 -> 0
A35: =A34+1 -> 27 | B35: N.S | C35: Rehabilitation of Pipe and fittings, complete plant fitting in all respect | D35: Per Plant | E35: 2 | F35: 22000 | G35: =F35*E35 -> 44000
A36: =A35+1 -> 28 | B36: N.S | C36: Supply installation & testing of Plastic water Taps with fusion joint, complete in all respect | D36: p/job | E36: =J1*3 -> 6 | F36: 585 | G36: =F36*E36 -> 3510
A37: =A36+1 -> 29 | B37: N.S | C37: Rehabilitation of Plant control panel with PLC & HMI complete in all respect | D37: Per Plant | E37: 2 | F37: 46000 | G37: =F37*E37 -> 92000
A38: Grand Total | H38: =G38-#REF! -> #REF!
D39: Per Unit Cost | G39: =G38/J1 -> 0 | H39: =G39-#REF! -> #REF!
A44: Assistant Manager (P&MC) - CZ | D44: Deputy Manager (P&MC) - CZ
A45: Punjab Aab-e-Pak Authority | D45: Punjab Aab-e-Pak Authority

Sheet U4
A1: ='R5'!A1:G2 -> PUNJAB SAAF PANI AUTHORITY | H1: 39402793 | I1: UF | J1: 9
A2: ='R5'!A2:G2 -> REHABILITATION & O&M OF DYSFUNCTIONAL WATER FILTRATION PLANTS INSTALLED IN DIVISON FAISALABAD | H2: =G35 -> 0 | I2: Abnd
A3: =GS!A4:E4 -> BILL OF QUANTITY | I3: Dys
A4: Bill No. 4: Rehabilitation of Ultra Filtration 4000 LPH | I4: fun
A5: Sr. No. | B5: MRS Ref. # | C5: Description | D5: Unit | E5: Qty. | F5: Unit Rate (PKR) | G5: Amount (PKR) | J5: =GS!#REF! -> #REF!
A6: 1 | B6: N.S | C6: Rehabilitation of Plant Skid frame and Finishing, complete in all respect, inclusive of Carriage to Site and Labor for Installation Frame: Frame stainless steel | D6: Per Plant | E6: 9 | H6: 10800
A7: 2 | B7: N.S | C7: Membranes recovery with chemicals cleaning, including labour & testing, Complete in all respects, inclusive of Carriage to Site and Labor for Installation | D7: Per Plant | E7: 5 | H7: 19000
A8: 3 | B8: N.S | C8: Supply, Installation & Commissioning of UF membrane including membrane housing complete in all respect Origin: Europe / USA or Equivalent. Removal Size: 0.02 Micron Certification: NSF Material of vessel: uPVC Thickness: 5mm Membrane material: PVDF (Polyvinylidene flouride)/ PES (Polyethersulfone) - Multibore technology Membrane Working pressure: upto 5 Bar Membrane Life: Minimum 5 years Bacterail Removal effciency of UF membrane: 99.9999% log 6 Viruses Removal effciency of UF membrane: 99.99% log 4 Auto Backwash enabled Working temprature: Max 40 degree Celsius | D8: Per Plant | E8: 4 | H8: =304070*4 -> 1216280 | I8: 45000
A9: 4 | B9: N.S | C9: Supply Installation and commissioning of 4000 LPH Feed Pump for 4000 LPH UF WFP, complete in all respect Origin: Europe / USA / Asia or Equivalent Discharge: 4000 LPH Pump Type: Vertical / Horizontal Low Pressure Pump Impeller Type: S.S. 304 Operating Head: Up to 05 Barg Pump Efficiency: > 40% Motor Starter: DOL | D9: No. | E9: 5 | H9: 94745 | I9: 80000
A10: 5 | B10: N.S | C10: Rehabilitation of UF Feed water pump 4000 LPH, for 4000 LPH UF Plant, complete in all respect | D10: p/job | E10: 4 | H10: 18800
A11: 6 | B11: N.S | C11: Supply Installation & commissioning of submersible pump 3HP including supporting clamp, pump coupling, cable clip, delivery pipe, cable complete in all respect. Discharge: 3000-5000 LPHSupply Installation & commissioning of submersible pump 3HP including supporting clamp with steel cable, pump coupling, cable clip, delivery pipe, electric cable complete in all respect. Origin: Europe / USA/ Asia or Equivalent Minimum Discharge: 2000 LPH Minimum Operation Head: Up to 130 m. Pump Type: Submersible Pump Impeller Type: S.S. 304 Motor Starter: DOL | D11: p/job | E11: 4 | H11: 91365
A12: 7 | B12: N.S | C12: Supply and installation of S.S safety filter strainer | D12: p/job | E12: =J1 -> 9 | H12: 8405
A13: 8 | B13: N.S | C13: Supply Installation and Testing of Pressure Switches complete with all respects | D13: p/job | E13: =J1 -> 9 | H13: 6375
A14: 9 | B14: N.S | C14: Supply Installation and testing of Rota meter complete in all respect Origin: Europe / USA / German / Pakistan or Equiavlent Type: Rota Meter / Flow Type Material: Acryclic | D14: p/job | E14: =J1*2 -> 18 | H14: 5117
A15: 10 | B15: N.S | C15: Supply Installation and Testing of pressure gauges, complete in all respect | D15: p/job | E15: =J1*3 -> 27 | H15: 3400
A16: 11 | B16: N.S | C16: Supply Installation and testing of Analogue Water meter, complete in all respect | D16: p/job | E16: =J1 -> 9 | H16: 17540
A17: 12 | B17: N.S | C17: Rehabilitation of Analogue Water meter including callibration, complete in all respect | D17: p/job | E17: 0 | H17: 6000
A18: 13 | B18: N.S | C18: Supply Installation and Testing of Solinoid valve complete in all respect | D18: p/job | E18: =J1*2 -> 18 | H18: 8500
A19: 14 | B19: N.S | C19: Rehabilitation of Solinoid valve complete in all respect | D19: p/job | E19: =J1*2 -> 18 | H19: 3200
A20: 15 | B20: N.S | C20: Supply Installation & Commissioning of 3way Automatic Multiport Valve, top & bottom distributers, complete in all respect | D20: p/job | E20: =J1 -> 9 | H20: 40930
A21: 16 | B21: N.S | C21: Rehabilitation of 3way Automatic Multiport Valve, top & bottom distributers, complete in all respect | D21: p/job | E21: =J1 -> 9 | H21: 8400
A22: 17 | B22: N.S | C22: Supply, installation and Testing of Chlorine Dosing Pump with working pressure 5 - 7 Bar imported, along with 80 liter capacity tank with all repects.complete in all respect Origin: Europe / USA / Asia or Equivalent Pressure: 5 -7 bar Tank Size: Maximum 80 liter Material: PVDF | D22: p/job | E22: 4 | H22: 89235
A23: 18 | B23: N.S | C23: Supply and installation of Water Storage Tank, Capacity 2000 Liters, Material PE, Food Grade, 3 to 5 mm wall thickness, weight minimum 32 kg, complete in all respects Capacity : 2000 Litre minimum Material: Plastic food grade | D23: p/job | E23: =J1 -> 9 | H23: 45575
A24: 19 | B24: N.S | C24: Chemical Cleaning & repair of Water Storage tank, complete in all respects at site | D24: p/job | E24: =J1*2-E23 -> 9 | H24: 2500
A25: 20 | B25: N.S | C25: Supply and installation of 2 No. electric float switch for Water Storage Tank, complete in all respect | D25: No. | E25: =J1 -> 9 | H25: 3625
A26: 21 | B26: N.S | C26: Replacement of Activated Carbon media supply, installation and commissioning complete in all respect NSF Certified, Iodine No 850-1000 Material: Coconut Shell Origin: Sri Lanka / Thailand or Equivalent Size of Media: 1.2 - 1.6 mm Surface Area: 900 m2 / g Bulk Density: 440 - 540 kg / m3 Hardness No: 80 Ash Contents: 5 % Height of Gravel: 200 mm Media Bed Height: > 800 mm | D26: kg | E26: =60*(J1*60%) -> 324 | H26: 1510
A27: 22 | B27: N.S | C27: Replacement of Silica sand media supply, installation and commissioning complete in all respect Material: Quartz Silica Sand Size of Media: 0.85 - 2 mm Cleaning Process: Automatic, through PLC / Time Controller MPV | D27: kg | E27: =380*(J1*70%) -> 2394 | H27: 70
A28: 23 | B28: N.S | C28: Replacement of Natural Gravels media supply, installation and commissioning complete in all respect Material: Gravel Media | D28: kg | E28: =380*(J1*60%) -> 2052 | H28: 70
A29: 24 | B29: N.S | C29: Replacement of Granular Feric Hydroxide use for drinking water treatment with oxidation capacity of As3 to As5, commissioning complete in all respect Operating Pressure: 1.5 - 3 Bar Media: Grannular Ferric Hydroxide Origin: Europe / USA / German or Equivalent (NSF Certified) Cleaning Process: Automatic, through PLC / Time Controller MPV | D29: kg | E29: =320*(J1*40%) -> 1152 | H29: 2510
A30: 25 | B30: N.S | C30: Supply installation and commissioning of UV lamp rod with quartz complete in all respect Origin: Europe / USA / German or Equivalen | D30: No. | E30: 4
A31: 26 | B31: N.S | C31: Rehabilitation of Pipe and fittings, complete plant fitting in all respect | D31: Per Plant | E31: 5 | H31: 22000
A32: 27 | B32: N.S | C32: Supply installation & testing of Plastic water Taps with fusion joint, complete in all respect | D32: p/job | E32: =J1*5 -> 45 | H32: 585
A33: 28 | B33: N.S | C33: Rehabilitation of Plant control panel with PLC & HMI complete in all respect | D33: Per Plant | E33: 5 | H33: 46000
A34: 29 | B34: N.S | C34: Supply & Installation of FRP Vessel (Size24 X 72) Origin: Europe / USA / German / China or Equivalent | D34: No. | E34: 1
A35: Grand Total
A36: Per Unit Cost = Grand Total / 9

Sheet B3 R1 New
A1: ='R5'!A1 -> PUNJAB SAAF PANI AUTHORITY
A2: LAHORE DISTRICT
A3: ENGINEERING COST ESTIMATE
A4: Bill No 3 : Installation of Reverse Osmosis 1000 LPH
A5: RO 1000 LPH Plant
A6: Sr. No | B6: Description | C6: Qty | D6: Unit Rate (Rs) | E6: Amount (Rs)
A7: 1 | B7: Supply, transport, erection, installation, testing & commissioning of 1,000 L/H Reverse Osmosis (RO) Plant for TDS removal along with all other contaminants, including carriage, loading/unloading charges inclusive of all taxes conforming to Mentioned in Technical specifications of filtration plants. Control PLC GSM/GPRS/ SCADA enabled. The unit should be composed of Raw and Product water tanks (1000 Liter capacity for each) Feed and High Pressure Pump, pressure gauges, variable area flow meter for raw water and for product water totalizer/ water meter, pressure safety switch and valves, Multiport valves, safety filter strainers/cartridges filter, sand filter, carbon filters. System should be fully automatic. Provission of UV system, Anti secalent system with Anti scalent PVDF based dosing Pumps and chemical tank. The complete plant should be able to operate/backwash automatically through Automatic Multiport Valve operated by PLC with same feed pump based system. All type of piping and instrumentation shall be considered as part of filtration plant complete in all respect. The plant should be supplied to provide the treated water as per the WHO limits (strict compliance). The specifications along with equipment and accessories properly mounted in the frame/skid are given below: | C7: 1 | D7: 2129660 | E7: 2129660
A8: 2 | B8: Raw Water Feed Pump
B9: Discharge: 2000 LPH Minimum Operation Head: 04 Barg Maximum. Origin: Europe / USA / German / Pakistan or Equivalent Pump Type: Vertical / Horizontal Low Pressure Pump Impeller Type: SS 304 Discharge: As per the capacity of Plant (2000 LPH) Operating Head: Up to 06 Barg Pump Efficiency: >60% Motor Starter: Star Delta
A10: 3 | B10: Submersible Pump
B11: Discharge: 2000 LPH Minimum Operation Head: Up to 130 m. Origin: Europe / USA / German / Pakistan or Equivalent Pump Type: Submersible Pump Impeller Type: SS 304 Discharge: As per the capacity of Plant (2000 LPH) Pump Efficiency: >60% Motor Starter: Star Delta
A12: 4 | B12: Pre-Filtration
A13: 4 (a) | B13: Sand Filter
B14: Material: FRP Origin: Europe / USA / German or Equivalent Fitration Rate: 6 - 15 m/hr Vessel Certification: NSF Operating Pressure Max: Up to 06 Barg
A15: 4 (b) | B15: Filter Media Sand
B16: Material: Quartz Silica Sand Origin: Europe / USA / German or Equivalent Size of Media: 0.6 - 0.8 mm Cleaning Process: Automatic, through PLC / Time Controller MPV
A17: 4 (c) | B17: Activated Carbon Filter
B18: Material: FRP Origin: Europe / USA / German or Equivalent Media & Vessel Certification: NSF Fitration Rate: 5 - 15 m/hr Operating Pressure Max: Up to 06 Barg
A19: 4 (d) | B19: Filter Media Carbon
B20: Material: Coconut Shell Origin: Sri Lanka / Thailand or Equivalent Size of Media: 1.2 - 1.6 mm Surface Area: 900 m2 / g Bulk Density: 440 - 540 kg / m3 Hardness No: 80 Ash Contents: 5 % Height of Gravel: 200 mm Media Bed Height: > 800 mm
A21: 4 (e) | B21: Cartridge Filter
B22: Size: 20 Inches / As per Flow Porosity: 1-5 micron Material: High pressure Plastic Melt Blown PE
A23: 5 | B23: RO Skid
B24: Frame: Stainless Steel
A25: 6 | B25: High Pressure Pump multistage
B26: Discharge: 2000 LPH Operating Head: Upto 06 Barg Pump Type: Vertical High Pressure Pump Origin: Europe / USA / German or Equivalent Impeller material: S.S. 304 Pump Efficiency: >60% Motor Starter: Star Delta Motor Temperature Class: 45 degree Celsius Make: Lewara / Grundfous / KSB / CNP / Vilo or Equivalent
A27: 7 | B27: RO Housing
B28: Material: FRP Certification: NSF
A29: 8 | B29: RO Membrane
B30: Origin: Europe / USA / German or Equivalent (Assembly of Parts may be Pakistan) No. of Stages: Up to 2 No. of Membranes: Up to 4 Certification: NSF Stable salt rejection: Minimum - 99% Capacity: 1000 LPH For Permeate water Capable for TDS: Upto 5000 mg/l Recovery: Should be More than 50% Ambient Temperature: Upto 45 degree celsius Life of RO Membrane: Minimum 03 years Pressure Vessels: As per required Pressure Rating: Upto 17 Barg
A31: 9 | B31: Automatic PLC Panel
B32: Origin: Europe / USA / German or Equivalent Programming: Fully automatic with breaker, timer and relays complete in all respects HMI display: For PLC - 10" minimum size with touch screen (Fully automatic control of plant) SCADA enable
A33: 10 | B33: Anti Scalent + Injection System
B34: Origin: Europe / USA / German or Equivalent Pressure: 5 -7 bar Tank Size: Maximum 80 liter Chemical Anti Sclanet: Food Grade Material: PVDF
A35: 11 | B35: UV Light with SS casing
B36: Origin: Europe / USA / German or Equivalent Material of Casing: SS 304 / 316 Operating Pressure: 04 Barg Ambient Temperature: Upto 45 degree celsius
A37: 12 | B37: Raw & Product water tank (1000 L) Each
B38: Material: PE Food Grade
A39: 13 | B39: Level Meter / Float Valve / Switch Electronic
B40: No: 02 Origin: Europe / USA / German or Equiavlent
A41: 14 | B41: Water Flow Meter
B42: No: 02 Origin: Europe / USA / German or Equiavlent Type: Rota Meter / Flow Type Material: Acryclic
A43: 15 | B43: Pressure Gauges
A44: 16 | B44: Online TDS meter
A45: 17 | B45: All fittings of PVC Sch.80
A46: 18 | B46: Pressure Regulation Switch
A47: 19 | B47: Auto on/off Switch for Pump
A48: 20 | B48: Automatic Back Wash system for Membrane
A49: 21 | B49: Including any item required for Filtration Plant if required
A50: Total | E50: =E7 -> 2129660
A56: Assistant Manager (P&MC) - CZ
A57: Punjab Aab-e-Pak Authority

Sheet B4 R2 New
A1: ='R5'!A1 -> PUNJAB SAAF PANI AUTHORITY
A2: LAHORE DISTRICT
A3: ENGINEERING COST ESTIMATE
A4: Bill No 4 : Installation of Reverse Osmosis 2000 LPH
A5: RO 2000 LPH Plant
A6: Sr No | B6: Description | C6: Qty | D6: Unit Rate (Rs) | E6: Amount (Rs)
A7: 1 | B7: Supply, transport, erection, installation, testing & commissioning of 2,000 L/H Reverse Osmosis (RO) Plant for TDS removal along with all other contaminants, including carriage, loading/unloading charges inclusive of all taxes conforming to Mentioned in Technical specifications of filtration plants. Control PLC GSM/GPRS/ SCADA enabled. The unit should be composed of Raw and Product water tanks (2000Liter capacity for each) Feed and High Pressure Pump, pressure gauges, variable area flow meter for raw water and for product water totalizer/ water meter, pressure safety switch and valves, Multiport valves, safety filter strainers/cartridges filter, sand filter, carbon filters. System should be fully automatic. Provission of UV system, Anti secalent system with Anti secalent PVDF based dosing Pumps and chemical tank. The complete plant should be able to operate/backwash automatically through Automatic Multiport Valve operated by PLC with same feed pump based system. All type of piping and instrumentation shall be considered as part of filtration plant complete in all respect. The plant should be supplied to provide the treated water as per the WHO limits (strict compliance). The specifications along with equipment and accessories properly mounted in the frame/skid are given below: | C7: 1 | D7: 2831355 | E7: 2831355
A8: 2 | B8: Raw Water Feed Pump
B9: Discharge: 4000 LPH Minimum Operation Head: 04 Barg Maximum. Origin: Europe / USA / German / Pakistan or Equivalent Pump Type: Vertical / Horizontal Low Pressure Pump Impeller Type: SS 304 Discharge: As per the capacity of Plant (4000 LPH) Operating Head: Up to 06 Barg Pump Efficiency: >60% Motor Starter: Star Delta
A10: 3 | B10: Submersible Pump
B11: Discharge: 4000 LPH Minimum Operation Head: Up to 130 m. Origin: Europe / USA / German / Pakistan or Equivalent Pump Type: Submersible Pump Impeller Type: SS 304 Discharge: As per the capacity of Plant (4000 LPH) Pump Efficiency: >60% Motor Starter: Star Delta
A12: 4 | B12: Pre-Filtration
A13: 4 (a) | B13: Sand Filter
B14: Material: FRP Origin: Europe / USA / German or Equivalent Fitration Rate: 6 - 15 m/hr Vessel Certification: NSF Operating Pressure Max: Up to 06 Barg
A15: 4 (b) | B15: Filter Media Sand
B16: Material: Quartz Silica Sand Origin: Europe / USA / German or Equivalent Size of Media: 0.6 - 0.8 mm Cleaning Process: Automatic, through PLC / Time Controller MPV
A17: 4 (c) | B17: Activated Carbon Filter
B18: Material: FRP Origin: Europe / USA / German or Equivalent Media & Vessel Certification: NSF Fitration Rate: 5 - 15 m/hr Operating Pressure Max: Up to 06 Barg
A19: 4 (d) | B19: Filter Media Carbon
B20: Material: Coconut Shell Origin: Sri Lanka / Thailand or Equivalent Size of Media: 1.2 - 1.6 mm Surface Area: 900 m2 / g Bulk Density: 440 - 540 kg / m3 Hardness No: 80 Ash Contents: 5 % Height of Gravel: 200 mm Media Bed Height: > 800 mm
A21: 4 (e) | B21: Cartridge Filter
B22: Size: 20 Inches / As per Flow Porosity: 1-5 micron Material: High pressure Plastic Melt Blown PE
A23: 5 | B23: RO Skid
B24: Frame: Stainless Steel
A25: 6 | B25: High Pressure Pump multistage
B26: Discharge: 4000 LPH Operating Head: Upto 06 Barg Pump Type: Vertical High Pressure Pump Origin: Europe / USA / German or Equivalent Impeller material: S.S. 304 Pump Efficiency: >60% Motor Starter: Star Delta Motor Temperature Class: 45 degree Celsius Make: Lewara / Grundfous / KSB / CNP / Vilo or Equivalent
A27: 7 | B27: RO Housing
B28: Material: FRP Certification: NSF
A29: 8 | B29: RO Membrane
B30: Origin: Europe / USA / German or Equivalent (Assembly of Parts may be Pakistan) No. of Stages: Up to 4 No. of Membranes: Up to 8 Certification: NSF Stable salt rejection: Minimum - 99% Capacity: 2000 LPH For Permeate water Capable for TDS: Upto 5000 mg/l Recovery: Should be More than 50% Ambient Temperature: Upto 45 degree celsius Life of RO Membrane: Minimum 03 years Pressure Vessels: As per required Pressure Rating: Upto 17 Barg
A31: 9 | B31: Automatic PLC Panel
B32: Origin: Europe / USA / German or Equivalent Programming: Fully automatic with breaker, timer and relays complete in all respects HMI display: For PLC - 10" minimum size with touch screen (Fully automatic control of plant) SCADA enable
A33: 10 | B33: Anti Scalent + Injection System
B34: Origin: Europe / USA / German or Equivalent Pressure: 5 -7 bar Tank Size: Maximum 80 liter Chemical Anti Sclanet: Food Grade Material: PVDF
A35: 11 | B35: UV Light with SS casing
B36: Origin: Europe / USA / German or Equivalent Material of Casing: SS 304 / 316 Operating Pressure: 04 Barg Ambient Temperature: Upto 45 degree celsius
A37: 12 | B37: Raw & Product water tank (2000 L) Each
B38: Material: PE Food Grade
A39: 13 | B39: Level Meter / Float Valve / Switch Electronic
B40: No: 02 Origin: Europe / USA / German or Equiavlent
A41: 14 | B41: Water Flow Meter
B42: No: 02 Origin: Europe / USA / German or Equiavlent Type: Rota Meter / Flow Type Material: Acryclic
A43: 15 | B43: Pressure Gauges
A44: 16 | B44: Online TDS meter
A45: 17 | B45: All fittings of PVC Sch.80
A46: 18 | B46: Pressure Regulation Switch
A47: 19 | B47: Auto on/off Switch for Pump
A48: 20 | B48: Automatic Back Wash system for Membrane
A49: 21 | B49: Including any item required for Filtration Plant if required
A50: Total | E50: =E7 -> 2831355
A56: Assistant Manager (P&MC) - CZ
A57: Punjab Aab-e-Pak Authority

Sheet B5 U2 New
A1: ='R5'!A1 -> PUNJAB SAAF PANI AUTHORITY
A2: LAHORE DISTRICT
A3: ENGINEERING COST ESTIMATE
A4: Bill No 5 : Installation of Ultra Filtration 2000 LPH
A5: Specification of UF 2000 LPH Plants
A6: Sr No | B6: Description | C6: Specifications | D6: Qty | E6: Unit Rate (Rs) | F6: Amount (Rs)
B7: Supply, Install, Testing and Commissioning of water Ultra filtration plant, capable of removing Turbidity, Arsenic, Bacteria & Viruses, having capacity of 2000 litres/ hour and fully automated (Auto filtration, flush and backwash process) complete in all respects. Pressure Gauges, Flow Meters and Level Sensors, Multiport and Solenoid Valves, Stainles Steel 304 Frame, All Pipe work including feed water pipe line connection to the delivery pipeline and necessary gate and flow regulating valves, water taps including pipework & uPVC pipe to drain off the spent/ waste water. | D7: 1 | E7: 2634290 | F7: 2634290
A8: 1 | B8: Pre Filtration
B9: Pressure Sand filtration
B10: Constant flow valve for fitration backwash | C10: 3way automatic valve with automatic back wash system
B11: Sand effective size | C11: 0.85 - 2 mm
B12: Vessel Material | C12: Material FRP, Make Pentair / Frotec / G Fiber or Equivalent NSF certified company
B13: Vessel diameter / height | C13: size 16" x 65" / Size 24" x 72"
A14: 2 | B14: Activited Carbon filtration
B15: Carbon Media | C15: Iodine No 850-1000 Material: Coconut Shell Origin: Sri Lanka / Thailand or Equivalent Size of Media: 1.2 - 1.6 mm Surface Area: 900 m2 / g Bulk Density: 440 - 540 kg / m3 Hardness No: 80 Ash Contents: 5 % Height of Gravel: 200 mm Media Bed Height: > 800 mm
B16: Vessel Material | C16: Material FRP, Make Pentair / Frotec / G Fiber or Equivalent NSF certified company
B17: Vessel diameter / height | C17: size 16" x 65" / Size 24" x 72"
A18: 3 | B18: Arscenic Removal Filter
B19: Arsenic Media | C19: Grannular Ferric Hydroxide oxidation capacity of As3 to As5, Operating Pressure: 1.5 - 3 Bar Origin: Europe / USA / German or Equivalent (NSF Certified) Cleaning Process: Automatic, through PLC / Time Controller MPV
B20: Vessel Material | C20: Material FRP, Make Pentair / Frotec / G Fiber or Equivalent NSF certified company
B21: Vessel diameter / height | C21: size 16" x 65" / Size 24" x 72"
A22: 4 | B22: UF Unit
B23: Mounting / Frame | C23: Frame stainless steel SS 304
B24: Pre treatment objectives turbidity | C24: < 1 NTU
A25: 5 | B25: Well pump or / with feed pump | C25: Stainless Steel, NEMA Insulation Class F and Pump Efficiency > 50%
A26: 6 | B26: UF Membrane
B27: Membrane Type | C27: Material of vessel: uPVC Removal Size: 0.02 Micron Manufacturer Type: Mutibore (seven bore) Manufecturer: GE Power (IMT) / INGE or Equivalent Filter vessel: uPVC Thickness: 5mm Membrane material: PES (Polystyrene) Country Made: Europe / USA / Germany or Equivalent. Membrane Working pressure: 5 Bar Max Membrane Life: 5 years Bacterail Removal Effciency of UF membrane: 99.9999% log 6 Viruses Removal effciency of the UF membrane: 99.99% log 4 Auto Back wash Working pressure: 0-2 Bar Working temprature: Max 40 degree Celsius
B28: Trans membrane Pressure (TMP) | C28: <10 bar
B29: Piping for Units | C29: All fittings of UPVC Sch.80
A30: 7 | B30: Dosing Pump | C30: Operational / rinsing
B31: Dosing Pump working pressure | C31: 5 - 7 bar
B32: Chemical Used | C32: Anti Scalant Food Grade
B33: Pre Treatment | C33: Disinfection by UV radiation
B34: Bacteria | C34: Below Detection level
A35: 8 | B35: Control System | C35: Automatic PLC Panel / Micro processor based embedded system
C36: Programming fully automatic with breaker, timer and relays complete in all respects
C37: Visual Display Unit with Membrane Keypad / HMI with Touch interface
C38: Fully automatic control of plant
C39: SCADA enable
A40: 9 | B40: Raw water tank | C40: Raw water tank
C41: Capacity 2000 Litre minimum
C42: Material Plastic food grade
C43: Float Switch
A44: 10 | B44: Clean Water Storage Tank | C44: Product water tank
C45: Material Plastic food grade
C46: Capacity 2000 Litre minimum
C47: Float Switch
A48: 11 | B48: Waste disposal | C48: Discharge in the sanitory sewerage system
A49: Total | F49: =F7 -> 2634290
A55: Assistant Manager (P&MC) - CZ | C55: Deputy Manager (P&MC) - CZ
A56: Punjab Aab-e-Pak Authority | C56: Punjab Aab-e-Pak Authority

Sheet Bill no 3 RO 1000 New
A1: ='R5'!A1 -> PUNJAB SAAF PANI AUTHORITY
A2: LAHORE DISTRICT
A3: ENGINEER'S COST ESTIMATE
A4: Bill No 3 : Installation of Reverse Osmosis 1 m3/hr
A5: Sr, No | B5: Description | C5: Unit | D5: Quantity | E5: Unit Rate (RS) | F5: Amount (RS)
A6: 1 | B6: ='RA RO1000'!B76 -> Supply installation and commissioning of 1000 L/H Reverse Osmosis (RO) Plant for TDS removal up to 5000 mg/l and inclusive of all taxes conforming to standard specifications according to the Punjab Aab-e-Pak Authority. The specifications along with equipment and accessories properly mounted in the SS frame/skid. | C6: No. | D6: 1 | E6: ='RA RO1000'!F82 -> 1929660 | F6: =D6*E6 -> 1929660
B7: Total Capital | F7: =F6 -> 1929660
A14: Assistant Manager (P&MC) - CZ | C14: Deputy Manager (P&MC) - CZ
A15: Punjab Aab-e-Pak Authority | C15: Punjab Aab-e-Pak Authority

Sheet Bill No 4 RO 2000 New
A1: ='Bill No 2 RO 2000 Rehab'!A1 -> PUNJAB SAAF PANI AUTHORITY
A2: LAHORE DISTRICT
A3: ENGINEER'S COST ESTIMATE
A4: Bill No 4 : Installation of Reverse Osmosis 2 m3/hr
A5: Sr, No | B5: Description | C5: Unit | D5: Quantity | E5: Unit Rate (RS) | F5: Amount (RS)
A6: 1 | B6: ='RA RO2000'!B73 -> Supply installation and commissioning of 2000 L/H Reverse Osmosis (RO) Plant for TDS removal up to 5000 mg/l and inclusive of all taxes conforming to standard specifications according to the Punjab Aab-e-Pak Authority. The specifications along with equipment and accessories properly mounted in the SS frame/skid. | C6: No. | D6: 1 | E6: ='RA RO2000'!F79 -> 2631355 | F6: =D6*E6 -> 2631355
B7: Total Capital | F7: =F6 -> 2631355
A14: Assistant Manager (P&MC) - CZ | C14: Deputy Manager (P&MC) - CZ
A15: Punjab Aab-e-Pak Authority | C15: Punjab Aab-e-Pak Authority

Sheet Bill No 5 UF 2000 New
A1: ='U2'!A1 -> PUNJAB SAAF PANI AUTHORITY
A2: LAHORE DISTRICT
A3: ENGINEER'S COST ESTIMATE
A4: Bill No 5 : Installation of Ultra Filtration 2 m3/hr
A5: Sr, No | B5: Description | C5: Unit | D5: Quantity | E5: Unit Rate (RS) | F5: Amount (RS)
A6: 1 | B6: ='RA UF2000'!B58 -> Supply installation and commissioning of 2000 L/H Ultra Filtration (UF) Plant for removal of Bacteriological & other contaminants and inclusive of all taxes conforming to standard specifications of filtration plants. The specifications along with equipment and accessories properly mounted in the SS frame/skid. | C6: No. | D6: 1 | E6: ='RA UF2000'!F64 -> 2534290 | F6: =D6*E6 -> 2534290
B7: Total Capital | F7: =F6 -> 2534290
A14: Assistant Manager (P&MC) - CZ | C14: Deputy Manager (P&MC) - CZ
A15: Punjab Aab-e-Pak Authority | C15: Punjab Aab-e-Pak Authority

Sheet NEW MF 2000
A1: ='RO Rehab 500LPH'!A1 -> REHABILITATION OF WATER FILTRATION PLANTS IN DISTRICT BAHAWALPUR
A2: INSTALATION OF MF 2000 LPH WFP
A3: Sr, No | B3: Description | C3: Unit | D3: Quantity | E3: Unit Rate (RS) | F3: Amount (RS)
A4: 1 | B4: ='RA UF2000'!#REF! -> #REF! | C4: No. | D4: 1 | E4: ='RA MF2000'!F35 -> 637375 | F4: =D4*E4 -> 637375
B5: Total Capital | F5: =F4 -> 637375
B6: PRA 5% | F6: =F5*5% -> 31868.75
B7: Grand Total :- | F7: =F5+F6 -> 669243.75

Sheet U2
A1: ='R5'!A1:G2 -> PUNJAB SAAF PANI AUTHORITY | H1: 39402793 | I1: UF | J1: 3
A2: ='R5'!A2:G2 -> REHABILITATION & O&M OF DYSFUNCTIONAL WATER FILTRATION PLANTS INSTALLED IN DIVISON FAISALABAD | H2: =G35 -> 0 | I2: Abnd
A3: =GS!A4:E4 -> BILL OF QUANTITY | I3: Dys
A4: Bill No. 5: Rehabilitation of Ultra Filtration 2000 LPH | I4: fun
A5: Sr. No. | B5: MRS Ref. # | C5: Description | D5: Unit | E5: Qty. | F5: Unit Rate (PKR) | G5: Amount (PKR) | J5: =GS!#REF! -> #REF!
A6: 1 | B6: N.S | C6: Rehabilitation of Plant Skid frame and Finishing, complete in all respect, inclusive of Carriage to Site and Labor for Installation Frame: Frame stainless steel | D6: Per Plant | E6: 3 | H6: 10800
A7: 2 | B7: N.S | C7: Membranes recovery with chemicals cleaning, including labour & testing, Complete in all respects, inclusive of Carriage to Site and Labor for Installation | D7: Per Plant | E7: 2 | H7: 19000
A8: 3 | B8: N.S | C8: Supply, Installation & Commissioning of UF membrane including membrane housing complete in all respect Origin: Europe / USA or Equivalent. Removal Size: 0.02 Micron Certification: NSF Material of vessel: uPVC Thickness: 5mm Membrane material: PVDF (Polyvinylidene flouride)/ PES (Polyethersulfone) - Multibore technology Membrane Working pressure: upto 5 Bar Membrane Life: Minimum 5 years Bacterail Removal effciency of UF membrane: 99.9999% log 6 Viruses Removal effciency of UF membrane: 99.99% log 4 Auto Backwash enabled Working temprature: Max 40 degree Celsius | D8: Per Plant | E8: 1 | H8: =304070*2 -> 608140 | I8: 45000
A9: 4 | B9: N.S | C9: Supply Installation and commissioning of 2000 LPH Feed Pump for 2000 LPH UF WFP, complete in all respect Origin: Europe / USA / Asia or Equivalent Discharge: 2000 LPH Pump Type: Vertical / Horizontal Low Pressure Pump Impeller Type: S.S. 304 Operating Head: Up to 05 Barg Pump Efficiency: > 40% Motor Starter: DOL | D9: No. | E9: 1 | H9: 94745 | I9: 80000
A10: 5 | B10: N.S | C10: Rehabilitation of UF Feed water pump 4000 LPH, for 2000 LPH UF Plant, complete in all respect | D10: p/job | E10: 2 | H10: 18800
A11: 6 | B11: N.S | C11: Supply Installation & commissioning of submersible pump 3HP including supporting clamp with steel cable, pump coupling, cable clip, delivery pipe, electric cable complete in all respect. Origin: Europe / USA/ Asia or Equivalent Minimum Discharge: 2000 LPH Minimum Operation Head: Up to 130 m. Pump Type: Submersible Pump Impeller Type: S.S. 304 Motor Starter: DOL | D11: p/job | E11: 3 | H11: 91365
A12: 7 | B12: N.S | C12: Supply and installation of S.S safety filter strainer | D12: p/job | E12: =J1+K1 -> 3 | H12: 8405
A13: 8 | B13: N.S | C13: Supply Installation and Testing of Pressure Switches complete with all respects | D13: p/job | E13: =J1+K1 -> 3 | H13: 6375
A14: 9 | B14: N.S | C14: Supply Installation and testing of Rota meter complete in all respect Origin: Europe / USA / German / Pakistan or Equiavlent Type: Rota Meter / Flow Type Material: Acryclic | D14: p/job | E14: =J1+K1 -> 3 | H14: 5117
A15: 10 | B15: N.S | C15: Supply Installation and Testing of pressure gauges, complete in all respect | D15: p/job | E15: =J1*3 -> 9 | H15: 3400
A16: 11 | B16: N.S | C16: Supply Installation and testing of Analogue Water meter, complete in all respect | D16: p/job | E16: 1 | H16: 17540
A17: 12 | B17: N.S | C17: Rehabilitation of Analogue Water meter including callibration, complete in all respect | D17: p/job | E17: 2 | H17: 6000
A18: 13 | B18: N.S | C18: Supply Installation and Testing of Solinoid valve complete in all respect | D18: p/job | E18: =J1*2 -> 6 | H18: 8500 | I18: =92-27 -> 65
A19: 14 | B19: N.S | C19: Rehabilitation of Solinoid valve complete in all respect | D19: p/job | E19: =J1*2 -> 6 | H19: 3200 | I19: 8
A20: 15 | B20: N.S | C20: Supply Installation & Commissioning of 3way Automatic Multiport Valve, top & bottom distributers, complete in all respect | D20: p/job | E20: =J1 -> 3 | H20: 40930
A21: 16 | B21: N.S | C21: Rehabilitation of 3way Automatic Multiport Valve, top & bottom distributers, complete in all respect | D21: p/job | E21: =J1 -> 3 | H21: 8400
A22: 17 | B22: N.S | C22: Supply, installation and Testing of Chlorine Dosing Pump with working pressure 5 - 7 Bar imported, along with 80 liter capacity tank with all repects.complete in all respect Origin: Europe / USA / Asia or Equivalent Pressure: 5 -7 bar Tank Size: Maximum 80 liter Material: PVDF | D22: p/job | E22: 1 | H22: 89235
A23: 18 | B23: N.S | C23: Supply and installation of Water Storage Tank, Capacity 2000 Liters, Material PE, Food Grade, 3 to 5 mm wall thickness, weight minimum 32 kg, complete in all respects Capacity : 2000 Litre minimum Material: Plastic food grade | D23: p/job | E23: =J1 -> 3 | H23: 45575
A24: 19 | B24: N.S | C24: Chemical Cleaning & repair of Water Storage tank, complete in all respects at site | D24: p/job | E24: =J1 -> 3 | H24: 2500
A25: 20 | B25: N.S | C25: Supply and installation of 2 No. electric float switch for Water Storage Tank, complete in all respect | D25: No. | E25: 3 | H25: 3625
A26: 21 | B26: N.S | C26: Replacement of Activated Carbon media supply, installation and commissioning complete in all respect NSF Certified, Iodine No 850-1000 Material: Coconut Shell Origin: Sri Lanka / Thailand or Equivalent Size of Media: 1.2 - 1.6 mm Surface Area: 900 m2 / g Bulk Density: 440 - 540 kg / m3 Hardness No: 80 Ash Contents: 5 % Height of Gravel: 200 mm Media Bed Height: > 800 mm | D26: kg | E26: =50*(J1*60%) -> 90 | H26: 1510
A27: 22 | B27: N.S | C27: Replacement of Silica sand media supply, installation and commissioning complete in all respect Material: Quartz Silica Sand Size of Media: 0.85 - 2 mm Cleaning Process: Automatic, through PLC / Time Controller MPV | D27: kg | E27: =160*(J1*70%) -> 336 | H27: 70
A28: 23 | B28: N.S | C28: Replacement of Natural Gravels media supply, installation and commissioning complete in all respect Material: Gravel Media | D28: kg | E28: =160*(J1*60%) -> 288 | H28: 70
A29: 24 | B29: N.S | C29: Replacement of Granular Feric Hydroxide use for drinking water treatment with oxidation capacity of As3 to As5, commissioning complete in all respect Operating Pressure: 1.5 - 3 Bar Media: Grannular Ferric Hydroxide Origin: Europe / USA / German or Equivalent (NSF Certified) Cleaning Process: Automatic, through PLC / Time Controller MPV | D29: kg | E29: =160*(J1*40%) -> 192 | H29: 2510
A30: 25 | B30: N.S | C30: Supply installation and commissioning of UV lamp rod with quartz complete in all respect Origin: Europe / USA / German or Equivalent | D30: No. | E30: 1
A31: 26 | B31: N.S | C31: Rehabilitation of Pipe and fittings, complete plant fitting in all respect | D31: Per Plant | E31: 2 | H31: 22000
A32: 27 | B32: N.S | C32: Supply installation & testing of Plastic water Taps with fusion joint, complete in all respect | D32: p/job | E32: =J1*5 -> 15 | H32: 585
A33: 28 | B33: N.S | C33: Rehabilitation of Plant control panel with PLC & HMI complete in all respect | D33: Per Plant | E33: 2 | H33: 46000
A34: 29 | B34: N.S | C34: Supply & Installation of FRP Vessel (Size16 X 65) Origin: Europe / USA / German / China or Equivalent | D34: No. | E34: 1
A35: Grand Total | H35: =G35-#REF! -> #REF!
A36: Per Unit Cost = Grand Total / 3

Sheet U1
A1: ='R5'!A1:G2 -> PUNJAB SAAF PANI AUTHORITY | J1: UF | K1: 7
A2: ='R5'!A2:G2 -> REHABILITATION & O&M OF DYSFUNCTIONAL WATER FILTRATION PLANTS INSTALLED IN DIVISON FAISALABAD
A3: ='U2'!A3:G3 -> BILL OF QUANTITY
A4: Bill No. 6: Rehabilitation of Ultra Filtration 1000 LPH
A5: Sr. No. | B5: MRS Ref. # | C5: Description | D5: Unit | E5: Qty. | F5: Unit Rate (PKR) | G5: Amount (PKR)
A6: 1 | B6: N.S | C6: Rehabilitation of Plant Skid frame and Finishing, complete in all respect, inclusive of Carriage to Site and Labor for Installation Frame: Frame stainless steel | D6: p/job | E6: 7 | K6: 0.3
A7: 2 | B7: N.S | C7: Membranes recovery with chemicals cleaning, including labour & testing, Complete in all respects, inclusive of Carriage to Site and Labor for Installation | D7: p/job | E7: 4 | K7: 0.3
A8: 3 | B8: N.S | C8: Supply, Installation & Commissioning of UF membrane including membrane housing complete in all respect Origin: Europe / USA or Equivalent. Removal Size: 0.02 Micron Certification: NSF Material of vessel: uPVC Thickness: 5mm Membrane material: PVDF (Polyvinylidene flouride)/ PES (Polyethersulfone) - Multibore technology Membrane Working pressure: upto 5 Bar Membrane Life: Minimum 5 years Bacterail Removal effciency of UF membrane: 99.9999% log 6 Viruses Removal effciency of UF membrane: 99.99% log 4 Auto Backwash enabled Working temprature: Max 40 degree Celsius | D8: Per Plant | E8: 3 | K8: 0.05
A9: 4 | B9: N.S | C9: Supply Installation and commissioning of 1000 LPH Feed Pump for 1000 LPH UF WFP, complete in all respect Origin: Europe / USA / Asia or Equivalent Discharge: 1000 LPH Pump Type: Vertical / Horizontal Low Pressure Pump Impeller Type: S.S. 304 Operating Head: Up to 05 Barg Pump Efficiency: > 40% Motor Starter: DOL | D9: No. | E9: 3 | K9: 0.1
A10: 5 | B10: N.S | C10: Rehabilitation of UF Feed water pump 2000 LPH, for 1000 LPH UF Plant, complete in all respect | D10: p/job | E10: 4 | K10: 0.3
A11: 6 | B11: N.S | C11: Supply Installation & commissioning of submersible pump 3HP including supporting clamp with steel cable, pump coupling, cable clip, delivery pipe, electric cable complete in all respect. Origin: Europe / USA/ Asia or Equivalent Minimum Discharge: 2000 LPH Minimum Operation Head: Up to 130 m. Pump Type: Submersible Pump Impeller Type: S.S. 304 Motor Starter: DOL | D11: p/job | E11: 7 | K11: 0.1
A12: 7 | B12: N.S | C12: Supply and installation of SS safety filter strainer | D12: p/job | E12: =K1 -> 7 | K12: 1
A13: 8 | B13: N.S | C13: Supply Installation and Testing of Pressure Switchs complete with all respects | D13: p/job | E13: =K1 -> 7 | K13: 0.4
A14: 9 | B14: N.S | C14: Supply Installation and testing of Rota meter complete in all respect Origin: Europe / USA / German / Pakistan or Equiavlent Type: Rota Meter / Flow Type Material: Acryclic | D14: p/job | E14: =K1*2 -> 14 | K14: 0.6
A15: 10 | B15: N.S | C15: Supply Installation and Testing of pressure gauges, complete in all respect | D15: p/job | E15: =K1*3 -> 21 | K15: 2
A16: 11 | B16: N.S | C16: Supply Installation and testing of analogue Water meter, complete in all respect | D16: p/job | E16: 4 | K16: 0.2
A17: 12 | B17: N.S | C17: Rehabilitation of analogue water meter including callibration, complete in all respect | D17: p/job | E17: 3 | K17: 0.5
A18: 13 | B18: N.S | C18: Supply Installation and Testing of Solinoid valve complete in all respect | D18: p/job | E18: =K1*2 -> 14 | K18: 0.5
A19: 14 | B19: N.S | C19: Rehabilitation of Solinoid valve complete in all respect | D19: p/job | E19: =K1*2 -> 14 | K19: 1
A20: 15 | B20: N.S | C20: Supply Installation & Commissioning of 3way Multiport Valve, top & bottom distributers, complete in all respect | D20: p/job | E20: =K1 -> 7 | K20: 0.1
A21: 16 | B21: N.S | C21: Rehabilitation of 3way Multiport Valve, top & bottom distributers, complete in all respect | D21: p/job | E21: =K1*1.5 -> 10.5 | K21: 0.6
A22: 17 | B22: N.S | C22: Supply, installation and Testing of Chemical Dosing Pump / Liquid Dosing Pump with working pressure 5 - 7 Bar Imported, along with 80 liter capacity tank complete in all respect Origin: Europe / USA / Asia or Equivalent Pressure: 5 -7 bar Tank Size: Maximum 80 liter Chemical Anti Sclanet: Food Grade | D22: p/job | E22: 5
A23: 18 | B23: N.S | C23: Supply and installation of Water Storage Tank, Capacity 2000 Liters, Material PE, Food Grade, 3 to 5 mm wall thickness, weight minimum 32 kg, complete in all respects Capacity : 2000 Litre minimum Material: Plastic food grade | D23: p/job | E23: =K1 -> 7
A24: 19 | B24: N.S | C24: Chemical Cleaning & repair of Water Storage tanks, complete in all respects at site | D24: p/job | E24: =K1 -> 7
A25: 20 | B25: N.S | C25: Supply and installation of 2 No. float switch for Water Storage Tank, complete in all respect | D25: kg | E25: 7 | K25: 0.3
A26: 21 | B26: N.S | C26: Replacement of Activated Carbon media supply, installation and commissioning complete in all respect NSF Certified, Iodine No 850-1000 Material: Coconut Shell Origin: Sri Lanka / Thailand or Equivalent Size of Media: 1.2 - 1.6 mm Surface Area: 900 m2 / g Bulk Density: 440 - 540 kg / m3 Hardness No: 80 Ash Contents: 5 % Height of Gravel: 200 mm Media Bed Height: > 800 mm | D26: kg | E26: =40*(K1*60%) -> 168 | K26: 50
A27: 22 | B27: N.S | C27: Replacement of Silica sand media supply, installation and commissioning complete in all respect Material: Quartz Silica Sand Size of Media: 0.85 - 2 mm Cleaning Process: Automatic, through PLC / Time Controller MPV | D27: kg | E27: =130*(K1*70%) -> 637 | K27: 160
A28: 23 | B28: N.S | C28: Replacement of Natural Gravels media supply, installation and commissioning complete in all respect Material: Gravel media | D28: kg | E28: =130*(K1*60%) -> 546 | K28: 160
A29: 24 | B29: N.S | C29: Replacement of Granular Feric Hydroxide use for drinking water treatment with oxidation capacity of As3 to As5, commissioning complete in all respect Operating Pressure: 1.5 - 3 Bar Media: Grannular Ferric Hydroxide Origin: Europe / USA / German or Equivalent (NSF Certified) Cleaning Process: Automatic, through PLC / Time Controller MPV | D29: kg | E29: =90*(K1*60%) -> 378
A30: 25 | B30: N.S | C30: Supply installation and commissioning of UV lamp rod with quartz complete in all respect Origin: Europe / USA / German or Equivalent | D30: p/job | E30: 5 | K30: 1
A31: 26 | B31: N.S | C31: Rehabilitation of Pipe and fittings, complete plant fitting in all respect | D31: no. | E31: 5 | K31: 0.5
A32: 27 | B32: N.S | C32: Supply installation & testing of Plastic water Taps with fussion joint, complete in all respect | D32: p/job | E32: =K1*K32 -> 35 | K32: 5
A33: 28 | B33: N.S | C33: Rehabilitation of Plant control panel with PLC & HMI complete in all respect | D33: p/job | E33: 5 | K33: 1
A34: 29 | B34: N.S | C34: Supply & Installation of FRP Vessel (Size16 X 65) Origin: Europe / USA / German / China or Equivalent | D34: No. | E34: 1
A35: Grand Total | H35: =G35/1000000 -> 0
A36: Per Unit Cost = Grand Total / 7

Sheet R5 N
A1: ='U1'!A1:G2 -> PUNJAB SAAF PANI AUTHORITY
A2: ='U1'!A2:G2 -> REHABILITATION & O&M OF DYSFUNCTIONAL WATER FILTRATION PLANTS INSTALLED IN DIVISON FAISALABAD
A3: ='U1'!A3:G3 -> BILL OF QUANTITY
A4: Bill No 8 : Installation of Reverse Osmosis 500 LPH
A5: RO 500 LPH Plant
A6: Sr. No | B6: Description | C6: Qty | D6: Unit Rate (Rs) | E6: Amount (Rs)
A7: 1 | B7: Supply, transport, erection, installation, testing & commissioning of 500 L/H Reverse Osmosis (RO) Plant for TDS removal along with all other contaminants, including carriage, loading/unloading charges inclusive of all taxes conforming to Mentioned in Technical specifications of filtration plants. Control PLC GSM/GPRS/ SCADA enabled. The unit should be composed of Raw and Product water tanks (1000 Liter capacity for each) Feed and High Pressure Pump, pressure gauges, variable area flow meter for raw water and for product water totalizer/ water meter, pressure safety switch and valves, Multiport valves, safety filter strainers/cartridges filter, sand filter, carbon filters. System should be fully automatic. Provission of UV system, Anti secalent system with Anti scalent PVDF based dosing Pumps and chemical tank. The complete plant should be able to operate/backwash automatically through Automatic Multiport Valve operated by PLC with same feed pump based system. All type of piping and instrumentation shall be considered as part of filtration plant complete in all respect. The plant should be supplied to provide the treated water as per the WHO limits (strict compliance). The specifications along with equipment and accessories properly mounted in the frame/skid are given below: | C7: 1
A8: 2 | B8: Raw Water Feed Pump
B9: Supply Installation and commissioning of 1000 LPH Feed Pump for 500 LPH RO WFP, complete in all respect Discharge: 1000 LPH Minimum Operation Head: 04 Barg Maximum. Origin: Europe / USA / China or Equivalent Pump Type: Vertical / Horizontal Low Pressure Pump Impeller Type: S.S. 304 Operating Head: Up to 06 Barg Pump Efficiency: ≥ 40% Motor Starter: DOL
A10: 3 | B10: Submersible Pump
B11: Supply Installation & commissioning of submersible pump 3HP including supporting clamp with steel cable, pump coupling, cable clip, delivery pipe, electric cable complete in all respect. Origin: Europe / USA/ Asia or Equivalent Minimum Discharge: 2000 LPH Minimum Operation Head: Up to 130 m. Pump Type: Submersible Pump Impeller Type: S.S. 304 Motor Starter: DOL
A12: 4 | B12: Pre-Filtration
A13: 4 (a) | B13: Sand Filter
B14: Material: FRP Origin: Europe / USA / German or Equivalent Fitration Rate: 6 - 15 m/hr Vessel Certification: NSF Operating Pressure Max: Up to 06 Barg
A15: 4 (b) | B15: Filter Media Sand
B16: Material: Quartz Silica Sand Origin: Europe / USA / German or Equivalent Size of Media: 0.6 - 0.8 mm Cleaning Process: Automatic, through PLC / Time Controller MPV
A17: 4 (c) | B17: Activated Carbon Filter
B18: Material: FRP Origin: Europe / USA / German or Equivalent Media & Vessel Certification: NSF Fitration Rate: 5 - 15 m/hr Operating Pressure Max: Up to 06 Barg
A19: 4 (d) | B19: Filter Media Carbon
B20: Material: Coconut Shell Origin: Sri Lanka / Thailand or Equivalent Size of Media: 1.2 - 1.6 mm Surface Area: 900 m2 / g Bulk Density: 440 - 540 kg / m3 Hardness No: 80 Ash Contents: 5 % Height of Gravel: 200 mm Media Bed Height: > 800 mm
A21: 4 (e) | B21: Cartridge Filter
B22: Size: 20 Inches / As per Flow Porosity: 1-5 micron Material: High pressure Plastic Melt Blown PE
A23: 5 | B23: RO Skid
B24: Frame: Stainless Steel
A25: 6 | B25: High Pressure Pump multistage
B26: Supply, Installation and commissioning of 2000 LPH High Pressure Pump for 1000 LPH RO WFP, complete in all respect Origin: Europe / USA / Japan or Equivalent Discharge: 2000 LPH Operating Head: Up to 16 Barg Pump Type: Vertical / Horizontal High Pressure Pump Impeller material: S.S. 304 Pump Efficiency: > 50% Motor Starter: DOL IP 55 Ambient Temperature Class: 45 degree Celsius
A27: 7 | B27: RO Housing
B28: Material: FRP Certification: NSF
A29: 8 | B29: RO Membrane
B30: Supply Installation and commissioning of RO Plant membrane (4x40), including Membrane Housing complete in all respect. Origin: Europe / USA or Equivalent Certification: NSF Pore Size: 0.001 Micron Stablized salt rejection: 99% Capable for TDS: Upto 5000 mg/l Recovery: 15% (each) Life of RO Membrane: 03 to 05 years Pressure Rating: Upto 17 Barg
A31: 9 | B31: Automatic PLC Panel
B32: Origin: Europe / USA / German or Equivalent Programming: Fully automatic with breaker, timer and relays complete in all respects HMI display: For PLC - 10" minimum size with touch screen (Fully automatic control of plant) SCADA enable
A33: 10 | B33: Anti Scalent + Injection System
B34: Origin: Europe / USA / German or Equivalent Pressure: 5 -7 bar Tank Size: Maximum 80 liter Chemical Anti Sclanet: Food Grade Material: PVDF
A35: 11 | B35: UV Light with SS casing
B36: Origin: Europe / USA / German or Equivalent Material of Casing: SS 304 / 316 Operating Pressure: 04 Barg Ambient Temperature: Upto 45 degree celsius
A37: 12 | B37: Raw & Product water tank (1000 L) Each
B38: Material: PE Food Grade
A39: 13 | B39: Level Meter / Float Valve / Switch Electronic
B40: No: 02 Origin: Europe / USA / German or Equiavlent
A41: 14 | B41: Water Flow Meter
B42: No: 02 Origin: Europe / USA / German or Equiavlent Type: Rota Meter / Flow Type Material: Acryclic
A43: 15 | B43: Pressure Gauges
A44: 16 | B44: Online TDS meter
A45: 17 | B45: All fittings of PVC Sch.80
A46: 18 | B46: Pressure Regulation Switch
A47: 19 | B47: Auto on/off Switch for Pump
A48: 20 | B48: Automatic Back Wash system for Membrane
A49: 21 | B49: Including any item required for Filtration Plant if required
A50: Total

Sheet U2 N
A1: ='U1'!A1:G2 -> PUNJAB SAAF PANI AUTHORITY
A2: ='R5 N'!A2:E2 -> REHABILITATION & O&M OF DYSFUNCTIONAL WATER FILTRATION PLANTS INSTALLED IN DIVISON FAISALABAD
A3: ='R5 N'!A3:E3 -> BILL OF QUANTITY
A4: Bill No 7 : Installation of Ultra Filtration 2000 LPH
A5: Specification of UF 2000 LPH Plants
A6: Sr No | B6: Description | C6: Specifications | D6: Qty | E6: Unit Rate (Rs) | F6: Amount (Rs)
B7: Supply, Install, Testing and Commissioning of water Ultra filtration plant, capable of removing Turbidity, Arsenic, Bacteria & Viruses, having capacity of 2000 litres/ hour and fully automated (Auto filtration, flush and backwash process) complete in all respects. Pressure Gauges, Flow Meters and Level Sensors, Multiport and Solenoid Valves, Stainles Steel 304 Frame, All Pipe work including feed water pipe line connection to the delivery pipeline and necessary gate and flow regulating valves, water taps including pipework & uPVC pipe to drain off the spent/ waste water. | D7: 1
A8: 1 | B8: Pre Filtration
B9: Pressure Sand filtration
B10: Constant flow valve for fitration backwash | C10: 3way automatic valve with automatic back wash system
B11: Sand effective size | C11: 0.85 - 2 mm
B12: Vessel Material | C12: Material FRP, Make Pentair / Frotec / G Fiber or Equivalent NSF certified company
B13: Vessel diameter / height | C13: size 16" x 65" / Size 24" x 72"
A14: 2 | B14: Activited Carbon filtration
B15: Carbon Media | C15: Iodine No 850-1000 Material: Coconut Shell Origin: Sri Lanka / Thailand or Equivalent Size of Media: 1.2 - 1.6 mm Surface Area: 900 m2 / g Bulk Density: 440 - 540 kg / m3 Hardness No: 80 Ash Contents: 5 % Height of Gravel: 200 mm Media Bed Height: > 800 mm
B16: Vessel Material | C16: Material FRP, Make Pentair / Frotec / G Fiber or Equivalent NSF certified company
B17: Vessel diameter / height | C17: size 16" x 65" / Size 24" x 72"
A18: 3 | B18: Arscenic Removal Filter
B19: Arsenic Media | C19: Grannular Ferric Hydroxide oxidation capacity of As3 to As5, Operating Pressure: 1.5 - 3 Bar Origin: Europe / USA / German or Equivalent (NSF Certified) Cleaning Process: Automatic, through PLC / Time Controller MPV
B20: Vessel Material | C20: Material FRP, Make Pentair / Frotec / G Fiber or Equivalent NSF certified company
B21: Vessel diameter / height | C21: size 16" x 65" / Size 24" x 72"
A22: 4 | B22: UF Unit
B23: Mounting / Frame | C23: Frame stainless steel SS 304
B24: Pre treatment objectives turbidity | C24: < 1 NTU
A25: 5 | B25: Well pump or / with feed pump | C25: Stainless Steel, NEMA Insulation Class F and Pump Efficiency > 50%
A26: 6 | B26: UF Membrane
B27: Membrane Type | C27: Supply, Installation & Commissioning of UF membrane including membrane housing complete in all respect Origin: Europe / USA or Equivalent. Removal Size: 0.02 Micron Certification: NSF Material of vessel: uPVC Thickness: 5mm Membrane material: PVDF (Polyvinylidene flouride)/ PES (Polyethersulfone) - Multibore technology Membrane Working pressure: upto 5 Bar Membrane Life: Minimum 5 years Bacterail Removal effciency of UF membrane: 99.9999% log 6 Viruses Removal effciency of UF membrane: 99.99% log 4 Auto Backwash enabled Working temprature: Max 40 degree Celsius
B28: Trans membrane Pressure (TMP) | C28: <10 bar
B29: Piping for Units | C29: All fittings of UPVC Sch.80
A30: 7 | B30: Dosing Pump | C30: Operational / rinsing
B31: Dosing Pump working pressure | C31: 5 - 7 bar
B32: Chemical Used | C32: Anti Scalant Food Grade
B33: Pre Treatment | C33: Disinfection by UV radiation
B34: Bacteria | C34: Below Detection level
A35: 8 | B35: Control System | C35: Automatic PLC Panel / Micro processor based embedded system
C36: Programming fully automatic with breaker, timer and relays complete in all respects
C37: Visual Display Unit with Membrane Keypad / HMI with Touch interface
C38: Fully automatic control of plant
C39: SCADA enable
A40: 9 | B40: Raw water tank | C40: Raw water tank
C41: Capacity 2000 Litre minimum
C42: Material Plastic food grade
C43: Float Switch
A44: 10 | B44: Clean Water Storage Tank | C44: Product water tank
C45: Material Plastic food grade
C46: Capacity 2000 Litre minimum
C47: Float Switch
A48: 11 | B48: Waste disposal | C48: Discharge in the sanitory sewerage system
A49: Total

Sheet R2 N
A1: ='U2 N'!A1:F1 -> PUNJAB SAAF PANI AUTHORITY
A2: ='U2 N'!A2:F2 -> REHABILITATION & O&M OF DYSFUNCTIONAL WATER FILTRATION PLANTS INSTALLED IN DIVISON FAISALABAD
A3: ='U2 N'!A3:F3 -> BILL OF QUANTITY
A4: Bill No 9 : Installation of Reverse Osmosis 2000 LPH
A5: RO 2000 LPH Plant
A6: Sr No | B6: Description | C6: Qty | D6: Unit Rate (Rs) | E6: Amount (Rs)
A7: 1 | B7: Supply, transport, erection, installation, testing & commissioning of 2,000 L/H Reverse Osmosis (RO) Plant for TDS removal along with all other contaminants, including carriage, loading/unloading charges inclusive of all taxes conforming to Mentioned in Technical specifications of filtration plants. Control PLC GSM/GPRS/ SCADA enabled. The unit should be composed of Raw and Product water tanks (2000Liter capacity for each) Feed and High Pressure Pump, pressure gauges, variable area flow meter for raw water and for product water totalizer/ water meter, pressure safety switch and valves, Multiport valves, safety filter strainers/cartridges filter, sand filter, carbon filters. System should be fully automatic. Provission of UV system, Anti secalent system with Anti secalent PVDF based dosing Pumps and chemical tank. The complete plant should be able to operate/backwash automatically through Automatic Multiport Valve operated by PLC with same feed pump based system. All type of piping and instrumentation shall be considered as part of filtration plant complete in all respect. The plant should be supplied to provide the treated water as per the WHO limits (strict compliance). The specifications along with equipment and accessories properly mounted in the frame/skid are given below: | C7: 1
A8: 2 | B8: Raw Water Feed Pump
B9: Supply Installation and commissioning of 4000 LPH Feed Pump for 2000 LPH RO WFP, complete in all respect Discharge: 4000 LPH Minimum Operation Head: 04 Barg Maximum. Origin: Europe / USA / China or Equivalent Pump Type: Vertical / Horizontal Low Pressure Pump Impeller Type: S.S. 304 Operating Head: Up to 06 Barg Pump Efficiency: ≥ 40% Motor Starter: DOL
A10: 3 | B10: Submersible Pump
B11: Supply Installation & commissioning of submersible pump 3HP including supporting clamp with steel cable, pump coupling, cable clip, delivery pipe, electric cable complete in all respect. Origin: Europe / USA/ Asia or Equivalent Minimum Discharge: 2000 LPH Minimum Operation Head: Up to 130 m. Pump Type: Submersible Pump Impeller Type: S.S. 304 Motor Starter: DOL
A12: 4 | B12: Pre-Filtration
A13: 4 (a) | B13: Sand Filter
B14: Material: FRP Origin: Europe / USA / German or Equivalent Fitration Rate: 6 - 15 m/hr Vessel Certification: NSF Operating Pressure Max: Up to 06 Barg
A15: 4 (b) | B15: Filter Media Sand
B16: Material: Quartz Silica Sand Origin: Europe / USA / German or Equivalent Size of Media: 0.6 - 0.8 mm Cleaning Process: Automatic, through PLC / Time Controller MPV
A17: 4 (c) | B17: Activated Carbon Filter
B18: Material: FRP Origin: Europe / USA / German or Equivalent Media & Vessel Certification: NSF Fitration Rate: 5 - 15 m/hr Operating Pressure Max: Up to 06 Barg
A19: 4 (d) | B19: Filter Media Carbon
B20: Material: Coconut Shell Origin: Sri Lanka / Thailand or Equivalent Size of Media: 1.2 - 1.6 mm Surface Area: 900 m2 / g Bulk Density: 440 - 540 kg / m3 Hardness No: 80 Ash Contents: 5 % Height of Gravel: 200 mm Media Bed Height: > 800 mm
A21: 4 (e) | B21: Cartridge Filter
B22: Size: 20 Inches / As per Flow Porosity: 1-5 micron Material: High pressure Plastic Melt Blown PE
A23: 5 | B23: RO Skid
B24: Frame: Stainless Steel
A25: 6 | B25: High Pressure Pump multistage
B26: Supply, Installation and commissioning of 4000 LPH High Pressure Pump for 2000 LPH RO WFP, complete in all respect Origin: Europe / USA / Japan or Equivalent Discharge: 4000 LPH Operating Head: Up to 16 Barg Pump Type: Vertical / Horizontal High Pressure Pump Impeller material: S.S. 304 Pump Efficiency: > 50% Motor Starter: DOL IP 55 Ambient Temperature Class: 45 degree Celsius
A27: 7 | B27: RO Housing
B28: Material: FRP Certification: NSF
A29: 8 | B29: RO Membrane
B30: Supply Installation and commissioning of RO Plant membrane (4x40), including Membrane Housing complete in all respect. Origin: Europe / USA or Equivalent Certification: NSF Pore Size: 0.001 Micron Stablized salt rejection: 99% Capable for TDS: Upto 5000 mg/l Recovery: 15% (each) Life of RO Membrane: 03 to 05 years Pressure Rating: Upto 17 Barg
A31: 9 | B31: Automatic PLC Panel
B32: Origin: Europe / USA / German or Equivalent Programming: Fully automatic with breaker, timer and relays complete in all respects HMI display: For PLC - 10" minimum size with touch screen (Fully automatic control of plant) SCADA enable
A33: 10 | B33: Anti Scalent + Injection System
B34: Origin: Europe / USA / German or Equivalent Pressure: 5 -7 bar Tank Size: Maximum 80 liter Chemical Anti Sclanet: Food Grade Material: PVDF
A35: 11 | B35: UV Light with SS casing
B36: Origin: Europe / USA / German or Equivalent Material of Casing: SS 304 / 316 Operating Pressure: 04 Barg Ambient Temperature: Upto 45 degree celsius
A37: 12 | B37: Raw & Product water tank (2000 L) Each
B38: Material: PE Food Grade
A39: 13 | B39: Level Meter / Float Valve / Switch Electronic
B40: No: 02 Origin: Europe / USA / German or Equiavlent
A41: 14 | B41: Water Flow Meter
B42: No: 02 Origin: Europe / USA / German or Equiavlent Type: Rota Meter / Flow Type Material: Acryclic
A43: 15 | B43: Pressure Gauges
A44: 16 | B44: Online TDS meter
A45: 17 | B45: All fittings of PVC Sch.80
A46: 18 | B46: Pressure Regulation Switch
A47: 19 | B47: Auto on/off Switch for Pump
A48: 20 | B48: Automatic Back Wash system for Membrane
A49: 21 | B49: Including any item required for Filtration Plant if required
A50: Total

Sheet R1 N
A1: ='U1'!A1:G2 -> PUNJAB SAAF PANI AUTHORITY
A2: ='R2 N'!A2:E2 -> REHABILITATION & O&M OF DYSFUNCTIONAL WATER FILTRATION PLANTS INSTALLED IN DIVISON FAISALABAD
A3: ='R2 N'!A3:E3 -> BILL OF QUANTITY
A4: Bill No 10 : Installation of Reverse Osmosis 1000 LPH
A5: RO 1000 LPH Plant
A6: Sr. No | B6: Description | C6: Qty | D6: Unit Rate (Rs) | E6: Amount (Rs)
A7: 1 | B7: Supply, transport, erection, installation, testing & commissioning of 1,000 L/H Reverse Osmosis (RO) Plant for TDS removal along with all other contaminants, including carriage, loading/unloading charges inclusive of all taxes conforming to Mentioned in Technical specifications of filtration plants. Control PLC GSM/GPRS/ SCADA enabled. The unit should be composed of Raw and Product water tanks (1000 Liter capacity for each) Feed and High Pressure Pump, pressure gauges, variable area flow meter for raw water and for product water totalizer/ water meter, pressure safety switch and valves, Multiport valves, safety filter strainers/cartridges filter, sand filter, carbon filters. System should be fully automatic. Provission of UV system, Anti secalent system with Anti scalent PVDF based dosing Pumps and chemical tank. The complete plant should be able to operate/backwash automatically through Automatic Multiport Valve operated by PLC with same feed pump based system. All type of piping and instrumentation shall be considered as part of filtration plant complete in all respect. The plant should be supplied to provide the treated water as per the WHO limits (strict compliance). The specifications along with equipment and accessories properly mounted in the frame/skid are given below: | C7: 1
A8: 2 | B8: Raw Water Feed Pump
B9: Supply Installation and commissioning of 2000 LPH Feed Pump for 1000 LPH RO WFP, complete in all respect Discharge: 2000 LPH Minimum Operation Head: 04 Barg Maximum. Origin: Europe / USA / China or Equivalent Pump Type: Vertical / Horizontal Low Pressure Pump Impeller Type: S.S. 304 Operating Head: Up to 06 Barg Pump Efficiency: ≥ 40% Motor Starter: DOL
A10: 3 | B10: Submersible Pump
B11: Supply, Installation and commissioning of 2000 LPH High Pressure Pump for 1000 LPH RO WFP, complete in all respect Origin: Europe / USA / Japan or Equivalent Discharge: 2000 LPH Operating Head: Up to 16 Barg Pump Type: Vertical / Horizontal High Pressure Pump Impeller material: S.S. 304 Pump Efficiency: > 50% Motor Starter: DOL IP 55 Ambient Temperature Class: 45 degree Celsius
A12: 4 | B12: Pre-Filtration
A13: 4 (a) | B13: Sand Filter
B14: Material: FRP Origin: Europe / USA / German or Equivalent Fitration Rate: 6 - 15 m/hr Vessel Certification: NSF Operating Pressure Max: Up to 06 Barg
A15: 4 (b) | B15: Filter Media Sand
B16: Material: Quartz Silica Sand Origin: Europe / USA / German or Equivalent Size of Media: 0.6 - 0.8 mm Cleaning Process: Automatic, through PLC / Time Controller MPV
A17: 4 (c) | B17: Activated Carbon Filter
B18: Material: FRP Origin: Europe / USA / German or Equivalent Media & Vessel Certification: NSF Fitration Rate: 5 - 15 m/hr Operating Pressure Max: Up to 06 Barg
A19: 4 (d) | B19: Filter Media Carbon
B20: Material: Coconut Shell Origin: Sri Lanka / Thailand or Equivalent Size of Media: 1.2 - 1.6 mm Surface Area: 900 m2 / g Bulk Density: 440 - 540 kg / m3 Hardness No: 80 Ash Contents: 5 % Height of Gravel: 200 mm Media Bed Height: > 800 mm
A21: 4 (e) | B21: Cartridge Filter
B22: Size: 20 Inches / As per Flow Porosity: 1-5 micron Material: High pressure Plastic Melt Blown PE
A23: 5 | B23: RO Skid
B24: Frame: Stainless Steel
A25: 6 | B25: High Pressure Pump multistage
B26: Supply, Installation and commissioning of 2000 LPH High Pressure Pump for 1000 LPH RO WFP, complete in all respect Origin: Europe / USA / Japan or Equivalent Discharge: 2000 LPH Operating Head: Up to 16 Barg Pump Type: Vertical / Horizontal High Pressure Pump Impeller material: S.S. 304 Pump Efficiency: > 50% Motor Starter: DOL IP 55 Ambient Temperature Class: 45 degree Celsius
A27: 7 | B27: RO Housing
B28: Material: FRP Certification: NSF
A29: 8 | B29: RO Membrane
B30: Supply Installation and commissioning of RO Plant membrane (4x40), including Membrane Housing complete in all respect. Origin: Europe / USA or Equivalent Certification: NSF Pore Size: 0.001 Micron Stablized salt rejection: 99% Capable for TDS: Upto 5000 mg/l Recovery: 15% (each) Life of RO Membrane: 03 to 05 years Pressure Rating: Upto 17 Barg
A31: 9 | B31: Automatic PLC Panel
B32: Origin: Europe / USA / German or Equivalent Programming: Fully automatic with breaker, timer and relays complete in all respects HMI display: For PLC - 10" minimum size with touch screen (Fully automatic control of plant) SCADA enable
A33: 10 | B33: Anti Scalent + Injection System
B34: Origin: Europe / USA / German or Equivalent Pressure: 5 -7 bar Tank Size: Maximum 80 liter Chemical Anti Sclanet: Food Grade Material: PVDF
A35: 11 | B35: UV Light with SS casing
B36: Origin: Europe / USA / German or Equivalent Material of Casing: SS 304 / 316 Operating Pressure: 04 Barg Ambient Temperature: Upto 45 degree celsius
A37: 12 | B37: Raw & Product water tank (1000 L) Each
B38: Material: PE Food Grade
A39: 13 | B39: Level Meter / Float Valve / Switch Electronic
B40: No: 02 Origin: Europe / USA / German or Equiavlent
A41: 14 | B41: Water Flow Meter
B42: No: 02 Origin: Europe / USA / German or Equiavlent Type: Rota Meter / Flow Type Material: Acryclic
A43: 15 | B43: Pressure Gauges
A44: 16 | B44: Online TDS meter
A45: 17 | B45: All fittings of PVC Sch.80
A46: 18 | B46: Pressure Regulation Switch
A47: 19 | B47: Auto on/off Switch for Pump
A48: 20 | B48: Automatic Back Wash system for Membrane
A49: 21 | B49: Including any item required for Filtration Plant if required
A50: Total

Sheet BH
A1: ='U2'!A1:G2 -> PUNJAB SAAF PANI AUTHORITY
A2: ='R1 N'!A2:E2 -> REHABILITATION & O&M OF DYSFUNCTIONAL WATER FILTRATION PLANTS INSTALLED IN DIVISON FAISALABAD
A3: ='R1 N'!A3:E3 -> BILL OF QUANTITY
A4: Bill No 11: Installation of New Bore Holes
A5: Sr. No. | B5: MRS | C5: Description | D5: Unit | E5: Qty | F5: Rate | G5: Total Amount (Rs)
A6: 1 | B6: N.S | C6: Boring of tubewell with 350 ft dept, along with casing Pipe (PVC Class B - 4" i/d), discharge Pipe (PVC class B - 1.5" i/d) with steel wire, copper cable for connection of motor, M.S clamp, strainer (B.S.S. Class 'B' - 4" i/d) , Bail/End Plug (4"), reinforced cement concrete in retaining/Shear walls, with contructing of foundation (3'*3'*3'), control panel, etc complete in all respect. | D6: Job | E6: 1
D7: M | E7: 30
A8: 1 | B8: 23-2-b | C8: Boring for tubewell in all types of soil except shingle, gravel & rock, from a depth of 100 ft to 200 ft (30 m to 60m) below ground level, including sinking and withdrawing of casing pipe, complete:- 6"( 150mm)
D9: M | E9: 30
E11: 30
A12: 3 | B12: 6-5-f | C12: Cement concrete plain including placing, compacting, finishing and curing complete (including screening and washing of stone aggregate): Ratio 1: 2: 4
D13: Cu.m | E13: 0.5
A14: 4 | B14: 6-6-a ii b(i) | C14: (a)(ii)Reinforced cement concrete in retaining/Shear walls laid in situ or precasted in position,or pre stressed members cast ins itu(Formwork on both sides) , complete in all respects: Type C (nominal mix 1:2:4) Upto 9" thick (Avg)
D15: Cu.m | E15: 1.5
A16: 5 | B16: 23-15-iii | C16: Providing and installing P.V.C. Bail/End plug, in tubewell bore hole:- (4" dia). (100 mm)
D17: Each | E17: 1
A18: 6 | B18: 23-11-b | C18: Providing and installing, P.V.C. strainer B.S.S. Class 'B' in tubewell bore hole, including sockets and solvents, etc. complete . 4" dia (100mm).
D19: per M | E19: 15
A20: 7 | B20: 23-17-b | C20: Providing and installing P.V.C. blind pipe, B.S.S. Class `B', in tubewell bore hole, including sockets and solvents and jointing with strainer, etc. complete (4" dia)
D21: M | E21: 75
A22: 8 | B22: N.S | C22: Providing, fixing, jointing and testing Polypropylene Random Copolymer (PPRC) PN20 pressure pipe for cold and hot water as per DIN 8077-8078, PN 20 for pipes and DIN 16962, PN 25 for fittings (polyfusion welded joints) inside building including fittings and specials (sockets, tees, elbows, bends, crosses, reducers, adaptor, plugs and union etc.) supported on walls or suspended from roof slab or run in chases including pipe hangers, supports, cutting and making good the chases and holes, complete in all respects.
D23: M | E23: 10
A24: 9 | B24: N.S | C24: Supply & installation of 1/2" i/d thick M.S Cap for 6" housing pipe joint by means of welding & hinges with lock & locking arrangements.
D25: Each | E25: 1
A26: 2 | B26: N.S | C26: Taking of water samples (2 bottles each) at the end of the pumping test. Full chemical and bacteriological analysis, of water samples according to WHO. | D26: Each | E26: 1
A27: Total

Sheet WB
A1: ='Bill No 5 UF 2000 New'!A1 -> PUNJAB SAAF PANI AUTHORITY
A2: =BH!A2 -> REHABILITATION & O&M OF DYSFUNCTIONAL WATER FILTRATION PLANTS INSTALLED IN DIVISON FAISALABAD
A3: =BH!A3 -> BILL OF QUANTITY
A4: Bill No 12:Development of Bore Holes
A5: Sr, No | B5: Description | C5: Unit | D5: Quantity | E5: Unit Rate (RS) | F5: Amount (RS)
A6: 1 | B6: Rehabilitation, Cleaning & Washing existing bore holes by using air compresseor or any other equipment | C6: No. | D6: 1
B7: Total

Sheet B8 Civil
A1: ='U2'!A1 -> PUNJAB SAAF PANI AUTHORITY
A2: ENGINEERING COST ESTIMATE
A3: Civil Room 12*12
A4: Bill No 8: Rehabilitation of Civil Works
A5: SCHEDULE ITEMS BASED ON MRS, 2nd BI-ANNUAL PERIOD (1st Jun, 2024 TO 30th Dec, 2024) Lahore
A6: Sr. | B6: DESCRIPTION | K6: QTY | L6: UNIT | M6: RATE | N6: AMOUNT
A7: No. | M7: ( In Rupees)
B8: Chapter. 7 Item No. 5 (i)
A9: 1 | B9: Pacca brick work in ground floor:- cement, sand mortar:-Ratio 1:5
B10: L.W | D10: 2 | E10: 13.5 | F10: 0.75 | G10: 10 | H10: = | I10: =ROUND(D10*F10*G10*E10,0) -> 203
B11: S.W | D11: 2 | E11: 12 | F11: 0.75 | G11: 10 | H11: = | I11: =ROUND(D11*F11*G11*E11,0) -> 180
B12: Parapet L.W | D12: 2 | E12: 16.5 | F12: 0.75 | G12: 1.5 | H12: = | I12: =ROUND(D12*F12*G12*E12,0) -> 37
B13: Parapet S.W | D13: 2 | E13: 12 | F13: 0.375 | G13: 1.5 | H13: = | I13: =ROUND(D13*F13*G13*E13,0) -> 14
F14: Total: | I14: =ROUND(SUM(I10:J13),0) -> 434 | K14: 30 | L14: cft | M14: =41988.8/100 -> 419.888 | N14: =M14*K14 -> 12596.64
B15: Chapter. 11 Item No. 9 b,
A16: 2 | B16: Cement plaster 1 : 4 upto 20 ft. height
B17: (b) 1/2 inch thick
B18: Inside | D18: 2 | E18: 12 | F18: + | G18: 12 | H18: 10 | I18: = | J18: =ROUND(D18*(E18+G18)*H18,0) -> 480
B19: under roof | D19: 1 | E19: x | F19: 12 | G19: x | H19: 15 | I19: = | J19: =ROUND(D19*F19*H19,0) -> 180
B20: Below plinth | D20: 4 | E20: x | F20: 12 | G20: x | H20: 1.25 | I20: = | J20: =ROUND(D20*F20*H20,0) -> 60
B21: D/d | H21: Total | I21: (Sft) | J21: =SUM(J18:J20) -> 720
D22: 1 | E22: x | F22: 5 | G22: x | H22: 7 | I22: = | J22: =ROUND(D22*F22*H22,0) -> 35
D23: 1 | E23: x | F23: 4 | G23: x | H23: 4 | I23: = | J23: =ROUND(D23*F23*H23,0) -> 16
H24: Total | I24: (Sft) | J24: =SUM(J22:J23) -> 51
B25: Net | D25: =J21 -> 720 | E25: - | F25: =J24 -> 51 | I25: = | J25: =D25-F25 -> 669 | K25: 30 | L25: Sft. | M25: =4708.2/100 -> 47.082 | N25: =ROUND(M25*K25/100,0) -> 14
B26: Chapter. 6 Item No. 5.f
A27: 3 | B27: Cement concrete plain including placing, compacting, finishing and curing complete (including screening and washing of stone aggregate):
B28: 1 | C28: 12 | D28: x | E28: 12 | F28: x | G28: 0.33 | H28: = | I28: =ROUND(B28*C28*E28*G28,0) -> 48 | J28: Sft.
B29: 1 | C29: 12 | D29: x | E29: 3 | F29: x | G29: 2 | H29: = | I29: =ROUND(B29*C29*E29*G29,0) -> 72 | J29: Sft.
B30: Plinth
B31: 2 | C31: 19.5 | D31: x | E31: 3 | F31: x | G31: 0.33 | H31: = | I31: =ROUND(B31*C31*E31*G31,0) -> 39 | J31: Sft.
B32: 2 | C32: 13.5 | D32: x | E32: 3 | F32: x | G32: 0.33 | H32: = | I32: =ROUND(B32*C32*E32*G32,0) -> 27 | J32: Sft.
H33: Total | I33: =SUM(I28:I32) -> 186 | J33: Sft. | K33: 30 | L33: Sft. | M33: =50377.8/100 -> 503.778 | N33: =(M33*K33) -> 15113.34
B34: Chapter. 4 Item No. 19(a)
A35: 4 | B35: Dismantling of plain cement concrete (1:4:8) | K35: 40 | L35: cft | M35: =8276.4/100 -> 82.764 | N35: =M35*K35 -> 3310.56
B36: Chapter. 1 Item No. 1
A37: 5 | B37: Carriage of 100 Cft. (2.83 cu.m) of all materials like stone aggregate, spawl, kankar lime (unslaked), surkhi, etc. or 150 Cft. (4.25 cu.m) of timber, by truck or by any other means owned by the contractor. Upto 200 km
B38: Upto 0 to 10 K.M distance | H38: = | I38: =360.25+170.95+133.05+94.05+87.6+86.18025+79.35+74.45+69.7 -> 1155.5802
B39: 10.01 to 200 K.M | E39: 190 | F39: x | G39: 60.8 | H39: = | I39: =G39*E39 -> 11552
G40: Total | H40: = | I40: =I38+I39 -> 12707.58 | N40: =I40 -> 12707.58
A41: 6 | B41: Repair and Maintenance of panelled doors and windows in all aspects | N41: 8227
B42: Chapter. 11 Item No. 23 (b ii)
A43: 7 | B43: Distempering on new surface. Three Coats
B44: Walls 2 side | C44: 2 | D44: 4 | E44: 12 | F44: x | G44: 10 | H44: = | I44: =D44*E44*G44*C44 -> 960 | J44: Sft.
B45: Ceiling | D45: 1 | E45: 12 | F45: x | G45: 15 | H45: = | I45: =D45*E45*G45 -> 180 | J45: Sft.
G46: Total: | I46: =SUM(I44:I45) -> 1140 | J46: Sft.
B47: Net: | D47: =I46 -> 1140 | E47: - | F47: 51 | G47: = | H47: =D47-F47 -> 1089 | I47: Sft. | K47: =H47 -> 1089 | L47: %Sq.ft. | M47: =(692.4+905.35)/100 -> 15.9775 | N47: =ROUND(M47*K47/100,0) -> 174
B48: Chapter. 10 Item No. 46 A(i)
A49: 8 | B49: Providing and laying superb quality Porcelain glazed tiles of Master brand, skirting/dado of specified size, Color and Shade with adhesive/ bond over 1/2"thick (1:2) cement plaster i/c the cost of and sealer for finishing the joints, cutting grinding complete in all respect as approved and directed by the Engineer Incharge.
B50: Area
B51: 1 | C51: x | D51: 12 | E51: x | F51: 12 | G51: = | H51: =B51*D51*F51 -> 144 | I51: Sft.
B52: 1 | C52: x | D52: 12 | E52: x | F52: 5 | G52: = | H52: =B52*D52*F52 -> 60 | I52: Sft.
G53: Total: | H53: =SUM(H50:H52) -> 204 | I53: Sft. | K53: 50 | L53: P Sft. | M53: 386.35 | N53: =ROUND(M53*K53/1,0) -> 19318
A54: CIVIL ROOM | M54: Total :- | N54: =SUM(N8:N53) -> 71461.12
A59: Assistant Manager (P&MC) - CZ | I59: Deputy Manager (P&MC) - CZ
A60: Punjab Aab-e-Pak Authority | I60: Punjab Aab-e-Pak Authority

Sheet IW
A1: =WB!A1 -> PUNJAB SAAF PANI AUTHORITY
A2: =WB!A2 -> REHABILITATION & O&M OF DYSFUNCTIONAL WATER FILTRATION PLANTS INSTALLED IN DIVISON FAISALABAD
A3: =WB!A3 -> BILL OF QUANTITY
A4: Bill No 13: Injection Well
A5: Sr. No. | B5: MRS | C5: Description | D5: Unit | E5: Qty | F5: Rate | G5: Total Amount (Rs)
A6: 1 | B6: N.S | C6: Boring of tubewell with 350 ft dept, along with casing Pipe (PVC Class B - 4" i/d), discharge Pipe (PVC class B - 1.5" i/d), reinforced cement concrete in retaining/Shear walls and etc complete in all respect | D6: Job | E6: 1
A7: Total

Sheet PF F
A1: =IW!A1 -> PUNJAB SAAF PANI AUTHORITY
A2: =IW!A2 -> REHABILITATION & O&M OF DYSFUNCTIONAL WATER FILTRATION PLANTS INSTALLED IN DIVISON FAISALABAD
A3: =IW!A3 -> BILL OF QUANTITY
A4: Bill No. 14 : Rehabilitation of Pre Fabrication Room
A5: MRS, 1ST BI-ANNUAL-2025 (01.01.2025 to 30.06.2025) FSD
A6: Sr # | B6: Item # | C6: Description | D6: Unit | E6: Quantity | F6: Rate | G6: Amount
F7: Rs | G7: Rs.
A8: 1 | B8: =+'[72]Detail '!B6 -> 4/50. | C8: =+'[72]Detail '!C6 -> Dismantling glazed or encaustic tiles, etc. | D8: %Sft | E8: 0.9
A9: =+A8+1 -> 2 | B9: =+'[72]Detail '!B11 -> 7/5-i. | C9: =+'[72]Detail '!C11 -> Pacca brick work in ground floor:- i) cement, sand mortar:- Ratio 1:4 | D9: % Cft | E9: 0.2
A10: =+A9+1 -> 3 | B10: =+'[72]Detail '!B16 -> 11/9-b. | C10: =+'[72]Detail '!C16 -> Cement plaster 1:4 upto 20' (6.00 m) height:- b) ½" (13 mm) thick | D10: % Sft | E10: 0.71
A11: =+A10+1 -> 4 | B11: =+'[72]Detail '!B23 -> 10/24-i. | C11: =+'[72]Detail '!C23 -> Providing and laying superb quality Ceramic tile floors of Master/Stile brand or approved equivalent manufacturer of specified size, Glossy/Matt/Texture of approved Color and Shade as per approved design with adhesive bond, over3/4" thick (1;2) cement sand plaster i/c the cost of sealer for finishing the joints i/c cutting grinding complete in all respects and as approved and directed by the Engineer Incharge. i) 12"x18"/12"x24"/10"x24"/8"x24" /12"x36" | D11: Sft | E11: 222.25
A12: =+A11+1 -> 5 | B12: =+'[72]Detail '!B28 -> 10/25-i. | C12: =+'[72]Detail '!C28 -> Providing and laying superb quality Ceramic dado floors of Master/Stile brand or approved equivalent manufacturer of specified size, Glossy/Matt/Texture of approved Color and Shade as per approved design with adhesive bond, over3/4" thick (1;2) cement sand plaster i/c the cost of sealer for finishing the joints i/c cutting grinding complete in all respects and as approved and directed by the Engineer Incharge. i) 12"x18"/12"x24"/10"x24"/8"x24" /12"x36" | D12: Sft | E12: 43
A13: =+A12+1 -> 6 | B13: =+'[72]Detail '!B32 -> 13/4a-i+ii. | C13: =+'[72]Detail '!C32 -> Painting old surfaces:- a) Painting corrugated surfaces, patent roofing, etc. with oil Paint. i) first coat ii) two subsequent Coats | D13: %Sft | E13: 25.26
A14: =+A13+1 -> 7 | B14: =+'[72]Detail '!B42 -> 13/4d-i+ii. | C14: =+'[72]Detail '!C42 -> Painting guard bars, gates of iron bars, gratings, railing (including standards, braces etc.) and similar open work: i) first coat ii) two subsequent Coats | D14: %Sft | E14: 16.2
A15: =+A14+1 -> 8 | B15: =+'[72]Detail '!B48 -> 25/10 +11. | C15: =+'[72]Detail '!C48 -> Fabrication of heavy steel work, with angle, tees, flat iron round iron and sheet iron for making trusses, girders, tanks, etc., including cutting, drilling, revitting, handling, assembling and fixing, but excluding erection in position. | D15: %Kgs | E15: 1.96
A16: =+A15+1 -> 9 | B16: =+'[72]Detail '!B57 -> 19/27-i | C16: =+'[72]Detail '!C57 -> Providing and fixing chromium plated bib cock: i) 2 cm (¾") | D16: Each | E16: 7
A17: =+A16+1 -> 10 | B17: =+'[72]Detail '!B60 -> 26/49-iii | C17: =+'[72]Detail '!C60 -> Providing and fixing slip joint sandwich panels composed of two steel layers injected in between with polyurethane foam on existing surface, light weight of specified density and fire resistance grade-B. The steel sheet layers are polyester coated hot dipped galvanized, sandwich sheets panels are painted with reflective, anti dust and durable electrostatic paint from both sides i/c the cost of flashing trims, screws, revits, sealants, tapes etc. complete in all respects as approved and directed by the Engineer Incharge. (iii) 75 mm thick | D17: Sft | E17: 64
A18: =+A17+1 -> 11 | B18: =+'[72]Detail '!B63 -> 24/3-iii | C18: =+'[72]Detail '!C63 -> Supply and erection of PVC pipe for wiring recessed in walls, including inspection boxes, pull boxes, hooks, cutting jharries, and repairing surface, etc., complete with all specials. iii) 25 mm i/d | D18: P.Rft | E18: 40
A19: =+A18+1 -> 12 | B19: =+'[72]Detail '!B66 -> 24/11-i | C19: =+'[72]Detail '!C66 -> Supply and erection of single core PVC insulated copper conductor cables, in prelaid PVC pipe/M.S. conduit/G.I pipe/wooden strip batten/wooden casing an capping/G.I. wire/trenches (rate for cables only): 250/440 volts, PVC insulated: i) 3/0.74 mm (3/0.029") | D19: P.Rft | E19: 70
A20: =+A19+1 -> 13 | B20: =+'[72]Detail '!B69 -> 24/11-iii | C20: =+'[72]Detail '!C69 -> Supply and erection of single core PVC insulated copper conductor cables, in prelaid PVC pipe/M.S. conduit/G.I pipe/wooden strip batten/wooden casing an capping/G.I. wire/trenches (rate for cables only): 250/440 volts, PVC insulated: iii) 7/0.74 mm (7/0.029") | D20: P.Rft | E20: 60
A21: =+A20+1 -> 14 | B21: =+'[72]Detail '!B72 -> 24/108b-iii | C21: =+'[72]Detail '!C72 -> P/FPVC doublelayer Switch kit Face plate with specified switch holes i/c the costof switches/ sockets/ dimmer made of Legrand/ABB/Schenider or approved equvilent manufacturer, screw complete in all respect, as approved and directed by the Engineer Incharge b) One way Gange Switch (Large) iii) 06 Gange | D21: Each | E21: 1
A22: =+A21+1 -> 15 | B22: =+'[72]Detail '!B75 -> 24/105b-ii | C22: =+'[72]Detail '!C75 -> Providing and fixing Pakistan Energy Label NEECA approved Copper winded Exaust Fan i/c the cost of necessary cable and hardware for connection from ceiling rose complete asapproved and directed by Engineer Incharge. ) b)Steel body 18" Sweep | D22: Each | E22: 1
A23: =+A22+1 -> 16 | B23: NS | C23: =+'[72]Detail '!C78 -> Batten light 18 Watt | D23: Each | E23: 5 | H23: =1900*1.18 -> 2242 | I23: =+H23*1.3 -> 2914.6
A24: TOTAL

Sheet C FSD
A1: ='PF F'!A1:G1 -> PUNJAB SAAF PANI AUTHORITY
A2: ='PF F'!A2:G2 -> REHABILITATION & O&M OF DYSFUNCTIONAL WATER FILTRATION PLANTS INSTALLED IN DIVISON FAISALABAD
A3: ='PF F'!A3:G3 -> BILL OF QUANTITY
A4: Bill No 15: Rehabilitation of Civil Work
A5: MRS, 1ST BI-ANNUAL-2025 (01.01.2025 to 30.06.2025) DISTRICT FAISLABAD
A6: Sr No. | B6: MRS | C6: Description | E6: Nos | H6: Measurements | K6: Quantity | M6: Rate | N6: Amount (Rs)
H7: Length | I7: Breadth | J7: Height
A8: 1 | B8: 7/5 i | C8: Pacca brick work in ground floor:- Ratio (1:5) | K8: =SUM(K10:K10) -> 1.1286072 | L8: Cum
B10: 7/5 i | C10: Dispenser Platform | E10: 1 | F10: x | G10: 1 | H10: =3.658+0.229+0.229 -> 4.116 | I10: 0.914 | J10: 0.3 | K10: =PRODUCT(E10:J10) -> 1.1286072 | L10: Cum
J11: Total
A13: 2 | B13: 11/9-b | C13: Cement plaster (1:4) upto 20'-0" hight ½" thick | K13: =SUM(K14:K17) -> 57.38796 | L13: Sqm
C14: Room Outer Side | E14: 1 | F14: x | G14: 4 | H14: 4.116 | J14: 3.15 | K14: =PRODUCT(E14:J14) -> 51.8616 | L14: Sqm
C15: =+C10 -> Dispenser Platform | E15: 1 | F15: x | G15: 1 | H15: 4.116 | J15: 0.91 | K15: =PRODUCT(E15:J15) -> 3.74556 | L15: Sqm
E16: 1 | F16: x | G16: 1 | H16: 4.116 | J16: 0.3 | K16: =PRODUCT(E16:J16) -> 1.2348 | L16: Sqm
E17: 1 | F17: x | G17: 2 | H17: 0.91 | J17: 0.3 | K17: =PRODUCT(E17:J17) -> 0.546 | L17: Sqm
J18: Total
A20: 3 | B20: 7/37 i | C20: Providing and laying fair face Gutka cladding laid in(1:2)cement / red posso mortar having 1/4" thick groove finishing/c cost of 8SWGwirein shape of 8 placed horizontally and vertically at 36" and 18" c/c respectively i/c cutting charges as per approved drawing, complete in all respect as approved and directed by the Engineer Incharge. i. 2-1/4" x 2-1/4" x 9" | K20: =SUM(K21:K22) -> 25.9308 | L20: Sqm
C21: Back Wall | E21: 0.5 | F21: x | G21: 4 | H21: =+H14 -> 4.116 | J21: =+J14 -> 3.15 | K21: =PRODUCT(E21:J21) -> 25.9308 | L21: Sqm
J23: Total
A25: 4 | B25: 4-50 | C25: Dismantling glazed or encaustic tiles, etc. | K25: 20.745 | L25: Sqm
A26: 5 | B26: 10-24i | C26: Providing and laying superb quality Ceramic tile floors of Master/Stile brand or approved equivalent manufacturer of specified size,Glossy/Matt/Texture of approved Color and Shade as per approved design with adhesive bond, over 3/4" thick (1;2) cement sand plaster i/c the cost of sealer for finishing the joints i/c cutting grinding complete in all respects and as approved and directed by the Engineer Incharge. | K26: =SUM(K27:K28) -> 12.51264 | L26: Sqm
E27: 1 | F27: x | G27: 1 | H27: =3.658+0.229+0.229 -> 4.116 | I27: 3.04 | K27: =PRODUCT(E27:J27) -> 12.51264 | L27: Sqm
C29: 10-24 i | J29: Total
A30: 6 | B30: 10-25 i | C30: Providing and laying superb quality Ceramic tile dado of Master/Stile brand or approved equivalent manufacturer of specified size,Glossy/Matt/Texture of approved Color and Shade as per approved design with adhesive bond, over 1/2" thick (1;2) cement sand plaster i/c the cost of sealer for finishing the joints i/c cutting grinding complete in all respects and as approved and directed by the Engineer Incharge. | K30: =SUM(K31:K31) -> 8.232 | L30: Sqm
E31: 1 | F31: x | G31: 1 | H31: 4.116 | I31: 2 | K31: =PRODUCT(E31:J31) -> 8.232 | L31: Sqm
J32: Total
A34: 7 | B34: 11/ 22+23-b | C34: Distempering new surface 3coats Quantity as Ceiling, Internal & External Plaster | K34: =SUM(K35:K35) -> 51.8616 | L34: Sqm
E35: 1 | F35: x | G35: 1 | H35: =+K14 -> 51.8616 | K35: =PRODUCT(E35:J35) -> 51.8616 | L35: Sqm
J36: Total
A38: 8 | B38: 9/20a | C38: Cast iron rain water downpipe fixed in position, excluding heads and shoes, but including painting and clamps, etc:- | K38: =SUM(K39:K39) -> 4 | L38: M
C39: Roof | E39: 1 | F39: x | G39: 1 | H39: 4 | K39: =PRODUCT(E39:J39) -> 4
J40: Total
A42: 9 | B42: 9/21 | C42: Rain water down pipe cast iron head fixed in place, including cost of clamp holdfast and painting | K42: =SUM(K43:K43) -> 2 | L42: Each
C43: Roof | E43: 1 | F43: x | G43: 2 | K43: =PRODUCT(E43:J43) -> 2
J44: Total
A46: 10 | B46: 9/22 | C46: Shoes, bends or offsets for cast iron rain water down pipe, including fixing and painting. | K46: =SUM(K47:K47) -> 2 | L46: Each
C47: Roof | E47: 1 | F47: x | G47: 2 | K47: =PRODUCT(E47:J47) -> 2
J48: Total
A50: 11 | B50: 25/09. | C50: Small iron work, such as gusset plates, knees, bends, stirrups, straps, rings, etc. including cutting, drilling, riveting, handling, assembling and fixing; but excluding erection in position. | K50: =SUM(K51:K51) -> 300 | L50: Kg
E51: 1 | F51: x | G51: 1 | H51: 300 | I51: Kg | K51: 300
J52: Total
A54: 12 | B54: 25/32 | C54: Making and fixing grating in opening, including fixing at site with flat iron 2"x3/8" (50x10 mm) and ¾" (19 mm) square bars, at 4" (100 mm) centre to centre. | K54: =SUM(K54:K55) -> 1.4172 | L54: Sqm
E55: 1 | F55: x | G55: 1 | H55: 4.724 | I55: 0.3 | K55: =PRODUCT(E55:J55) -> 1.4172
J56: Total
A58: 13 | B58: 13/5 d i & ii | C58: Painting new surface:-Preparing surface and painting guard bars, gates of iron bars, gratings, railing (including standards braces, etc.) and in similar open work Three Coats including priming coat. | K58: =SUM(K59:K60) -> 20.724 | L58: Sqm
C59: Grating | E59: 1 | F59: x | G59: 2 | H59: 4.724 | I59: 0.5 | K59: =PRODUCT(E59:J59) -> 4.724
C60: M.S Fence | E60: 2 | F60: x | G60: 2 | H60: 4 | I60: 1 | K60: =PRODUCT(E60:J60) -> 16
J61: Total
A65: 14 | B65: 23/47 a iii & iv | C65: Providing, laying, testing and commissioning of POLYPROPYLENE RANDOM COPOLYMER (PPRC) water supplypipe(Dadex /Popular/Beta or approved equivalent manufacturer, with specified pressure rating PN (PRESSURENOMINAL) and conforming to DIN8077-8078 code i/c cost of solvent,specials,making jharries complete in all respectas approved and directed by Engineer Incharge. (Internal/External Diameters mentioned). a) PN-16 pipe
C66: PPRC Pipe 40 mm dia | E66: 1 | F66: x | G66: 1 | H66: 15 | K66: =PRODUCT(E66:J66) -> 15 | L66: M
C67: PPRC Pipe 32 mm dia | E67: 1 | F67: x | G67: 1 | H67: 10 | K67: =PRODUCT(E67:J67) -> 10 | L67: M
A69: 15 | B69: 23/42 c 7 | C69: Providing, laying, cutting, jointing, testing and disinfecting High Density Polyethylene Pipe (HDPE-100) working presure pipe in trenches. complete in all respects:- 3" (90mm) PN-10 (SDR-17) | K69: =SUM(K70) -> 10 | L69: M
E70: 1 | F70: x | G70: 1 | H70: 10 | K70: =PRODUCT(E70:J70) -> 10
J71: Total
A74: 16 | B74: 19/27 | C74: Providing and fixing chromium plated bib cock:- ii) 1.5 cm (1/2"). | K74: 6 | L74: Each
J75: Total | K75: =SUM(K74:K74) -> 6 | L75: Each
A77: 17 | B77: 19/8-iii Rep | C77: Providing and fixing brass ball float valve:- 2.5 cm (1") dia | K77: 2 | L77: Each
J78: Total | K78: =SUM(K77:K77) -> 2 | L78: Each
A80: 18 | B80: 23/26 b | C80: Providing, laying, cutting, jointing, testing and disinfecting P.V.C. pipe line with `B' Class working pressure pipe, in trenches, complete in all respects 4" i/d (100 mm):- as per drawing, specifications and approval of the Engineer. | K80: =SUM(K81:K81) -> 7 | L80: M
E81: 1 | F81: x | G81: 1 | H81: 7 | K81: =PRODUCT(E81:J81) -> 7
J82: Total
A83: 19 | B83: 11/31. | C83: Extra cost of labour and material for red oxide pigment in cement pointing to match with the colour of bricks. | K83: =SUM(K84:K84) -> 25.9308 | L83: Sqm
K84: =K20 -> 25.9308
C85: 11/31. | J85: Total
A86: 20 | B86: 26/46-i | C86: Supply and Erection of 10 ft high Cantilever type Car Parking Shed consisting of 3mm thick fiber glass sheet roof fixed/ riveted with molded curved frame comprising of 1-1/2"x1-1/2"16-SWG MS box placed @2ft C/C both side sand1-1/2"x3"M.Sbox16-SWG at front and back side welded on cantilever arch type MS pipe 3"dia arms welded with 3/8" thick and 8"dia Main Post duly welded with 1/2" thick 1.5'x1.5' base plate and 4 no stiffeners of 1/2" thick MS sheet embedded in PCC 2'x2'x3'with18" long nut bolts1" dia i/c cost of foundation, cutting straightening assembling, bending as per drawing, welding/grinding of joints and painting three coats complete in all respect as approved by the Engineer Incharge. (i) One side Cantilever | K86: =SUM(K87:K87) -> 9 | L86: Sqm
E87: 1 | F87: x | G87: 1 | H87: 3 | I87: 3 | K87: =PRODUCT(E87:J87) -> 9
A88: 21 | B88: NS | C88: Branding of PSPA | K88: 1 | L88: Job
A89: 22 | B89: NS | C89: Repair of Doors and Windows along with installation of Neon Lights | K89: 1 | L89: Job
A90: 23 | B90: 24/3 ii) & iii) | C90: Supply and erection of PVC pipe for wiring recessed in walls, floors, roofs including inspection boxes, pull boxes, hooks, cutting jharries, and repairing surface, etc., complete with all specials. i) 20 mm | K90: 41.2 | L90: Ft
C91: ii) 25 mm | K91: 16.1 | L91: Ft
A92: 24 | B92: 24/14-a v) | C92: Supply and erection of PVC insulated, PVC sheathed twin core, 250/440 volts copper conductor cables for service connection, in prelaid pipe/G.I. wire/trenches, etc. (rate for cable only):- i) 7/0.044" | K92: 23.4 | L92: Ft
A93: 25 | B93: 24/11 i), ii), iii) & vi) | C93: Supply and erection of single core PVC insulated, PVC sheathed copper conductor, 250/440 volts grade cable (BSS-2004), in prelaid PVC pipes/M.S. conduit/G.I. pipe/wooden strip batten/wooden casing and capping/trenches, etc. (rate for cable only):- i) 3/0.029" | K93: 52.4 | L93: Ft
C94: ii) 3/0.036" | K94: 54.5 | L94: Ft
C95: iii) 7/0.029" | K95: 35.4 | L95: Ft
C96: vi) 7/0.064" | K96: 9.8 | L96: Ft
A97: 26 | B97: N.S | C97: Supply and installation of 4" deep u-PVC concealed switch box for recessed wiring, including making holes for regulators, switches, plugs, etc. | K97: 2 | L97: No.
A98: 27 | B98: 24/44 i) | C98: Supply and erection of button holder (bakelite large size). | K98: 2 | L98: No.
A99: 28 | B99: 24/36(ii) | C99: Supply and erection of switches 5 Amp Piano type | K99: 4 | L99: No.
A100: 29 | B100: N.S | C100: Supply and erection of 2 Pin switch with socket. | K100: 1 | L100: No.
A101: 30 | B101: 24/105a(i) | C101: Providing and fixing Copper winded Exhaust fan with louver and shutter made of Pak/Younas/G.F.C. i/c the cost of necessary cable and hardware for connection from ceiling rose complete as approved and directed by Engineer Incharge. Plastic body 10" dia | K101: 1 | L101: No.
A102: TOTAL

Sheet C F
A1: ='[73]Gran Sum'!A1:E1 -> PUNJAB SAAF PANI AUTHORITY
A2: =[74]WB!A1:F1 -> REHABILITATION & O&M OF DYSFUNCTIONAL WATER FILTRATION PLANTS INSTALLED IN DIVISON FAISLABAD
A3: ='[73]Gran Sum'!A4:E4 -> ENGINEERING COST ESTIMATE
A4: Bill No 15: Rehabilitation of Civil Work
A5: 1st BI-Annual 2025 FSD
A6: Item No | B6: Description | D6: Nos | G6: Measurements | J6: Quantity | L6: Rate | N6: Amount (Rs)
G7: Length | H7: Breadth | I7: Height
A9: 1
A10: =+A9+0.01 -> 1.01 | B10: Pacca brick work in ground floor:- Ratio (1:5)
B12: Dispenser Platform | D12: 1 | E12: x | F12: 1 | G12: =3.658+0.229+0.229 -> 4.116 | H12: 0.914 | I12: 0.3 | J12: =PRODUCT(D12:I12) -> 1.1286072 | K12: Cum
B13: 7/5 i | I13: Total | J13: =SUM(J12:J12) -> 1.1286072 | K13: Cum | L13: 13455.1 | M13: Cum | N13: =J13*L13 -> 15185.523
A15: =+A10+0.01 -> 1.02 | B15: Cement plaster (1:4) upto 20'-0" hight ½" thick
B16: Room Outer Side | D16: 1 | E16: x | F16: 4 | G16: 4.116 | I16: 3.15 | J16: =PRODUCT(D16:I16) -> 51.8616 | K16: Sqm
B17: =+B12 -> Dispenser Platform | D17: 1 | E17: x | F17: 1 | G17: 4.116 | I17: 0.91 | J17: =PRODUCT(D17:I17) -> 3.74556 | K17: Sqm
D18: 1 | E18: x | F18: 1 | G18: 4.116 | I18: 0.3 | J18: =PRODUCT(D18:I18) -> 1.2348 | K18: Sqm
D19: 1 | E19: x | F19: 2 | G19: 0.91 | I19: 0.3 | J19: =PRODUCT(D19:I19) -> 0.546 | K19: Sqm
B20: 11/9-b | I20: Total | J20: =SUM(J16:J19) -> 57.38796 | K20: Sqm | L20: 501.5 | M20: Sqm | N20: =J20*L20 -> 28780.062
A22: =+A15+0.01 -> 1.03 | B22: Providing and laying fair face Gutka cladding laid in(1:2)cement / red posso mortar having 1/4" thick groove finishing/c cost of 8SWGwirein shape of 8 placed horizontally and vertically at 36" and 18" c/c respectively i/c cutting charges as per approved drawing, complete in all respect as approved and directed by the Engineer Incharge. i. 2-1/4" x 2-1/4" x 9"
B23: Back Wall | D23: 0.5 | E23: x | F23: 4 | G23: =+G16 -> 4.116 | I23: =+I16 -> 3.15 | J23: =PRODUCT(D23:I23) -> 25.9308 | K23: Sqm | P23: Chp-10/15-e | Q23: Providing and laying topping screed of cement concrete 1:2:4 (2" ( 50mm) thick), including surface finishing and dividing in panels
P24: Chp-11/18-b | Q24: Deep struck pointing (1:2), complete as per drawing and specification.
B25: 7/37 i | I25: Total | J25: =SUM(J23:J24) -> 25.9308 | K25: Sqm | L25: 2813.45 | M25: Sqm | N25: =J25*L25 -> 72955.009
A27: =+A22+0.01 -> 1.04 | B27: Dismantling glazed or encaustic tiles, etc.
D28: 1 | E28: x | F28: 1 | G28: =3.658+0.229+0.229 -> 4.116 | H28: 3.04 | J28: =PRODUCT(D28:I28) -> 12.51264 | K28: Sqm
D29: 1 | E29: x | F29: 1 | G29: 4.116 | H29: 2 | J29: =PRODUCT(D29:I29) -> 8.232 | K29: Sqm
B30: 4-50 | I30: Total | J30: =SUM(J28:J29) -> 20.74464 | K30: Sqm | L30: 372.1 | M30: Sqm | N30: =J30*L30 -> 7719.0805
A31: =+A27+0.01 -> 1.05 | B31: Providing and laying superb quality Ceramic tile floors of Master/Stile brand or approved equivalent manufacturer of specified size,Glossy/Matt/Texture of approved Color and Shade as per approved design with adhesive bond, over 3/4" thick (1;2) cement sand plaster i/c the cost of sealer for finishing the joints i/c cutting grinding complete in all respects and as approved and directed by the Engineer Incharge.
D32: 1 | E32: x | F32: 1 | G32: =3.658+0.229+0.229 -> 4.116 | H32: 3.04 | J32: =PRODUCT(D32:I32) -> 12.51264 | K32: Sqm
B34: 10-24 i | I34: Total | J34: =SUM(J32:J33) -> 12.51264 | K34: Sqm | L34: 3375.35 | M34: Sqm | N34: =J34*L34 -> 42234.539
A35: =A31+0.01 -> 1.06 | B35: Providing and laying superb quality Ceramic tile dado of Master/Stile brand or approved equivalent manufacturer of specified size,Glossy/Matt/Texture of approved Color and Shade as per approved design with adhesive bond, over 1/2" thick (1;2) cement sand plaster i/c the cost of sealer for finishing the joints i/c cutting grinding complete in all respects and as approved and directed by the Engineer Incharge.
D36: 1 | E36: x | F36: 1 | G36: 4.116 | H36: 2 | J36: =PRODUCT(D36:I36) -> 8.232 | K36: Sqm
B37: 10-25 i | I37: Total | J37: =SUM(J36:J36) -> 8.232 | K37: Sqm | L37: 4150.95 | M37: Sqm | N37: =J37*L37 -> 34170.62
A39: =A35+0.01 -> 1.07 | B39: Distempering old surface 3coats
B40: Quantity as Ceiling, Internal & External Plaster | D40: 1 | E40: x | F40: 1 | G40: =+J16 -> 51.8616 | J40: =PRODUCT(D40:I40) -> 51.8616 | K40: Sqm
B41: 11/ 22+23-b | I41: Total | J41: =SUM(J40:J40) -> 51.8616 | K41: Sqm | L41: 211 | M41: Sqm | N41: =J41*L41 -> 10942.798
A43: =+A39+0.01 -> 1.08 | B43: Cast iron rain water downpipe fixed in position, excluding heads and shoes, but including painting and clamps, etc:-
B44: Roof | D44: 1 | E44: x | F44: 1 | G44: 4 | J44: =PRODUCT(D44:I44) -> 4
B45: 9/20a | I45: Total | J45: =SUM(J44:J44) -> 4 | K45: M | L45: 1619.5 | M45: M | N45: =J45*L45 -> 6478
A47: =A43+0.01 -> 1.09 | B47: Rain water down pipe cast iron head fixed in place, including cost of clamp holdfast and painting
B48: Roof | D48: 1 | E48: x | F48: 2 | J48: =PRODUCT(D48:I48) -> 2
B49: 9/21 | I49: Total | J49: =SUM(J48:J48) -> 2 | K49: Each | L49: 1402.45 | M49: P. No | N49: =J49*L49 -> 2804.9
A51: =A47+0.01 -> 1.1 | B51: Shoes, bends or offsets for cast iron rain water down pipe, including fixing and painting.
B52: Roof | D52: 1 | E52: x | F52: 2 | J52: =PRODUCT(D52:I52) -> 2
B53: 9/22 | I53: Total | J53: =SUM(J52:J52) -> 2 | K53: Each | L53: 702.65 | M53: P. No | N53: =J53*L53 -> 1405.3
A55: =A51+0.01 -> 1.11 | B55: Small iron work, such as gusset plates, knees, bends, stirrups, straps, rings, etc. including cutting, drilling, riveting, handling, assembling and fixing; but excluding erection in position.
D56: 1 | E56: x | F56: 1 | G56: 300 | H56: Kg | J56: 300
B57: 25/09. | I57: Total | J57: =SUM(J56:J56) -> 300 | K57: Kg | L57: 493.85 | M57: Kg | N57: =J57*L57 -> 148155
A59: =A55+0.01 -> 1.12 | B59: Making and fixing grating in opening, including fixing at site with flat iron 2"x3/8" (50x10 mm) and ¾" (19 mm) square bars, at 4" (100 mm) centre to centre.
D60: 1 | E60: x | F60: 1 | G60: 4.724 | H60: 0.3 | J60: =PRODUCT(D60:I60) -> 1.4172
B61: 25/32 | I61: Total | J61: =SUM(J59:J60) -> 1.4172 | K61: Sqm | L61: 11782.3 | M61: Sqm | N61: =J61*L61 -> 16697.876
A63: =A59+0.01 -> 1.13 | B63: Painting new surface:-Preparing surface and painting guard bars, gates of iron bars, gratings, railing (including standards braces, etc.) and in similar open work Three Coats including priming coat.
B64: Grating | D64: 1 | E64: x | F64: 2 | G64: 4.724 | H64: 0.5 | J64: =PRODUCT(D64:I64) -> 4.724
B65: M.S Fence | D65: 2 | E65: x | F65: 2 | G65: 4 | H65: 1 | J65: =PRODUCT(D65:I65) -> 16
I66: Total | J66: =SUM(J64:J65) -> 20.724 | K66: Sqm | L66: 217.65 | M66: Sqm | N66: =J66*L66 -> 4510.5786
B68: 13/5 d i & ii
A70: =+A63+0.01 -> 1.14 | B70: Providing, laying, testing and commissioning of POLYPROPYLENE RANDOM COPOLYMER (PPRC) water supplypipe(Dadex /Popular/ Beta or approved equivalent manufacturer, withs pecified pressure rating PN (PRESSURENOMINAL) and conforming to DIN8077-8078 code i/c cost of solvent,specials,making jharries complete in all respectas approved and directed by Engineer Incharge. (Internal/External Diameters mentioned). a) PN-16 pipe
B71: PPRC Pipe 40 mm dia | D71: 1 | E71: x | F71: 1 | G71: 15 | J71: =PRODUCT(D71:I71) -> 15 | K71: M | L71: 643.15 | M71: M | N71: =J71*L71 -> 9647.25
B72: PPRC Pipe 32 mm dia | D72: 1 | E72: x | F72: 1 | G72: 10 | J72: =PRODUCT(D72:I72) -> 10 | K72: M | L72: 433.95 | M72: M | N72: =J72*L72 -> 4339.5
B73: 23/47 a iii & iv
A74: =A70+0.01 -> 1.15 | B74: Providing, laying, cutting, jointing, testing and disinfecting High Density Polyethylene Pipe (HDPE-100) working presure pipe in trenches. complete in all respects:- 3" (90mm) PN-10 (SDR-17)
D75: 1 | E75: x | F75: 1 | G75: 10 | J75: =PRODUCT(D75:I75) -> 10
I76: Total | J76: =SUM(J75) -> 10 | K76: M | L76: 1112.15 | M76: M | N76: =J76*L76 -> 11121.5
B77: 23/42 c 7
A79: =A74+0.01 -> 1.16 | B79: Providing and fixing chromium plated bib cock:- ii) 1.5 cm (1/2"). | J79: 6
B80: 19/27 | I80: Total | J80: =SUM(J79:J79) -> 6 | K80: Each | L80: 1641.4 | M80: Each | N80: =J80*L80 -> 9848.4
A82: =A79+0.01 -> 1.17 | B82: Providing and fixing brass ball float valve:- 2.5 cm (1") dia | J82: 2
B83: 19/8-iii Rep | I83: Total | J83: =SUM(J82:J82) -> 2 | K83: Each | L83: 1479 | M83: Each | N83: =J83*L83 -> 2958
A85: =A82+0.01 -> 1.18 | B85: Providing, laying, cutting, jointing, testing and disinfecting P.V.C. pipe line with `B' Class working pressure pipe, in trenches, complete in all respects 4" i/d (100 mm):- as per drawing, specifications and approval of the Engineer.
D86: 1 | E86: x | F86: 1 | G86: 7 | J86: =PRODUCT(D86:I86) -> 7
B87: 23/26 b | I87: Total | J87: =SUM(J86:J86) -> 7 | K87: M | L87: 1689.9 | M87: M | N87: =J87*L87 -> 11829.3
A88: =A85+0.01 -> 1.19 | B88: Extra cost of labour and material for red oxide pigment in cement pointing to match with the colour of bricks.
J89: =J25 -> 25.9308
B90: 11/31. | I90: Total | J90: =SUM(J89:J89) -> 25.9308 | K90: Sqm | L90: 115.7 | M90: Sqm | N90: =J90*L90 -> 3000.1936
A92: =+A88+0.01 -> 1.2 | B92: Supply and Erection of 10 ft high Cantilever type Car Parking Shed consisting of 3mm thick fiber glass sheet roof fixed/ riveted with molded curved frame comprising of 1-1/2"x1-1/2"16-SWG MS box placed @2ft C/C both side sand1-1/2"x3"M.Sbox16-SWG at front and back side welded on cantilever arch type MS pipe 3"dia arms welded with 3/8" thick and 8"dia Main Post duly welded with 1/2" thick 1.5'x1.5' base plate and 4 no stiffeners of 1/2" thick MS sheet embedded in PCC 2'x2'x3'with18" long nut bolts1" dia i/c cost of foundation, cutting straightening assembling, bending as per drawing, welding/grinding of joints and painting three coats complete in all respect as approved by the Engineer Incharge. (i) One side Cantilever
D93: 1 | E93: x | F93: 1 | G93: 3 | H93: 3 | J93: =PRODUCT(D93:I93) -> 9
B94: 26/46-i | I94: Total | J94: =SUM(J93:J93) -> 9 | K94: Sqm | L94: 10448.75 | M94: Sqm | N94: =J94*L94 -> 94038.75
A95: 1.2 | B95: Branding of PSPA | J95: 1 | K95: Job | L95: 10000 | M95: Job | N95: =L95*J95 -> 10000
A96: 1.21 | B96: Repair of Doors and Windows along with installation of Neon Lights | J96: 1 | K96: Job | L96: 15031 | M96: Job | N96: =L96*J96 -> 15031
A97: 1.22 | B97: Supply and erection of PVC pipe for wiring recessed in walls, floors, roofs including inspection boxes, pull boxes, hooks, cutting jharries, and repairing surface, etc., complete with all specials. i) 20 mm | J97: 41.2 | K97: Ft | L97: 114.25 | M97: Ft | N97: =L97*J97 -> 4707.1
B98: ii) 25 mm | J98: 16.1 | K98: Ft | L98: 135.85 | M98: Ft | N98: =L98*J98 -> 2187.185
B99: 24/3 ii) & iii)
A100: 1.23 | B100: Supply and erection of PVC insulated, PVC sheathed twin core, 250/440 volts copper conductor cables for service connection, in prelaid pipe/G.I. wire/trenches, etc. (rate for cable only):- i) 7/0.044" | J100: 23.4 | K100: Ft | L100: 237.9 | M100: Ft | N100: =L100*J100 -> 5566.86
B101: 24/14-a v)
A102: 1.24 | B102: Supply and erection of single core PVC insulated, PVC sheathed copper conductor, 250/440 volts grade cable (BSS-2004), in prelaid PVC pipes/M.S. conduit/G.I. pipe/wooden strip batten/wooden casing and capping/trenches, etc. (rate for cable only):- i) 3/0.029" | J102: 52.4 | K102: Ft | L102: 35.9 | M102: Ft | N102: =L102*J102 -> 1881.16
B103: ii) 3/0.036" | J103: 54.5 | K103: Ft | L103: 36.3 | M103: Ft | N103: =L103*J103 -> 1978.35
B104: iii) 7/0.029" | J104: 35.4 | K104: Ft | L104: 56.5 | M104: Ft | N104: =L104*J104 -> 2000.1
B105: vi) 7/0.064" | J105: 9.8 | K105: Ft | L105: 269 | M105: Ft | N105: =L105*J105 -> 2636.2
B106: 24/11 i), ii), iii) & vi)
A107: 1.25 | B107: Supply and installation of 4" deep u-PVC concealed switch box for recessed wiring, including making holes for regulators, switches, plugs, etc. | J107: 2 | K107: No. | L107: 50 | M107: No. | N107: =L107*J107 -> 100
A108: 1.26 | B108: Supply and erection of button holder (bakelite large size). | J108: 2 | K108: No. | L108: 79.75 | M108: No. | N108: =L108*J108 -> 159.5
B109: 24/44 i)
A110: 1.27 | B110: Supply and erection of switches 5 Amp Piano type | C110: Supply and erection of switches 5 Amp Piano type | D110: Supply and erection of switches 5 Amp Piano type | E110: Supply and erection of switches 5 Amp Piano type | F110: Supply and erection of switches 5 Amp Piano type | G110: Supply and erection of switches 5 Amp Piano type | H110: Supply and erection of switches 5 Amp Piano type | I110: Supply and erection of switches 5 Amp Piano type | J110: 4 | K110: No. | L110: 104.05 | M110: No. | N110: =L110*J110 -> 416.2
B111: 24/36(ii)
A112: 1.28 | B112: Supply and erection of 2 Pin switch with socket. | J112: 1 | K112: No. | L112: 500 | M112: No. | N112: =L112*J112 -> 500
A113: 1.29 | B113: Providing and fixing Copper winded Exhaust fan with louver and shutter made of Pak/Younas/G.F.C. i/c the cost of necessary cable and hardware for connection from ceiling rose complete as approved and directed by Engineer Incharge. Plastic body 10" dia | J113: 1 | K113: No. | L113: 5568.1 | M113: No. | N113: =L113*J113 -> 5568.1
B114: 24/105a(i)
M115: TOTAL COST OF WATER TREATMENT PLANT = | N115: =SUM(N9:N114) -> 591553.93
A118: Assistant Manager (P&MC) - CZ | I118: Deputy Manager (P&MC) - CZ
A119: Punjab Saaf Pani Authority | I119: Punjab Saaf Pani Authority

Sheet C CHI
A1: ='PF F'!A1:G1 -> PUNJAB SAAF PANI AUTHORITY
A2: ='PF F'!A2:G2 -> REHABILITATION & O&M OF DYSFUNCTIONAL WATER FILTRATION PLANTS INSTALLED IN DIVISON FAISALABAD
A3: ='PF F'!A3:G3 -> BILL OF QUANTITY
A4: Bill No 16: Rehabilitation of Civil Work
A5: MRS, 1ST BI-ANNUAL-2025 (01.01.2025 to 30.06.2025) DISTRICT CHINIOT
A6: Sr No. | B6: MRS | C6: Description | E6: Nos | H6: Measurements | K6: Quantity | M6: Rate | N6: Amount (Rs)
H7: Length | I7: Breadth | J7: Height
A8: 1 | B8: 7/5 i | C8: Pacca brick work in ground floor:- Ratio (1:5) | K8: =SUM(K10:K10) -> 1.1286072 | L8: Cum
B10: 7/5 i | C10: Dispenser Platform | E10: 1 | F10: x | G10: 1 | H10: =3.658+0.229+0.229 -> 4.116 | I10: 0.914 | J10: 0.3 | K10: =PRODUCT(E10:J10) -> 1.1286072 | L10: Cum
J11: Total
A13: 2 | B13: 11/9-b | C13: Cement plaster (1:4) upto 20'-0" hight ½" thick | K13: =SUM(K14:K17) -> 57.38796 | L13: Sqm
C14: Room Outer Side | E14: 1 | F14: x | G14: 4 | H14: 4.116 | J14: 3.15 | K14: =PRODUCT(E14:J14) -> 51.8616 | L14: Sqm
C15: =+C10 -> Dispenser Platform | E15: 1 | F15: x | G15: 1 | H15: 4.116 | J15: 0.91 | K15: =PRODUCT(E15:J15) -> 3.74556 | L15: Sqm
E16: 1 | F16: x | G16: 1 | H16: 4.116 | J16: 0.3 | K16: =PRODUCT(E16:J16) -> 1.2348 | L16: Sqm
E17: 1 | F17: x | G17: 2 | H17: 0.91 | J17: 0.3 | K17: =PRODUCT(E17:J17) -> 0.546 | L17: Sqm
J18: Total
A20: 3 | B20: 7/37 i | C20: Providing and laying fair face Gutka cladding laid in(1:2)cement / red posso mortar having 1/4" thick groove finishing/c cost of 8SWGwirein shape of 8 placed horizontally and vertically at 36" and 18" c/c respectively i/c cutting charges as per approved drawing, complete in all respect as approved and directed by the Engineer Incharge. i. 2-1/4" x 2-1/4" x 9" | K20: =SUM(K21:K22) -> 25.9308 | L20: Sqm
C21: Back Wall | E21: 0.5 | F21: x | G21: 4 | H21: =+H14 -> 4.116 | J21: =+J14 -> 3.15 | K21: =PRODUCT(E21:J21) -> 25.9308 | L21: Sqm
J23: Total
A25: 4 | B25: 4-50 | C25: Dismantling glazed or encaustic tiles, etc. | K25: 20.745 | L25: Sqm
A26: 5 | B26: 10-24i | C26: Providing and laying superb quality Ceramic tile floors of Master/Stile brand or approved equivalent manufacturer of specified size,Glossy/Matt/Texture of approved Color and Shade as per approved design with adhesive bond, over 3/4" thick (1;2) cement sand plaster i/c the cost of sealer for finishing the joints i/c cutting grinding complete in all respects and as approved and directed by the Engineer Incharge. | K26: =SUM(K27:K28) -> 12.51264 | L26: Sqm
E27: 1 | F27: x | G27: 1 | H27: =3.658+0.229+0.229 -> 4.116 | I27: 3.04 | K27: =PRODUCT(E27:J27) -> 12.51264 | L27: Sqm
C29: 10-24 i | J29: Total
A30: 6 | B30: 10-25 i | C30: Providing and laying superb quality Ceramic tile dado of Master/Stile brand or approved equivalent manufacturer of specified size,Glossy/Matt/Texture of approved Color and Shade as per approved design with adhesive bond, over 1/2" thick (1;2) cement sand plaster i/c the cost of sealer for finishing the joints i/c cutting grinding complete in all respects and as approved and directed by the Engineer Incharge. | K30: =SUM(K31:K31) -> 8.232 | L30: Sqm
E31: 1 | F31: x | G31: 1 | H31: 4.116 | I31: 2 | K31: =PRODUCT(E31:J31) -> 8.232 | L31: Sqm
J32: Total
A34: 7 | B34: 11/ 22+23-b | C34: Distempering new surface 3coats Quantity as Ceiling, Internal & External Plaster | K34: =SUM(K35:K35) -> 51.8616 | L34: Sqm
E35: 1 | F35: x | G35: 1 | H35: =+K14 -> 51.8616 | K35: =PRODUCT(E35:J35) -> 51.8616 | L35: Sqm
J36: Total
A38: 8 | B38: 9/20a | C38: Cast iron rain water downpipe fixed in position, excluding heads and shoes, but including painting and clamps, etc:- | K38: =SUM(K39:K39) -> 4 | L38: M
C39: Roof | E39: 1 | F39: x | G39: 1 | H39: 4 | K39: =PRODUCT(E39:J39) -> 4
J40: Total
A42: 9 | B42: 9/21 | C42: Rain water down pipe cast iron head fixed in place, including cost of clamp holdfast and painting | K42: =SUM(K43:K43) -> 2 | L42: Each
C43: Roof | E43: 1 | F43: x | G43: 2 | K43: =PRODUCT(E43:J43) -> 2
J44: Total
A46: 10 | B46: 9/22 | C46: Shoes, bends or offsets for cast iron rain water down pipe, including fixing and painting. | K46: =SUM(K47:K47) -> 2 | L46: Each
C47: Roof | E47: 1 | F47: x | G47: 2 | K47: =PRODUCT(E47:J47) -> 2
J48: Total
A50: 11 | B50: 25/09. | C50: Small iron work, such as gusset plates, knees, bends, stirrups, straps, rings, etc. including cutting, drilling, riveting, handling, assembling and fixing; but excluding erection in position. | K50: =SUM(K51:K51) -> 300 | L50: Kg
E51: 1 | F51: x | G51: 1 | H51: 300 | I51: Kg | K51: 300
J52: Total
A54: 12 | B54: 25/32 | C54: Making and fixing grating in opening, including fixing at site with flat iron 2"x3/8" (50x10 mm) and ¾" (19 mm) square bars, at 4" (100 mm) centre to centre. | K54: =SUM(K54:K55) -> 1.4172 | L54: Sqm
E55: 1 | F55: x | G55: 1 | H55: 4.724 | I55: 0.3 | K55: =PRODUCT(E55:J55) -> 1.4172
J56: Total
A58: 13 | B58: 13/5 d i & ii | C58: Painting new surface:-Preparing surface and painting guard bars, gates of iron bars, gratings, railing (including standards braces, etc.) and in similar open work Three Coats including priming coat. | K58: =SUM(K59:K60) -> 20.724 | L58: Sqm
C59: Grating | E59: 1 | F59: x | G59: 2 | H59: 4.724 | I59: 0.5 | K59: =PRODUCT(E59:J59) -> 4.724
C60: M.S Fence | E60: 2 | F60: x | G60: 2 | H60: 4 | I60: 1 | K60: =PRODUCT(E60:J60) -> 16
J61: Total
A65: 14 | B65: 23/47 a iii & iv | C65: Providing, laying, testing and commissioning of POLYPROPYLENE RANDOM COPOLYMER (PPRC) water supplypipe(Dadex /Popular/Beta or approved equivalent manufacturer, with specified pressure rating PN (PRESSURENOMINAL) and conforming to DIN8077-8078 code i/c cost of solvent,specials,making jharries complete in all respectas approved and directed by Engineer Incharge. (Internal/External Diameters mentioned). a) PN-16 pipe
C66: PPRC Pipe 40 mm dia | E66: 1 | F66: x | G66: 1 | H66: 15 | K66: =PRODUCT(E66:J66) -> 15 | L66: M
C67: PPRC Pipe 32 mm dia | E67: 1 | F67: x | G67: 1 | H67: 10 | K67: =PRODUCT(E67:J67) -> 10 | L67: M
A69: 15 | B69: 23/42 c 7 | C69: Providing, laying, cutting, jointing, testing and disinfecting High Density Polyethylene Pipe (HDPE-100) working presure pipe in trenches. complete in all respects:- 3" (90mm) PN-10 (SDR-17) | K69: =SUM(K70) -> 10 | L69: M
E70: 1 | F70: x | G70: 1 | H70: 10 | K70: =PRODUCT(E70:J70) -> 10
J71: Total
A74: 16 | B74: 19/27 | C74: Providing and fixing chromium plated bib cock:- ii) 1.5 cm (1/2"). | K74: 6 | L74: Each
J75: Total | K75: =SUM(K74:K74) -> 6 | L75: Each
A77: 17 | B77: 19/8-iii Rep | C77: Providing and fixing brass ball float valve:- 2.5 cm (1") dia | K77: 2 | L77: Each
J78: Total | K78: =SUM(K77:K77) -> 2 | L78: Each
A80: 18 | B80: 23/26 b | C80: Providing, laying, cutting, jointing, testing and disinfecting P.V.C. pipe line with `B' Class working pressure pipe, in trenches, complete in all respects 4" i/d (100 mm):- as per drawing, specifications and approval of the Engineer. | K80: =SUM(K81:K81) -> 7 | L80: M
E81: 1 | F81: x | G81: 1 | H81: 7 | K81: =PRODUCT(E81:J81) -> 7
J82: Total
A83: 19 | B83: 11/31. | C83: Extra cost of labour and material for red oxide pigment in cement pointing to match with the colour of bricks. | K83: =SUM(K84:K84) -> 25.9308 | L83: Sqm
K84: =K20 -> 25.9308
C85: 11/31. | J85: Total
A86: 20 | B86: 26/46-i | C86: Supply and Erection of 10 ft high Cantilever type Car Parking Shed consisting of 3mm thick fiber glass sheet roof fixed/ riveted with molded curved frame comprising of 1-1/2"x1-1/2"16-SWG MS box placed @2ft C/C both side sand1-1/2"x3"M.Sbox16-SWG at front and back side welded on cantilever arch type MS pipe 3"dia arms welded with 3/8" thick and 8"dia Main Post duly welded with 1/2" thick 1.5'x1.5' base plate and 4 no stiffeners of 1/2" thick MS sheet embedded in PCC 2'x2'x3'with18" long nut bolts1" dia i/c cost of foundation, cutting straightening assembling, bending as per drawing, welding/grinding of joints and painting three coats complete in all respect as approved by the Engineer Incharge. (i) One side Cantilever | K86: =SUM(K87:K87) -> 9 | L86: Sqm
E87: 1 | F87: x | G87: 1 | H87: 3 | I87: 3 | K87: =PRODUCT(E87:J87) -> 9
A88: 21 | B88: NS | C88: Branding of PSPA | K88: 1 | L88: Job
A89: 22 | B89: NS | C89: Repair of Doors and Windows along with installation of Neon Lights | K89: 1 | L89: Job
A90: 23 | B90: 24/3 ii) & iii) | C90: Supply and erection of PVC pipe for wiring recessed in walls, floors, roofs including inspection boxes, pull boxes, hooks, cutting jharries, and repairing surface, etc., complete with all specials. i) 20 mm | K90: 41.2 | L90: Ft
C91: ii) 25 mm | K91: 16.1 | L91: Ft
A92: 24 | B92: 24/14-a v) | C92: Supply and erection of PVC insulated, PVC sheathed twin core, 250/440 volts copper conductor cables for service connection, in prelaid pipe/G.I. wire/trenches, etc. (rate for cable only):- i) 7/0.044" | K92: 23.4 | L92: Ft
A93: 25 | B93: 24/11 i), ii), iii) & vi) | C93: Supply and erection of single core PVC insulated, PVC sheathed copper conductor, 250/440 volts grade cable (BSS-2004), in prelaid PVC pipes/M.S. conduit/G.I. pipe/wooden strip batten/wooden casing and capping/trenches, etc. (rate for cable only):- i) 3/0.029" | K93: 52.4 | L93: Ft
C94: ii) 3/0.036" | K94: 54.5 | L94: Ft
C95: iii) 7/0.029" | K95: 35.4 | L95: Ft
C96: vi) 7/0.064" | K96: 9.8 | L96: Ft
A97: 26 | B97: N.S | C97: Supply and installation of 4" deep u-PVC concealed switch box for recessed wiring, including making holes for regulators, switches, plugs, etc. | K97: 2 | L97: No.
A98: 27 | B98: 24/44 i) | C98: Supply and erection of button holder (bakelite large size). | K98: 2 | L98: No.
A99: 28 | B99: 24/36(ii) | C99: Supply and erection of switches 5 Amp Piano type | K99: 4 | L99: No.
A100: 29 | B100: N.S | C100: Supply and erection of 2 Pin switch with socket. | K100: 1 | L100: No.
A101: 30 | B101: 24/105a(i) | C101: Providing and fixing Copper winded Exhaust fan with louver and shutter made of Pak/Younas/G.F.C. i/c the cost of necessary cable and hardware for connection from ceiling rose complete as approved and directed by Engineer Incharge. Plastic body 10" dia | K101: 1 | L101: No.
A102: TOTAL

Sheet C JHA
A1: ='PF F'!A1:G1 -> PUNJAB SAAF PANI AUTHORITY
A2: ='PF F'!A2:G2 -> REHABILITATION & O&M OF DYSFUNCTIONAL WATER FILTRATION PLANTS INSTALLED IN DIVISON FAISALABAD
A3: ='PF F'!A3:G3 -> BILL OF QUANTITY
A4: Bill No 17: Rehabilitation of Civil Work
A5: MRS, 1ST BI-ANNUAL-2025 (01.01.2025 to 30.06.2025) DISTRICT JHANG
A6: Sr No. | B6: MRS | C6: Description | E6: Nos | H6: Measurements | K6: Quantity | M6: Rate | N6: Amount (Rs)
H7: Length | I7: Breadth | J7: Height
A8: 1 | B8: 7/5 i | C8: Pacca brick work in ground floor:- Ratio (1:5) | K8: =SUM(K10:K10) -> 1.1286072 | L8: Cum
B10: 7/5 i | C10: Dispenser Platform | E10: 1 | F10: x | G10: 1 | H10: =3.658+0.229+0.229 -> 4.116 | I10: 0.914 | J10: 0.3 | K10: =PRODUCT(E10:J10) -> 1.1286072 | L10: Cum
J11: Total
A13: 2 | B13: 11/9-b | C13: Cement plaster (1:4) upto 20'-0" hight ½" thick | K13: =SUM(K14:K17) -> 57.38796 | L13: Sqm
C14: Room Outer Side | E14: 1 | F14: x | G14: 4 | H14: 4.116 | J14: 3.15 | K14: =PRODUCT(E14:J14) -> 51.8616 | L14: Sqm
C15: =+C10 -> Dispenser Platform | E15: 1 | F15: x | G15: 1 | H15: 4.116 | J15: 0.91 | K15: =PRODUCT(E15:J15) -> 3.74556 | L15: Sqm
E16: 1 | F16: x | G16: 1 | H16: 4.116 | J16: 0.3 | K16: =PRODUCT(E16:J16) -> 1.2348 | L16: Sqm
E17: 1 | F17: x | G17: 2 | H17: 0.91 | J17: 0.3 | K17: =PRODUCT(E17:J17) -> 0.546 | L17: Sqm
J18: Total
A20: 3 | B20: 7/37 i | C20: Providing and laying fair face Gutka cladding laid in(1:2)cement / red posso mortar having 1/4" thick groove finishing/c cost of 8SWGwirein shape of 8 placed horizontally and vertically at 36" and 18" c/c respectively i/c cutting charges as per approved drawing, complete in all respect as approved and directed by the Engineer Incharge. i. 2-1/4" x 2-1/4" x 9" | K20: =SUM(K21:K22) -> 25.9308 | L20: Sqm
C21: Back Wall | E21: 0.5 | F21: x | G21: 4 | H21: =+H14 -> 4.116 | J21: =+J14 -> 3.15 | K21: =PRODUCT(E21:J21) -> 25.9308 | L21: Sqm
J23: Total
A25: 4 | B25: 4-50 | C25: Dismantling glazed or encaustic tiles, etc. | K25: 20.745 | L25: Sqm
A26: 5 | B26: 10-24i | C26: Providing and laying superb quality Ceramic tile floors of Master/Stile brand or approved equivalent manufacturer of specified size,Glossy/Matt/Texture of approved Color and Shade as per approved design with adhesive bond, over 3/4" thick (1;2) cement sand plaster i/c the cost of sealer for finishing the joints i/c cutting grinding complete in all respects and as approved and directed by the Engineer Incharge. | K26: =SUM(K27:K28) -> 12.51264 | L26: Sqm
E27: 1 | F27: x | G27: 1 | H27: =3.658+0.229+0.229 -> 4.116 | I27: 3.04 | K27: =PRODUCT(E27:J27) -> 12.51264 | L27: Sqm
C29: 10-24 i | J29: Total
A30: 6 | B30: 10-25 i | C30: Providing and laying superb quality Ceramic tile dado of Master/Stile brand or approved equivalent manufacturer of specified size,Glossy/Matt/Texture of approved Color and Shade as per approved design with adhesive bond, over 1/2" thick (1;2) cement sand plaster i/c the cost of sealer for finishing the joints i/c cutting grinding complete in all respects and as approved and directed by the Engineer Incharge. | K30: =SUM(K31:K31) -> 8.232 | L30: Sqm
E31: 1 | F31: x | G31: 1 | H31: 4.116 | I31: 2 | K31: =PRODUCT(E31:J31) -> 8.232 | L31: Sqm
J32: Total
A34: 7 | B34: 11/ 22+23-b | C34: Distempering new surface 3coats Quantity as Ceiling, Internal & External Plaster | K34: =SUM(K35:K35) -> 51.8616 | L34: Sqm
E35: 1 | F35: x | G35: 1 | H35: =+K14 -> 51.8616 | K35: =PRODUCT(E35:J35) -> 51.8616 | L35: Sqm
J36: Total
A38: 8 | B38: 9/20a | C38: Cast iron rain water downpipe fixed in position, excluding heads and shoes, but including painting and clamps, etc:- | K38: =SUM(K39:K39) -> 4 | L38: M
C39: Roof | E39: 1 | F39: x | G39: 1 | H39: 4 | K39: =PRODUCT(E39:J39) -> 4
J40: Total
A42: 9 | B42: 9/21 | C42: Rain water down pipe cast iron head fixed in place, including cost of clamp holdfast and painting | K42: =SUM(K43:K43) -> 2 | L42: Each
C43: Roof | E43: 1 | F43: x | G43: 2 | K43: =PRODUCT(E43:J43) -> 2
J44: Total
A46: 10 | B46: 9/22 | C46: Shoes, bends or offsets for cast iron rain water down pipe, including fixing and painting. | K46: =SUM(K47:K47) -> 2 | L46: Each
C47: Roof | E47: 1 | F47: x | G47: 2 | K47: =PRODUCT(E47:J47) -> 2
J48: Total
A50: 11 | B50: 25/09. | C50: Small iron work, such as gusset plates, knees, bends, stirrups, straps, rings, etc. including cutting, drilling, riveting, handling, assembling and fixing; but excluding erection in position. | K50: =SUM(K51:K51) -> 300 | L50: Kg
E51: 1 | F51: x | G51: 1 | H51: 300 | I51: Kg | K51: 300
J52: Total
A54: 12 | B54: 25/32 | C54: Making and fixing grating in opening, including fixing at site with flat iron 2"x3/8" (50x10 mm) and ¾" (19 mm) square bars, at 4" (100 mm) centre to centre. | K54: =SUM(K54:K55) -> 1.4172 | L54: Sqm
E55: 1 | F55: x | G55: 1 | H55: 4.724 | I55: 0.3 | K55: =PRODUCT(E55:J55) -> 1.4172
J56: Total
A58: 13 | B58: 13/5 d i & ii | C58: Painting new surface:-Preparing surface and painting guard bars, gates of iron bars, gratings, railing (including standards braces, etc.) and in similar open work Three Coats including priming coat. | K58: =SUM(K59:K60) -> 20.724 | L58: Sqm
C59: Grating | E59: 1 | F59: x | G59: 2 | H59: 4.724 | I59: 0.5 | K59: =PRODUCT(E59:J59) -> 4.724
C60: M.S Fence | E60: 2 | F60: x | G60: 2 | H60: 4 | I60: 1 | K60: =PRODUCT(E60:J60) -> 16
J61: Total
A65: 14 | B65: 23/47 a iii & iv | C65: Providing, laying, testing and commissioning of POLYPROPYLENE RANDOM COPOLYMER (PPRC) water supplypipe(Dadex /Popular/Beta or approved equivalent manufacturer, with specified pressure rating PN (PRESSURENOMINAL) and conforming to DIN8077-8078 code i/c cost of solvent,specials,making jharries complete in all respectas approved and directed by Engineer Incharge. (Internal/External Diameters mentioned). a) PN-16 pipe
C66: PPRC Pipe 40 mm dia | E66: 1 | F66: x | G66: 1 | H66: 15 | K66: =PRODUCT(E66:J66) -> 15 | L66: M
C67: PPRC Pipe 32 mm dia | E67: 1 | F67: x | G67: 1 | H67: 10 | K67: =PRODUCT(E67:J67) -> 10 | L67: M
A69: 15 | B69: 23/42 c 7 | C69: Providing, laying, cutting, jointing, testing and disinfecting High Density Polyethylene Pipe (HDPE-100) working presure pipe in trenches. complete in all respects:- 3" (90mm) PN-10 (SDR-17) | K69: =SUM(K70) -> 10 | L69: M
E70: 1 | F70: x | G70: 1 | H70: 10 | K70: =PRODUCT(E70:J70) -> 10
J71: Total
A74: 16 | B74: 19/27 | C74: Providing and fixing chromium plated bib cock:- ii) 1.5 cm (1/2"). | K74: 6 | L74: Each
J75: Total | K75: =SUM(K74:K74) -> 6 | L75: Each
A77: 17 | B77: 19/8-iii Rep | C77: Providing and fixing brass ball float valve:- 2.5 cm (1") dia | K77: 2 | L77: Each
J78: Total | K78: =SUM(K77:K77) -> 2 | L78: Each
A80: 18 | B80: 23/26 b | C80: Providing, laying, cutting, jointing, testing and disinfecting P.V.C. pipe line with `B' Class working pressure pipe, in trenches, complete in all respects 4" i/d (100 mm):- as per drawing, specifications and approval of the Engineer. | K80: =SUM(K81:K81) -> 7 | L80: M
E81: 1 | F81: x | G81: 1 | H81: 7 | K81: =PRODUCT(E81:J81) -> 7
J82: Total
A83: 19 | B83: 11/31. | C83: Extra cost of labour and material for red oxide pigment in cement pointing to match with the colour of bricks. | K83: =SUM(K84:K84) -> 25.9308 | L83: Sqm
K84: =K20 -> 25.9308
C85: 11/31. | J85: Total
A86: 20 | B86: 26/46-i | C86: Supply and Erection of 10 ft high Cantilever type Car Parking Shed consisting of 3mm thick fiber glass sheet roof fixed/ riveted with molded curved frame comprising of 1-1/2"x1-1/2"16-SWG MS box placed @2ft C/C both side sand1-1/2"x3"M.Sbox16-SWG at front and back side welded on cantilever arch type MS pipe 3"dia arms welded with 3/8" thick and 8"dia Main Post duly welded with 1/2" thick 1.5'x1.5' base plate and 4 no stiffeners of 1/2" thick MS sheet embedded in PCC 2'x2'x3'with18" long nut bolts1" dia i/c cost of foundation, cutting straightening assembling, bending as per drawing, welding/grinding of joints and painting three coats complete in all respect as approved by the Engineer Incharge. (i) One side Cantilever | K86: =SUM(K87:K87) -> 9 | L86: Sqm
E87: 1 | F87: x | G87: 1 | H87: 3 | I87: 3 | K87: =PRODUCT(E87:J87) -> 9
A88: 21 | B88: NS | C88: Branding of PSPA | K88: 1 | L88: Job
A89: 22 | B89: NS | C89: Repair of Doors and Windows along with installation of Neon Lights | K89: 1 | L89: Job
A90: 23 | B90: 24/3 ii) & iii) | C90: Supply and erection of PVC pipe for wiring recessed in walls, floors, roofs including inspection boxes, pull boxes, hooks, cutting jharries, and repairing surface, etc., complete with all specials. i) 20 mm | K90: 41.2 | L90: Ft
C91: ii) 25 mm | K91: 16.1 | L91: Ft
A92: 24 | B92: 24/14-a v) | C92: Supply and erection of PVC insulated, PVC sheathed twin core, 250/440 volts copper conductor cables for service connection, in prelaid pipe/G.I. wire/trenches, etc. (rate for cable only):- i) 7/0.044" | K92: 23.4 | L92: Ft
